Workbook
Name Lista_Productos: Tabla_Productos[Nombre_Comercial]
Name ListaCategorias: TablaCategorias[Categoria]
Name ListaMateriales: TablaMateriales[Material]
Name ListaSubcategorias: TablaSubcategorias[Subcategoria]

Sheet Configuración
A1: Parámetro | B1: Valor | C1: Descripción
A2: PORC_DESC_CREDITO | B2: 0.2 | C2: Descuento aplicado para calcular 2 y 3 meses (20% del precio a credicontado)
A3: MESES_2_SEMANAS | B3: 8 | C3: Semanas equivalentes a 2 meses
A4: MESES_3_SEMANAS | B4: 12 | C4: Semanas equivalentes a 3 meses
A5: MIN_SEMANAL | B5: 100 | C5: Pago mínimo semanal permitido
A6: REDONDEO_MULT | B6: 10 | C6: Redondeo a múltiplos de (ej. 10 pesos)
A7: LIMITE_2_MESES | B7: 2000 | C7: Si precio crédito es menor a esto, NO aplica 2 meses
A8: LIMITE_3_MESES | B8: 3000 | C8: Si precio crédito es menor a esto, NO aplica 3 meses
A9: MAX_SEMANAS_LARGO | B9: 52 | C9: Máximo de semanas para el abono semanal (largo plazo)
A12: Categoria | B12: Codigo_Categoria | D12: Categoria | E12: Subcategoria | F12: Codigo_Sub | H12: Material | I12: Codigo_Material
A13: Cocina | B13: COC | D13: Cocina | E13: Vaporera | F13: VAP | H13: Alumino | I13: ALU
A14: Mobiliario | B14: MOB | D14: Cocina | E14: Budinera | F14: BUD | H14: Alumino y Teflon | I14: ALUT
A15: Electrodomésticos | B15: ELE | D15: Cocina | E15: Batería | F15: BAT | H15: Acero inoxidable | I15: ACI
A16: Electrónica | B16: ELC | D16: Cocina | E16: Comal | F16: COM | H16: Madera | I16: MAD
A17: Línea blanca | B17: LBL | D17: Cocina | E17: Olla | F17: OLL | H17: Metal | I17: MET
A18: Hogar | B18: HOG | D18: Cocina | E18: Sartén | F18: SAR | H18: Plástico | I18: PSL
A19: Plásticos | B19: PLA | D19: Cocina | E19: Cazo | F19: CAZ | H19: Tubular | I19: TUB
A20: Temporada | B20: TMP | D20: Cocina | E20: Arrocera | F20: ARR | H20: Peltre | I20: PEL
D21: Cocina | E21: Bandejas | F21: BAN | H21: Triple Fuerte | I21: TF
D22: Mobiliario | E22: Mecedora | F22: MEC | H22: Vidrio | I22: VID
D23: Mobiliario | E23: Silla | F23: SIL | H23: Espuma | I23: ESP
D24: Mobiliario | E24: Mesa | F24: MES | H24: Algodón | I24: ALG
D25: Mobiliario | E25: Ropero | F25: ROP
D26: Mobiliario | E26: Cama | F26: CAM
D27: Mobiliario | E27: Litera | F27: LIT
D28: Mobiliario | E28: Comedor | F28: COMD
D29: Mobiliario | E29: Tocador | F29: TOC
D30: Mobiliario | E30: Closet | F30: CLO
D31: Mobiliario | E31: Cajonera | F31: CAJ
D32: Mobiliario | E32: Alacena | F32: ALA
D33: Mobiliario | E33: Banca | F33: BAN
D34: Mobiliario | E34: Reposet | F34: REP
D35: Mobiliario | E35: Sofá | F35: SOF
D36: Mobiliario | E36: Banco | F36: BCO
... D65: Electrónica | E65: Bocina | F65: BOC

Sheet Respuestas de formulario 1
B1: Nombre del producto | C1: Marca | D1: Categoria del producto | E1: Precio a credito | F1: Precio a contado | G1: Precio a 2 meses | H1: Precio a 3 meses | I1: PG semanal a 2 meses | J1: PG semanal a 3 meses | K1: Abono semanal
B2: Vaporera de aluminio 180cm | C2: El abuelo | D2: Cocina | E2: 10900 | F2: 7630 | G2: =IF(I2="NO APLICA","NO APLICA",I2*8) -> 8720 | H2: =IF(J2="NO APLICA","NO APLICA",J2*12) -> 8760 | I2: =IF(E2<2000,"NO APLICA",MAX(CEILING((E2*0.8)/8,10),100)) -> 1090 | J2: =IF(E2<3000,"NO APLICA",MAX(CEILING((E2*0.8)/12,10),100)) -> 730 | K2: =MAX(CEILING(E2/52,10),100) -> 210
B3: Vaporera de aluminio 120cm | C3: El abuelo | D3: Cocina | E3: 5000 | F3: 3500 | G3: =IF(I3="NO APLICA","NO APLICA",I3*8) -> 4000 | H3: =IF(J3="NO APLICA","NO APLICA",J3*12) -> 4080 | I3: =IF(E3<2000,"NO APLICA",MAX(CEILING((E3*0.8)/8,10),100)) -> 500 | J3: =IF(E3<3000,"NO APLICA",MAX(CEILING((E3*0.8)/12,10),100)) -> 340 | K3: =MAX(CEILING(E3/52,10),100) -> 100
B4: Vaporera de aluminio 90cm pintado | C4: El abuelo | D4: Cocina | E4: 4000 | F4: 2800 | G4: =IF(I4="NO APLICA","NO APLICA",I4*8) -> 3200 | H4: =IF(J4="NO APLICA","NO APLICA",J4*12) -> 3240 | I4: =IF(E4<2000,"NO APLICA",MAX(CEILING((E4*0.8)/8,10),100)) -> 400 | J4: =IF(E4<3000,"NO APLICA",MAX(CEILING((E4*0.8)/12,10),100)) -> 270 | K4: =MAX(CEILING(E4/52,10),100) -> 100
B5: Vaporera de aluminio 70cm | C5: El abuelo | D5: Cocina | E5: 3300 | F5: 2310 | G5: =IF(I5="NO APLICA","NO APLICA",I5*8) -> 2640 | H5: =IF(J5="NO APLICA","NO APLICA",J5*12) -> 2640 | I5: =IF(E5<2000,"NO APLICA",MAX(CEILING((E5*0.8)/8,10),100)) -> 330 | J5: =IF(E5<3000,"NO APLICA",MAX(CEILING((E5*0.8)/12,10),100)) -> 220 | K5: =MAX(CEILING(E5/52,10),100) -> 100
B6: Vaporera de aluminio 100cm | C6: Lamex | D6: Cocina | E6: 4000 | F6: 2800 | G6: =IF(I6="NO APLICA","NO APLICA",I6*8) -> 3200 | H6: =IF(J6="NO APLICA","NO APLICA",J6*12) -> 3240 | I6: =IF(E6<2000,"NO APLICA",MAX(CEILING((E6*0.8)/8,10),100)) -> 400 | J6: =IF(E6<3000,"NO APLICA",MAX(CEILING((E6*0.8)/12,10),100)) -> 270 | K6: =MAX(CEILING(E6/52,10),100) -> 100
B7: Vaporera de aluminio 45cm | C7: El abuelo | D7: Cocina | E7: 2500 | F7: 1750 | G7: =IF(I7="NO APLICA","NO APLICA",I7*8) -> 2000 | H7: =IF(J7="NO APLICA","NO APLICA",J7*12) -> NO APLICA | I7: =IF(E7<2000,"NO APLICA",MAX(CEILING((E7*0.8)/8,10),100)) -> 250 | J7: =IF(E7<3000,"NO APLICA",MAX(CEILING((E7*0.8)/12,10),100)) -> NO APLICA | K7: =MAX(CEILING(E7/52,10),100) -> 100
B8: Vaporera de aluminio 34cm | C8: El abuelo | D8: Cocina | E8: 1800 | F8: 1440 | G8: =IF(I8="NO APLICA","NO APLICA",I8*8) -> NO APLICA | H8: =IF(J8="NO APLICA","NO APLICA",J8*12) -> NO APLICA | I8: =IF(E8<2000,"NO APLICA",MAX(CEILING((E8*0.8)/8,10),100)) -> NO APLICA | J8: =IF(E8<3000,"NO APLICA",MAX(CEILING((E8*0.8)/12,10),100)) -> NO APLICA | K8: =MAX(CEILING(E8/52,10),100) -> 100
B9: Juego de vaporera de 3pz de aluminio 34cm maya | C9: El abuelo | D9: Cocina | E9: 3100 | F9: 2170 | G9: =IF(I9="NO APLICA","NO APLICA",I9*8) -> 2480 | H9: =IF(J9="NO APLICA","NO APLICA",J9*12) -> 2520 | I9: =IF(E9<2000,"NO APLICA",MAX(CEILING((E9*0.8)/8,10),100)) -> 310 | J9: =IF(E9<3000,"NO APLICA",MAX(CEILING((E9*0.8)/12,10),100)) -> 210 | K9: =MAX(CEILING(E9/52,10),100) -> 100
B10: Juego básico 1 | C10: El abuelo | D10: Cocina | E10: 3000 | F10: 2100 | G10: =IF(I10="NO APLICA","NO APLICA",I10*8) -> 2400 | H10: =IF(J10="NO APLICA","NO APLICA",J10*12) -> 2400 | I10: =IF(E10<2000,"NO APLICA",MAX(CEILING((E10*0.8)/8,10),100)) -> 300 | J10: =IF(E10<3000,"NO APLICA",MAX(CEILING((E10*0.8)/12,10),100)) -> 200 | K10: =MAX(CEILING(E10/52,10),100) -> 100
B11: Juego básico 2 | C11: El abuelo | D11: Cocina | E11: 3000 | F11: 2100 | G11: =IF(I11="NO APLICA","NO APLICA",I11*8) -> 2400 | H11: =IF(J11="NO APLICA","NO APLICA",J11*12) -> 2400 | I11: =IF(E11<2000,"NO APLICA",MAX(CEILING((E11*0.8)/8,10),100)) -> 300 | J11: =IF(E11<3000,"NO APLICA",MAX(CEILING((E11*0.8)/12,10),100)) -> 200 | K11: =MAX(CEILING(E11/52,10),100) -> 100
B12: Juego de budineras 3pz | C12: El abuelo | D12: Cocina | E12: 2500 | F12: 1750 | G12: =IF(I12="NO APLICA","NO APLICA",I12*8) -> 2000 | H12: =IF(J12="NO APLICA","NO APLICA",J12*12) -> NO APLICA | I12: =IF(E12<2000,"NO APLICA",MAX(CEILING((E12*0.8)/8,10),100)) -> 250 | J12: =IF(E12<3000,"NO APLICA",MAX(CEILING((E12*0.8)/12,10),100)) -> NO APLICA | K12: =MAX(CEILING(E12/52,10),100) -> 100
B13: Juego Vallarta 3pz | C13: El abuelo | D13: Cocina | E13: 3500 | F13: 2450 | G13: =IF(I13="NO APLICA","NO APLICA",I13*8) -> 2800 | H13: =IF(J13="NO APLICA","NO APLICA",J13*12) -> 2880 | I13: =IF(E13<2000,"NO APLICA",MAX(CEILING((E13*0.8)/8,10),100)) -> 350 | J13: =IF(E13<3000,"NO APLICA",MAX(CEILING((E13*0.8)/12,10),100)) -> 240 | K13: =MAX(CEILING(E13/52,10),100) -> 100
... B181: Colchón kingsa Magic | C181: Restonic | D181: Hogar | E181: 15000 | F181: 10500 | G181: =IF(I181="NO APLICA","NO APLICA",I181*8) -> 12000 | H181: =IF(J181="NO APLICA","NO APLICA",J181*12) -> 12000 | I181: =IF(E181<2000,"NO APLICA",MAX(CEILING((E181*0.8)/8,10),100)) -> 1500 | J181: =IF(E181<3000,"NO APLICA",MAX(CEILING((E181*0.8)/12,10),100)) -> 1000 | K181: =MAX(CEILING(E181/52,10),100) -> 290

Sheet Lista_Maestra
A1: Codigo | B1: Categoria | C1: Subcategoria | D1: Material | E1: Codigo_Cat | F1: Codigo_Sub | G1: Codigo_Mat | H1: Nombre_Comercial | I1: Nombre_Interno | J1: Marca | K1: Medida_Modelo | L1: Precio_Contado | M1: Pago_Semanal_1m | N1: Precio_1_meses | O1: Precio_Credito | P1: Aplica_2_meses | Q1: Pago_Semanal_2m | R1: Precio_2_meses | S1: Aplica_3_meses | T1: Pago_Semanal_3m | U1: Precio_3_meses | V1: Abono_Semanal_Largo | W1: Estatus | X1: Fecha_Actualizacion | Y1: Notas
A2: =IF(OR(E2="",F2="",G2=""),"",E2&"-"&F2&"-"&G2&"-"&TEXT(COUNTIFS($E$2:E2,E2,$F$2:F2,F2,$G$2:G2,G2),"000")) -> MOB-SIL-PSL-001 | B2: Mobiliario | C2: Silla | D2: Plástico | E2: =_xlfn.XLOOKUP(B2,Configuración!A:A,Configuración!B:B,"") -> MOB | F2: {=IF($C2="","",_xlfn.XLOOKUP(1,(Configuración!D:D=$B2)*(Configuración!E:E=$C2),Configuración!F:F,""))} -> SIL | G2: =IF($D2="","",_xlfn.XLOOKUP($D2,Configuración!H:H,Configuración!I:I,"")) -> PSL | H2: 4 Sillas Aruba blanca | I2: 4 Sillas Aruba blanca | J2: Duna | L2: 1670 | M2: =MAX(CEILING(L2/4,10),100) -> 420 | N2: =M2*4 -> 1680 | O2: 2380 | P2: =IF($O2<Configuración!$B$7,"NO","SI") -> SI | Q2: =IF($P2="NO","NO APLICA",MAX(CEILING(($O2*(1-Configuración!$B$2))/Configuración!$B$3,Configuración!$B$6),Configuración!$B$5)) -> 240 | R2: =IF($Q2="NO APLICA","NO APLICA",$Q2*Configuración!$B$3) -> 1920 | S2: =IF($O2<Configuración!$B$8,"NO","SI") -> NO | T2: =IF($S2="NO","NO APLICA",MAX(CEILING(($O2*(1-Configuración!$B$2))/Configuración!$B$4,Configuración!$B$6),Configuración!$B$5)) -> NO APLICA | U2: =IF($T2="NO APLICA","NO APLICA",$T2*Configuración!$B$4) -> NO APLICA | V2: =MAX(CEILING($O2/Configuración!$B$9,Configuración!$B$6),Configuración!$B$5) -> 100 | W2: Activo | X2: 46079
A3: =IF(OR(E3="",F3="",G3=""),"",E3&"-"&F3&"-"&G3&"-"&TEXT(COUNTIFS($E$2:E3,E3,$F$2:F3,F3,$G$2:G3,G3),"000")) -> MOB-SIL-PSL-002 | B3: Mobiliario | C3: Silla | D3: Plástico | E3: =_xlfn.XLOOKUP(B3,Configuración!A:A,Configuración!B:B,"") -> MOB | F3: {=IF($C3="","",_xlfn.XLOOKUP(1,(Configuración!D:D=$B3)*(Configuración!E:E=$C3),Configuración!F:F,""))} -> SIL | G3: =IF($D3="","",_xlfn.XLOOKUP($D3,Configuración!H:H,Configuración!I:I,"")) -> PSL | H3: 4 Sillas Aruba gris | I3: 4 Sillas Aruba gris | J3: Duna | L3: 1380 | M3: =MAX(CEILING(L3/4,10),100) -> 350 | N3: =M3*4 -> 1400 | O3: 1980 | P3: =IF($O3<Configuración!$B$7,"NO","SI") -> NO | Q3: =IF($P3="NO","NO APLICA",MAX(CEILING(($O3*(1-Configuración!$B$2))/Configuración!$B$3,Configuración!$B$6),Configuración!$B$5)) -> NO APLICA | R3: =IF($Q3="NO APLICA","NO APLICA",$Q3*Configuración!$B$3) -> NO APLICA | S3: =IF($O3<Configuración!$B$8,"NO","SI") -> NO | T3: =IF($S3="NO","NO APLICA",MAX(CEILING(($O3*(1-Configuración!$B$2))/Configuración!$B$4,Configuración!$B$6),Configuración!$B$5)) -> NO APLICA | U3: =IF($T3="NO APLICA","NO APLICA",$T3*Configuración!$B$4) -> NO APLICA | V3: =MAX(CEILING($O3/Configuración!$B$9,Configuración!$B$6),Configuración!$B$5) -> 100 | W3: Activo | X3: 46079
A4: =IF(OR(E4="",F4="",G4=""),"",E4&"-"&F4&"-"&G4&"-"&TEXT(COUNTIFS($E$2:E4,E4,$F$2:F4,F4,$G$2:G4,G4),"000")) -> MOB-SIL-PSL-003 | B4: Mobiliario | C4: Silla | D4: Plástico | E4: =_xlfn.XLOOKUP(B4,Configuración!A:A,Configuración!B:B,"") -> MOB | F4: {=IF($C4="","",_xlfn.XLOOKUP(1,(Configuración!D:D=$B4)*(Configuración!E:E=$C4),Configuración!F:F,""))} -> SIL | G4: =IF($D4="","",_xlfn.XLOOKUP($D4,Configuración!H:H,Configuración!I:I,"")) -> PSL | H4: 4 Sillas Brexia color | I4: 4 Sillas Brexia color | J4: Duna | L4: 2100 | M4: =MAX(CEILING(L4/4,10),100) -> 530 | N4: =M4*4 -> 2120 | O4: 3000 | P4: =IF($O4<Configuración!$B$7,"NO","SI") -> SI | Q4: =IF($P4="NO","NO APLICA",MAX(CEILING(($O4*(1-Configuración!$B$2))/Configuración!$B$3,Configuración!$B$6),Configuración!$B$5)) -> 300 | R4: =IF($Q4="NO APLICA","NO APLICA",$Q4*Configuración!$B$3) -> 2400 | S4: =IF($O4<Configuración!$B$8,"NO","SI") -> SI | T4: =IF($S4="NO","NO APLICA",MAX(CEILING(($O4*(1-Configuración!$B$2))/Configuración!$B$4,Configuración!$B$6),Configuración!$B$5)) -> 200 | U4: =IF($T4="NO APLICA","NO APLICA",$T4*Configuración!$B$4) -> 2400 | V4: =MAX(CEILING($O4/Configuración!$B$9,Configuración!$B$6),Configuración!$B$5) -> 100 | W4: Activo | X4: 46079
A5: =IF(OR(E5="",F5="",G5=""),"",E5&"-"&F5&"-"&G5&"-"&TEXT(COUNTIFS($E$2:E5,E5,$F$2:F5,F5,$G$2:G5,G5),"000")) -> MOB-SIL-PSL-004 | B5: Mobiliario | C5: Silla | D5: Plástico | E5: =_xlfn.XLOOKUP(B5,Configuración!A:A,Configuración!B:B,"") -> MOB | F5: {=IF($C5="","",_xlfn.XLOOKUP(1,(Configuración!D:D=$B5)*(Configuración!E:E=$C5),Configuración!F:F,""))} -> SIL | G5: =IF($D5="","",_xlfn.XLOOKUP($D5,Configuración!H:H,Configuración!I:I,"")) -> PSL | H5: 4 Sillas Pata de elefante color | I5: 4 Sillas Pata de elefante color | J5: Conejo | L5: 2310 | M5: =MAX(CEILING(L5/4,10),100) -> 580 | N5: =M5*4 -> 2320 | O5: 3300 | P5: =IF($O5<Configuración!$B$7,"NO","SI") -> SI | Q5: =IF($P5="NO","NO APLICA",MAX(CEILING(($O5*(1-Configuración!$B$2))/Configuración!$B$3,Configuración!$B$6),Configuración!$B$5)) -> 330 | R5: =IF($Q5="NO APLICA","NO APLICA",$Q5*Configuración!$B$3) -> 2640 | S5: =IF($O5<Configuración!$B$8,"NO","SI") -> SI | T5: =IF($S5="NO","NO APLICA",MAX(CEILING(($O5*(1-Configuración!$B$2))/Configuración!$B$4,Configuración!$B$6),Configuración!$B$5)) -> 220 | U5: =IF($T5="NO APLICA","NO APLICA",$T5*Configuración!$B$4) -> 2640 | V5: =MAX(CEILING($O5/Configuración!$B$9,Configuración!$B$6),Configuración!$B$5) -> 100 | W5: Activo | X5: 46079
A6: =IF(OR(E6="",F6="",G6=""),"",E6&"-"&F6&"-"&G6&"-"&TEXT(COUNTIFS($E$2:E6,E6,$F$2:F6,F6,$G$2:G6,G6),"000")) -> LBL-AIRE-MET-001 | B6: Línea blanca | C6: Aire acondicionado | D6: Metal | E6: =_xlfn.XLOOKUP(B6,Configuración!A:A,Configuración!B:B,"") -> LBL | F6: {=IF($C6="","",_xlfn.XLOOKUP(1,(Configuración!D:D=$B6)*(Configuración!E:E=$C6),Configuración!F:F,""))} -> AIRE | G6: =IF($D6="","",_xlfn.XLOOKUP($D6,Configuración!H:H,Configuración!I:I,"")) -> MET | H6: Aireacondicionado 12000BTU | I6: Aireacondicionado 12000BTU | J6: Hisense | L6: 13950 | M6: =MAX(CEILING(L6/4,10),100) -> 3490 | N6: =M6*4 -> 13960 | O6: 19935 | P6: =IF($O6<Configuración!$B$7,"NO","SI") -> SI | Q6: =IF($P6="NO","NO APLICA",MAX(CEILING(($O6*(1-Configuración!$B$2))/Configuración!$B$3,Configuración!$B$6),Configuración!$B$5)) -> 2000 | R6: =IF($Q6="NO APLICA","NO APLICA",$Q6*Configuración!$B$3) -> 16000 | S6: =IF($O6<Configuración!$B$8,"NO","SI") -> SI | T6: =IF($S6="NO","NO APLICA",MAX(CEILING(($O6*(1-Configuración!$B$2))/Configuración!$B$4,Configuración!$B$6),Configuración!$B$5)) -> 1330 | U6: =IF($T6="NO APLICA","NO APLICA",$T6*Configuración!$B$4) -> 15960 | V6: =MAX(CEILING($O6/Configuración!$B$9,Configuración!$B$6),Configuración!$B$5) -> 390 | W6: Activo | X6: 46079
A7: =IF(OR(E7="",F7="",G7=""),"",E7&"-"&F7&"-"&G7&"-"&TEXT(COUNTIFS($E$2:E7,E7,$F$2:F7,F7,$G$2:G7,G7),"000")) -> MOB-ALA-MAD-001 | B7: Mobiliario | C7: Alacena | D7: Madera | E7: =_xlfn.XLOOKUP(B7,Configuración!A:A,Configuración!B:B,"") -> MOB | F7: {=IF($C7="","",_xlfn.XLOOKUP(1,(Configuración!D:D=$B7)*(Configuración!E:E=$C7),Configuración!F:F,""))} -> ALA | G7: =IF($D7="","",_xlfn.XLOOKUP($D7,Configuración!H:H,Configuración!I:I,"")) -> MAD | H7: Alacena cantinera chica | I7: Alacena cantinera chica | J7: Madera D.C | L7: 7000 | M7: =MAX(CEILING(L7/4,10),100) -> 1750 | N7: =M7*4 -> 7000 | O7: 10000 | P7: =IF($O7<Configuración!$B$7,"NO","SI") -> SI | Q7: =IF($P7="NO","NO APLICA",MAX(CEILING(($O7*(1-Configuración!$B$2))/Configuración!$B$3,Configuración!$B$6),Configuración!$B$5)) -> 1000 | R7: =IF($Q7="NO APLICA","NO APLICA",$Q7*Configuración!$B$3) -> 8000 | S7: =IF($O7<Configuración!$B$8,"NO","SI") -> SI | T7: =IF($S7="NO","NO APLICA",MAX(CEILING(($O7*(1-Configuración!$B$2))/Configuración!$B$4,Configuración!$B$6),Configuración!$B$5)) -> 670 | U7: =IF($T7="NO APLICA","NO APLICA",$T7*Configuración!$B$4) -> 8040 | V7: =MAX(CEILING($O7/Configuración!$B$9,Configuración!$B$6),Configuración!$B$5) -> 200 | W7: Activo | X7: 46079
A8: =IF(OR(E8="",F8="",G8=""),"",E8&"-"&F8&"-"&G8&"-"&TEXT(COUNTIFS($E$2:E8,E8,$F$2:F8,F8,$G$2:G8,G8),"000")) -> MOB-ALA-MAD-002 | B8: Mobiliario | C8: Alacena | D8: Madera | E8: =_xlfn.XLOOKUP(B8,Configuración!A:A,Configuración!B:B,"") -> MOB | F8: {=IF($C8="","",_xlfn.XLOOKUP(1,(Configuración!D:D=$B8)*(Configuración!E:E=$C8),Configuración!F:F,""))} -> ALA | G8: =IF($D8="","",_xlfn.XLOOKUP($D8,Configuración!H:H,Configuración!I:I,"")) -> MAD | H8: Alacena cantinera grande | I8: Alacena cantinera grande | J8: Madera D.C | L8: 8750 | M8: =MAX(CEILING(L8/4,10),100) -> 2190 | N8: =M8*4 -> 8760 | O8: 12500 | P8: =IF($O8<Configuración!$B$7,"NO","SI") -> SI | Q8: =IF($P8="NO","NO APLICA",MAX(CEILING(($O8*(1-Configuración!$B$2))/Configuración!$B$3,Configuración!$B$6),Configuración!$B$5)) -> 1250 | R8: =IF($Q8="NO APLICA","NO APLICA",$Q8*Configuración!$B$3) -> 10000 | S8: =IF($O8<Configuración!$B$8,"NO","SI") -> SI | T8: =IF($S8="NO","NO APLICA",MAX(CEILING(($O8*(1-Configuración!$B$2))/Configuración!$B$4,Configuración!$B$6),Configuración!$B$5)) -> 840 | U8: =IF($T8="NO APLICA","NO APLICA",$T8*Configuración!$B$4) -> 10080 | V8: =MAX(CEILING($O8/Configuración!$B$9,Configuración!$B$6),Configuración!$B$5) -> 250 | W8: Activo | X8: 46079
A9: =IF(OR(E9="",F9="",G9=""),"",E9&"-"&F9&"-"&G9&"-"&TEXT(COUNTIFS($E$2:E9,E9,$F$2:F9,F9,$G$2:G9,G9),"000")) -> MOB-ALA-MAD-003 | B9: Mobiliario | C9: Alacena | D9: Madera | E9: =_xlfn.XLOOKUP(B9,Configuración!A:A,Configuración!B:B,"") -> MOB | F9: {=IF($C9="","",_xlfn.XLOOKUP(1,(Configuración!D:D=$B9)*(Configuración!E:E=$C9),Configuración!F:F,""))} -> ALA | G9: =IF($D9="","",_xlfn.XLOOKUP($D9,Configuración!H:H,Configuración!I:I,"")) -> MAD | H9: Alacena portamicro chica | I9: Alacena portamicro chica | J9: Madera D.C | L9: 4410 | M9: =MAX(CEILING(L9/4,10),100) -> 1110 | N9: =M9*4 -> 4440 | O9: 6300 | P9: =IF($O9<Configuración!$B$7,"NO","SI") -> SI | Q9: =IF($P9="NO","NO APLICA",MAX(CEILING(($O9*(1-Configuración!$B$2))/Configuración!$B$3,Configuración!$B$6),Configuración!$B$5)) -> 630 | R9: =IF($Q9="NO APLICA","NO APLICA",$Q9*Configuración!$B$3) -> 5040 | S9: =IF($O9<Configuración!$B$8,"NO","SI") -> SI | T9: =IF($S9="NO","NO APLICA",MAX(CEILING(($O9*(1-Configuración!$B$2))/Configuración!$B$4,Configuración!$B$6),Configuración!$B$5)) -> 420 | U9: =IF($T9="NO APLICA","NO APLICA",$T9*Configuración!$B$4) -> 5040 | V9: =MAX(CEILING($O9/Configuración!$B$9,Configuración!$B$6),Configuración!$B$5) -> 130 | W9: Activo | X9: 46079
A10: =IF(OR(E10="",F10="",G10=""),"",E10&"-"&F10&"-"&G10&"-"&TEXT(COUNTIFS($E$2:E10,E10,$F$2:F10,F10,$G$2:G10,G10),"000")) -> MOB-ANA-PSL-001 | B10: Mobiliario | C10: Anaquel | D10: Plástico | E10: =_xlfn.XLOOKUP(B10,Configuración!A:A,Configuración!B:B,"") -> MOB | F10: {=IF($C10="","",_xlfn.XLOOKUP(1,(Configuración!D:D=$B10)*(Configuración!E:E=$C10),Configuración!F:F,""))} -> ANA | G10: =IF($D10="","",_xlfn.XLOOKUP($D10,Configuración!H:H,Configuración!I:I,"")) -> PSL | H10: Anaquel de plástico | I10: Anaquel de plástico | J10: Lara | L10: 2310 | M10: =MAX(CEILING(L10/4,10),100) -> 580 | N10: =M10*4 -> 2320 | O10: 3300 | P10: =IF($O10<Configuración!$B$7,"NO","SI") -> SI | Q10: =IF($P10="NO","NO APLICA",MAX(CEILING(($O10*(1-Configuración!$B$2))/Configuración!$B$3,Configuración!$B$6),Configuración!$B$5)) -> 330 | R10: =IF($Q10="NO APLICA","NO APLICA",$Q10*Configuración!$B$3) -> 2640 | S10: =IF($O10<Configuración!$B$8,"NO","SI") -> SI | T10: =IF($S10="NO","NO APLICA",MAX(CEILING(($O10*(1-Configuración!$B$2))/Configuración!$B$4,Configuración!$B$6),Configuración!$B$5)) -> 220 | U10: =IF($T10="NO APLICA","NO APLICA",$T10*Configuración!$B$4) -> 2640 | V10: =MAX(CEILING($O10/Configuración!$B$9,Configuración!$B$6),Configuración!$B$5) -> 100 | W10: Activo | X10: 46079
A11: =IF(OR(E11="",F11="",G11=""),"",E11&"-"&F11&"-"&G11&"-"&TEXT(COUNTIFS($E$2:E11,E11,$F$2:F11,F11,$G$2:G11,G11),"000")) -> MOB-ANA-TUB-001 | B11: Mobiliario | C11: Anaquel | D11: Tubular | E11: =_xlfn.XLOOKUP(B11,Configuración!A:A,Configuración!B:B,"") -> MOB | F11: {=IF($C11="","",_xlfn.XLOOKUP(1,(Configuración!D:D=$B11)*(Configuración!E:E=$C11),Configuración!F:F,""))} -> ANA | G11: =IF($D11="","",_xlfn.XLOOKUP($D11,Configuración!H:H,Configuración!I:I,"")) -> TUB | H11: Anaquel estampado infantil tubular | I11: Anaquel estampado infantil tubular | J11: D.C | L11: 2100 | M11: =MAX(CEILING(L11/4,10),100) -> 530 | N11: =M11*4 -> 2120 | O11: 3000 | P11: =IF($O11<Configuración!$B$7,"NO","SI") -> SI | Q11: =IF($P11="NO","NO APLICA",MAX(CEILING(($O11*(1-Configuración!$B$2))/Configuración!$B$3,Configuración!$B$6),Configuración!$B$5)) -> 300 | R11: =IF($Q11="NO APLICA","NO APLICA",$Q11*Configuración!$B$3) -> 2400 | S11: =IF($O11<Configuración!$B$8,"NO","SI") -> SI | T11: =IF($S11="NO","NO APLICA",MAX(CEILING(($O11*(1-Configuración!$B$2))/Configuración!$B$4,Configuración!$B$6),Configuración!$B$5)) -> 200 | U11: =IF($T11="NO APLICA","NO APLICA",$T11*Configuración!$B$4) -> 2400 | V11: =MAX(CEILING($O11/Configuración!$B$9,Configuración!$B$6),Configuración!$B$5) -> 100 | W11: Activo | X11: 46079
A12: =IF(OR(E12="",F12="",G12=""),"",E12&"-"&F12&"-"&G12&"-"&TEXT(COUNTIFS($E$2:E12,E12,$F$2:F12,F12,$G$2:G12,G12),"000")) -> MOB-ANA-TUB-002 | B12: Mobiliario | C12: Anaquel | D12: Tubular | E12: =_xlfn.XLOOKUP(B12,Configuración!A:A,Configuración!B:B,"") -> MOB | F12: {=IF($C12="","",_xlfn.XLOOKUP(1,(Configuración!D:D=$B12)*(Configuración!E:E=$C12),Configuración!F:F,""))} -> ANA | G12: =IF($D12="","",_xlfn.XLOOKUP($D12,Configuración!H:H,Configuración!I:I,"")) -> TUB | H12: Anaquel tubular | I12: Anaquel tubular | J12: D.C | L12: 1960 | M12: =MAX(CEILING(L12/4,10),100) -> 490 | N12: =M12*4 -> 1960 | O12: 2800 | P12: =IF($O12<Configuración!$B$7,"NO","SI") -> SI | Q12: =IF($P12="NO","NO APLICA",MAX(CEILING(($O12*(1-Configuración!$B$2))/Configuración!$B$3,Configuración!$B$6),Configuración!$B$5)) -> 280 | R12: =IF($Q12="NO APLICA","NO APLICA",$Q12*Configuración!$B$3) -> 2240 | S12: =IF($O12<Configuración!$B$8,"NO","SI") -> NO | T12: =IF($S12="NO","NO APLICA",MAX(CEILING(($O12*(1-Configuración!$B$2))/Configuración!$B$4,Configuración!$B$6),Configuración!$B$5)) -> NO APLICA | U12: =IF($T12="NO APLICA","NO APLICA",$T12*Configuración!$B$4) -> NO APLICA | V12: =MAX(CEILING($O12/Configuración!$B$9,Configuración!$B$6),Configuración!$B$5) -> 100 | W12: Activo | X12: 46079
A13: =IF(OR(E13="",F13="",G13=""),"",E13&"-"&F13&"-"&G13&"-"&TEXT(COUNTIFS($E$2:E13,E13,$F$2:F13,F13,$G$2:G13,G13),"000")) -> COC-ARR-ALU-001 | B13: Cocina | C13: Arrocera | D13: Alumino | E13: =_xlfn.XLOOKUP(B13,Configuración!A:A,Configuración!B:B,"") -> COC | F13: {=IF($C13="","",_xlfn.XLOOKUP(1,(Configuración!D:D=$B13)*(Configuración!E:E=$C13),Configuración!F:F,""))} -> ARR | G13: =IF($D13="","",_xlfn.XLOOKUP($D13,Configuración!H:H,Configuración!I:I,"")) -> ALU | H13: Arrocera 70cm jumbo | I13: Arrocera jumbo | J13: El abuelo | K13: listo | L13: 3500 | M13: =MAX(CEILING(L13/4,10),100) -> 880 | N13: =M13*4 -> 3520 | O13: 5000 | P13: =IF($O13<Configuración!$B$7,"NO","SI") -> SI | Q13: =IF($P13="NO","NO APLICA",MAX(CEILING(($O13*(1-Configuración!$B$2))/Configuración!$B$3,Configuración!$B$6),Configuración!$B$5)) -> 500 | R13: =IF($Q13="NO APLICA","NO APLICA",$Q13*Configuración!$B$3) -> 4000 | S13: =IF($O13<Configuración!$B$8,"NO","SI") -> SI | T13: =IF($S13="NO","NO APLICA",MAX(CEILING(($O13*(1-Configuración!$B$2))/Configuración!$B$4,Configuración!$B$6),Configuración!$B$5)) -> 340 | U13: =IF($T13="NO APLICA","NO APLICA",$T13*Configuración!$B$4) -> 4080 | V13: =MAX(CEILING($O13/Configuración!$B$9,Configuración!$B$6),Configuración!$B$5) -> 100 | W13: Activo | X13: 46079
A14: =IF(OR(E14="",F14="",G14=""),"",E14&"-"&F14&"-"&G14&"-"&TEXT(COUNTIFS($E$2:E14,E14,$F$2:F14,F14,$G$2:G14,G14),"000")) -> COC-ARR-ALU-002 | B14: Cocina | C14: Arrocera | D14: Alumino | E14: =_xlfn.XLOOKUP(B14,Configuración!A:A,Configuración!B:B,"") -> COC | F14: {=IF($C14="","",_xlfn.XLOOKUP(1,(Configuración!D:D=$B14)*(Configuración!E:E=$C14),Configuración!F:F,""))} -> ARR | G14: =IF($D14="","",_xlfn.XLOOKUP($D14,Configuración!H:H,Configuración!I:I,"")) -> ALU | H14: Arrocera tepiaca 3pz | I14: Tepiaca | J14: Maytesa | K14: Listo | L14: 3850 | M14: =MAX(CEILING(L14/4,10),100) -> 970 | N14: =M14*4 -> 3880 | O14: 5500 | P14: =IF($O14<Configuración!$B$7,"NO","SI") -> SI | Q14: =IF($P14="NO","NO APLICA",MAX(CEILING(($O14*(1-Configuración!$B$2))/Configuración!$B$3,Configuración!$B$6),Configuración!$B$5)) -> 550 | R14: =IF($Q14="NO APLICA","NO APLICA",$Q14*Configuración!$B$3) -> 4400 | S14: =IF($O14<Configuración!$B$8,"NO","SI") -> SI | T14: =IF($S14="NO","NO APLICA",MAX(CEILING(($O14*(1-Configuración!$B$2))/Configuración!$B$4,Configuración!$B$6),Configuración!$B$5)) -> 370 | U14: =IF($T14="NO APLICA","NO APLICA",$T14*Configuración!$B$4) -> 4440 | V14: =MAX(CEILING($O14/Configuración!$B$9,Configuración!$B$6),Configuración!$B$5) -> 110 | W14: Activo | X14: 46079
A15: =IF(OR(E15="",F15="",G15=""),"",E15&"-"&F15&"-"&G15&"-"&TEXT(COUNTIFS($E$2:E15,E15,$F$2:F15,F15,$G$2:G15,G15),"000")) -> COC-ARR-ACI-001 | B15: Cocina | C15: Arrocera | D15: Acero inoxidable | E15: =_xlfn.XLOOKUP(B15,Configuración!A:A,Configuración!B:B,"") -> COC | F15: {=IF($C15="","",_xlfn.XLOOKUP(1,(Configuración!D:D=$B15)*(Configuración!E:E=$C15),Configuración!F:F,""))} -> ARR | G15: =IF($D15="","",_xlfn.XLOOKUP($D15,Configuración!H:H,Configuración!I:I,"")) -> ACI | H15: Arrocera Valencia 8pz | I15: Valencia | J15: Acero inoxidable | K15: Listo | L15: 3500 | M15: =MAX(CEILING(L15/4,10),100) -> 880 | N15: =M15*4 -> 3520 | O15: 5000 | P15: =IF($O15<Configuración!$B$7,"NO","SI") -> SI | Q15: =IF($P15="NO","NO APLICA",MAX(CEILING(($O15*(1-Configuración!$B$2))/Configuración!$B$3,Configuración!$B$6),Configuración!$B$5)) -> 500 | R15: =IF($Q15="NO APLICA","NO APLICA",$Q15*Configuración!$B$3) -> 4000 | S15: =IF($O15<Configuración!$B$8,"NO","SI") -> SI | T15: =IF($S15="NO","NO APLICA",MAX(CEILING(($O15*(1-Configuración!$B$2))/Configuración!$B$4,Configuración!$B$6),Configuración!$B$5)) -> 340 | U15: =IF($T15="NO APLICA","NO APLICA",$T15*Configuración!$B$4) -> 4080 | V15: =MAX(CEILING($O15/Configuración!$B$9,Configuración!$B$6),Configuración!$B$5) -> 100 | W15: Activo | X15: 46079
A16: =IF(OR(E16="",F16="",G16=""),"",E16&"-"&F16&"-"&G16&"-"&TEXT(COUNTIFS($E$2:E16,E16,$F$2:F16,F16,$G$2:G16,G16),"000")) -> COC-ARR-ACI-002 | B16: Cocina | C16: Arrocera | D16: Acero inoxidable | E16: =_xlfn.XLOOKUP(B16,Configuración!A:A,Configuración!B:B,"") -> COC | F16: {=IF($C16="","",_xlfn.XLOOKUP(1,(Configuración!D:D=$B16)*(Configuración!E:E=$C16),Configuración!F:F,""))} -> ARR | G16: =IF($D16="","",_xlfn.XLOOKUP($D16,Configuración!H:H,Configuración!I:I,"")) -> ACI | H16: Arrocera Velentina 6pz | I16: Valentina | J16: Acero inoxidable | K16: Listo | L16: 3850 | M16: =MAX(CEILING(L16/4,10),100) -> 970 | N16: =M16*4 -> 3880 | O16: 5500 | P16: =IF($O16<Configuración!$B$7,"NO","SI") -> SI | Q16: =IF($P16="NO","NO APLICA",MAX(CEILING(($O16*(1-Configuración!$B$2))/Configuración!$B$3,Configuración!$B$6),Configuración!$B$5)) -> 550 | R16: =IF($Q16="NO APLICA","NO APLICA",$Q16*Configuración!$B$3) -> 4400 | S16: =IF($O16<Configuración!$B$8,"NO","SI") -> SI | T16: =IF($S16="NO","NO APLICA",MAX(CEILING(($O16*(1-Configuración!$B$2))/Configuración!$B$4,Configuración!$B$6),Configuración!$B$5)) -> 370 | U16: =IF($T16="NO APLICA","NO APLICA",$T16*Configuración!$B$4) -> 4440 | V16: =MAX(CEILING($O16/Configuración!$B$9,Configuración!$B$6),Configuración!$B$5) -> 110 | W16: Activo | X16: 46079
A17: =IF(OR(E17="",F17="",G17=""),"",E17&"-"&F17&"-"&G17&"-"&TEXT(COUNTIFS($E$2:E17,E17,$F$2:F17,F17,$G$2:G17,G17),"000")) -> MOB-BAN-TUB-001 | B17: Mobiliario | C17: Banca | D17: Tubular | E17: =_xlfn.XLOOKUP(B17,Configuración!A:A,Configuración!B:B,"") -> MOB | F17: {=IF($C17="","",_xlfn.XLOOKUP(1,(Configuración!D:D=$B17)*(Configuración!E:E=$C17),Configuración!F:F,""))} -> BAN | G17: =IF($D17="","",_xlfn.XLOOKUP($D17,Configuración!H:H,Configuración!I:I,"")) -> TUB | H17: Banca tapizada tubular | I17: Banca tapizada tubular | J17: D.C | L17: 1960 | M17: =MAX(CEILING(L17/4,10),100) -> 490 | N17: =M17*4 -> 1960 | O17: 2800 | P17: =IF($O17<Configuración!$B$7,"NO","SI") -> SI | Q17: =IF($P17="NO","NO APLICA",MAX(CEILING(($O17*(1-Configuración!$B$2))/Configuración!$B$3,Configuración!$B$6),Configuración!$B$5)) -> 280 | R17: =IF($Q17="NO APLICA","NO APLICA",$Q17*Configuración!$B$3) -> 2240 | S17: =IF($O17<Configuración!$B$8,"NO","SI") -> NO | T17: =IF($S17="NO","NO APLICA",MAX(CEILING(($O17*(1-Configuración!$B$2))/Configuración!$B$4,Configuración!$B$6),Configuración!$B$5)) -> NO APLICA | U17: =IF($T17="NO APLICA","NO APLICA",$T17*Configuración!$B$4) -> NO APLICA | V17: =MAX(CEILING($O17/Configuración!$B$9,Configuración!$B$6),Configuración!$B$5) -> 100 | W17: Activo | X17: 46079
A18: =IF(OR(E18="",F18="",G18=""),"",E18&"-"&F18&"-"&G18&"-"&TEXT(COUNTIFS($E$2:E18,E18,$F$2:F18,F18,$G$2:G18,G18),"000")) -> MOB-BAN-MET-001 | B18: Mobiliario | C18: Banca | D18: Metal | E18: =_xlfn.XLOOKUP(B18,Configuración!A:A,Configuración!B:B,"") -> MOB | F18: {=IF($C18="","",_xlfn.XLOOKUP(1,(Configuración!D:D=$B18)*(Configuración!E:E=$C18),Configuración!F:F,""))} -> BAN | G18: =IF($D18="","",_xlfn.XLOOKUP($D18,Configuración!H:H,Configuración!I:I,"")) -> MET | H18: Banca tejida | I18: Banca tejida | J18: D.C | L18: 2100 | M18: =MAX(CEILING(L18/4,10),100) -> 530 | N18: =M18*4 -> 2120 | O18: 3000 | P18: =IF($O18<Configuración!$B$7,"NO","SI") -> SI | Q18: =IF($P18="NO","NO APLICA",MAX(CEILING(($O18*(1-Configuración!$B$2))/Configuración!$B$3,Configuración!$B$6),Configuración!$B$5)) -> 300 | R18: =IF($Q18="NO APLICA","NO APLICA",$Q18*Configuración!$B$3) -> 2400 | S18: =IF($O18<Configuración!$B$8,"NO","SI") -> SI | T18: =IF($S18="NO","NO APLICA",MAX(CEILING(($O18*(1-Configuración!$B$2))/Configuración!$B$4,Configuración!$B$6),Configuración!$B$5)) -> 200 | U18: =IF($T18="NO APLICA","NO APLICA",$T18*Configuración!$B$4) -> 2400 | V18: =MAX(CEILING($O18/Configuración!$B$9,Configuración!$B$6),Configuración!$B$5) -> 100 | W18: Activo | X18: 46079
A19: =IF(OR(E19="",F19="",G19=""),"",E19&"-"&F19&"-"&G19&"-"&TEXT(COUNTIFS($E$2:E19,E19,$F$2:F19,F19,$G$2:G19,G19),"000")) -> MOB-BCO-TUB-001 | B19: Mobiliario | C19: Banco | D19: Tubular | E19: =_xlfn.XLOOKUP(B19,Configuración!A:A,Configuración!B:B,"") -> MOB | F19: {=IF($C19="","",_xlfn.XLOOKUP(1,(Configuración!D:D=$B19)*(Configuración!E:E=$C19),Configuración!F:F,""))} -> BCO | G19: =IF($D19="","",_xlfn.XLOOKUP($D19,Configuración!H:H,Configuración!I:I,"")) -> TUB | H19: Banco redondo tubular | I19: Banco redondo tubular | J19: D.C | L19: 980 | M19: =MAX(CEILING(L19/4,10),100) -> 250 | N19: =M19*4 -> 1000 | O19: 1400 | P19: =IF($O19<Configuración!$B$7,"NO","SI") -> NO | Q19: =IF($P19="NO","NO APLICA",MAX(CEILING(($O19*(1-Configuración!$B$2))/Configuración!$B$3,Configuración!$B$6),Configuración!$B$5)) -> NO APLICA | R19: =IF($Q19="NO APLICA","NO APLICA",$Q19*Configuración!$B$3) -> NO APLICA | S19: =IF($O19<Configuración!$B$8,"NO","SI") -> NO | T19: =IF($S19="NO","NO APLICA",MAX(CEILING(($O19*(1-Configuración!$B$2))/Configuración!$B$4,Configuración!$B$6),Configuración!$B$5)) -> NO APLICA | U19: =IF($T19="NO APLICA","NO APLICA",$T19*Configuración!$B$4) -> NO APLICA | V19: =MAX(CEILING($O19/Configuración!$B$9,Configuración!$B$6),Configuración!$B$5) -> 100 | W19: Activo | X19: 46079
A20: =IF(OR(E20="",F20="",G20=""),"",E20&"-"&F20&"-"&G20&"-"&TEXT(COUNTIFS($E$2:E20,E20,$F$2:F20,F20,$G$2:G20,G20),"000")) -> COC-BAN-PEL-001 | B20: Cocina | C20: Bandejas | D20: Peltre | E20: =_xlfn.XLOOKUP(B20,Configuración!A:A,Configuración!B:B,"") -> COC | F20: {=IF($C20="","",_xlfn.XLOOKUP(1,(Configuración!D:D=$B20)*(Configuración!E:E=$C20),Configuración!F:F,""))} -> BAN | G20: =IF($D20="","",_xlfn.XLOOKUP($D20,Configuración!H:H,Configuración!I:I,"")) -> PEL | H20: Bandejas de peltre yaretzi 344044 | I20: Bandejas de peltre yaretzi 344044 | J20: Cinsa | K20: listo | L20: 1540 | M20: =MAX(CEILING(L20/4,10),100) -> 390 | N20: =M20*4 -> 1560 | O20: 2200 | P20: =IF($O20<Configuración!$B$7,"NO","SI") -> SI | Q20: =IF($P20="NO","NO APLICA",MAX(CEILING(($O20*(1-Configuración!$B$2))/Configuración!$B$3,Configuración!$B$6),Configuración!$B$5)) -> 220 | R20: =IF($Q20="NO APLICA","NO APLICA",$Q20*Configuración!$B$3) -> 1760 | S20: =IF($O20<Configuración!$B$8,"NO","SI") -> NO | T20: =IF($S20="NO","NO APLICA",MAX(CEILING(($O20*(1-Configuración!$B$2))/Configuración!$B$4,Configuración!$B$6),Configuración!$B$5)) -> NO APLICA | U20: =IF($T20="NO APLICA","NO APLICA",$T20*Configuración!$B$4) -> NO APLICA | V20: =MAX(CEILING($O20/Configuración!$B$9,Configuración!$B$6),Configuración!$B$5) -> 100 | W20: Activo | X20: 46079
A21: =IF(OR(E21="",F21="",G21=""),"",E21&"-"&F21&"-"&G21&"-"&TEXT(COUNTIFS($E$2:E21,E21,$F$2:F21,F21,$G$2:G21,G21),"000")) -> PLA-BAN-PSL-001 | B21: Plásticos | C21: Bañera | D21: Plástico | E21: =_xlfn.XLOOKUP(B21,Configuración!A:A,Configuración!B:B,"") -> PLA | F21: {=IF($C21="","",_xlfn.XLOOKUP(1,(Configuración!D:D=$B21)*(Configuración!E:E=$C21),Configuración!F:F,""))} -> BAN | G21: =IF($D21="","",_xlfn.XLOOKUP($D21,Configuración!H:H,Configuración!I:I,"")) -> PSL | H21: Bañera ovalada 110LTS | I21: Bañera ovalada 110LTS | J21: Placero | L21: 1050 | M21: =MAX(CEILING(L21/4,10),100) -> 270 | N21: =M21*4 -> 1080 | O21: 1500 | P21: =IF($O21<Configuración!$B$7,"NO","SI") -> NO | Q21: =IF($P21="NO","NO APLICA",MAX(CEILING(($O21*(1-Configuración!$B$2))/Configuración!$B$3,Configuración!$B$6),Configuración!$B$5)) -> NO APLICA | R21: =IF($Q21="NO APLICA","NO APLICA",$Q21*Configuración!$B$3) -> NO APLICA | S21: =IF($O21<Configuración!$B$8,"NO","SI") -> NO | T21: =IF($S21="NO","NO APLICA",MAX(CEILING(($O21*(1-Configuración!$B$2))/Configuración!$B$4,Configuración!$B$6),Configuración!$B$5)) -> NO APLICA | U21: =IF($T21="NO APLICA","NO APLICA",$T21*Configuración!$B$4) -> NO APLICA | V21: =MAX(CEILING($O21/Configuración!$B$9,Configuración!$B$6),Configuración!$B$5) -> 100 | W21: Activo | X21: 46079
A22: =IF(OR(E22="",F22="",G22=""),"",E22&"-"&F22&"-"&G22&"-"&TEXT(COUNTIFS($E$2:E22,E22,$F$2:F22,F22,$G$2:G22,G22),"000")) -> PLA-BAN-PSL-002 | B22: Plásticos | C22: Bañera | D22: Plástico | E22: =_xlfn.XLOOKUP(B22,Configuración!A:A,Configuración!B:B,"") -> PLA | F22: {=IF($C22="","",_xlfn.XLOOKUP(1,(Configuración!D:D=$B22)*(Configuración!E:E=$C22),Configuración!F:F,""))} -> BAN | G22: =IF($D22="","",_xlfn.XLOOKUP($D22,Configuración!H:H,Configuración!I:I,"")) -> PSL | H22: Bañera ovalada 210 LTS | I22: Bañera ovalada 210 LTS | J22: Placero | L22: 1330 | M22: =MAX(CEILING(L22/4,10),100) -> 340 | N22: =M22*4 -> 1360 | O22: 1900 | P22: =IF($O22<Configuración!$B$7,"NO","SI") -> NO | Q22: =IF($P22="NO","NO APLICA",MAX(CEILING(($O22*(1-Configuración!$B$2))/Configuración!$B$3,Configuración!$B$6),Configuración!$B$5)) -> NO APLICA | R22: =IF($Q22="NO APLICA","NO APLICA",$Q22*Configuración!$B$3) -> NO APLICA | S22: =IF($O22<Configuración!$B$8,"NO","SI") -> NO | T22: =IF($S22="NO","NO APLICA",MAX(CEILING(($O22*(1-Configuración!$B$2))/Configuración!$B$4,Configuración!$B$6),Configuración!$B$5)) -> NO APLICA | U22: =IF($T22="NO APLICA","NO APLICA",$T22*Configuración!$B$4) -> NO APLICA | V22: =MAX(CEILING($O22/Configuración!$B$9,Configuración!$B$6),Configuración!$B$5) -> 100 | W22: Activo | X22: 46079
A23: =IF(OR(E23="",F23="",G23=""),"",E23&"-"&F23&"-"&G23&"-"&TEXT(COUNTIFS($E$2:E23,E23,$F$2:F23,F23,$G$2:G23,G23),"000")) -> PLA-BAN-PSL-003 | B23: Plásticos | C23: Bañera | D23: Plástico | E23: =_xlfn.XLOOKUP(B23,Configuración!A:A,Configuración!B:B,"") -> PLA | F23: {=IF($C23="","",_xlfn.XLOOKUP(1,(Configuración!D:D=$B23)*(Configuración!E:E=$C23),Configuración!F:F,""))} -> BAN | G23: =IF($D23="","",_xlfn.XLOOKUP($D23,Configuración!H:H,Configuración!I:I,"")) -> PSL | H23: Bañera ovalada 310LTS | I23: Bañera ovalada 310LTS | J23: Placero | L23: 1855 | M23: =MAX(CEILING(L23/4,10),100) -> 470 | N23: =M23*4 -> 1880 | O23: 2650 | P23: =IF($O23<Configuración!$B$7,"NO","SI") -> SI | Q23: =IF($P23="NO","NO APLICA",MAX(CEILING(($O23*(1-Configuración!$B$2))/Configuración!$B$3,Configuración!$B$6),Configuración!$B$5)) -> 270 | R23: =IF($Q23="NO APLICA","NO APLICA",$Q23*Configuración!$B$3) -> 2160 | S23: =IF($O23<Configuración!$B$8,"NO","SI") -> NO | T23: =IF($S23="NO","NO APLICA",MAX(CEILING(($O23*(1-Configuración!$B$2))/Configuración!$B$4,Configuración!$B$6),Configuración!$B$5)) -> NO APLICA | U23: =IF($T23="NO APLICA","NO APLICA",$T23*Configuración!$B$4) -> NO APLICA | V23: =MAX(CEILING($O23/Configuración!$B$9,Configuración!$B$6),Configuración!$B$5) -> 100 | W23: Activo | X23: 46079
A24: =IF(OR(E24="",F24="",G24=""),"",E24&"-"&F24&"-"&G24&"-"&TEXT(COUNTIFS($E$2:E24,E24,$F$2:F24,F24,$G$2:G24,G24),"000")) -> PLA-BAN-PSL-004 | B24: Plásticos | C24: Bañera | D24: Plástico | E24: =_xlfn.XLOOKUP(B24,Configuración!A:A,Configuración!B:B,"") -> PLA | F24: {=IF($C24="","",_xlfn.XLOOKUP(1,(Configuración!D:D=$B24)*(Configuración!E:E=$C24),Configuración!F:F,""))} -> BAN | G24: =IF($D24="","",_xlfn.XLOOKUP($D24,Configuración!H:H,Configuración!I:I,"")) -> PSL | H24: Bañera ovalada 380LTS | I24: Bañera ovalada 380LTS | J24: Placero | L24: 2450 | M24: =MAX(CEILING(L24/4,10),100) -> 620 | N24: =M24*4 -> 2480 | O24: 3500 | P24: =IF($O24<Configuración!$B$7,"NO","SI") -> SI | Q24: =IF($P24="NO","NO APLICA",MAX(CEILING(($O24*(1-Configuración!$B$2))/Configuración!$B$3,Configuración!$B$6),Configuración!$B$5)) -> 350 | R24: =IF($Q24="NO APLICA","NO APLICA",$Q24*Configuración!$B$3) -> 2800 | S24: =IF($O24<Configuración!$B$8,"NO","SI") -> SI | T24: =IF($S24="NO","NO APLICA",MAX(CEILING(($O24*(1-Configuración!$B$2))/Configuración!$B$4,Configuración!$B$6),Configuración!$B$5)) -> 240 | U24: =IF($T24="NO APLICA","NO APLICA",$T24*Configuración!$B$4) -> 2880 | V24: =MAX(CEILING($O24/Configuración!$B$9,Configuración!$B$6),Configuración!$B$5) -> 100 | W24: Activo | X24: 46079
A25: =IF(OR(E25="",F25="",G25=""),"",E25&"-"&F25&"-"&G25&"-"&TEXT(COUNTIFS($E$2:E25,E25,$F$2:F25,F25,$G$2:G25,G25),"000")) -> PLA-BAN-PSL-005 | B25: Plásticos | C25: Bañera | D25: Plástico | E25: =_xlfn.XLOOKUP(B25,Configuración!A:A,Configuración!B:B,"") -> PLA | F25: {=IF($C25="","",_xlfn.XLOOKUP(1,(Configuración!D:D=$B25)*(Configuración!E:E=$C25),Configuración!F:F,""))} -> BAN | G25: =IF($D25="","",_xlfn.XLOOKUP($D25,Configuración!H:H,Configuración!I:I,"")) -> PSL | H25: Bañera ovalada 400LTS | I25: Bañera ovalada 400LTS | J25: Placero | L25: 2660 | M25: =MAX(CEILING(L25/4,10),100) -> 670 | N25: =M25*4 -> 2680 | O25: 3700 | P25: =IF($O25<Configuración!$B$7,"NO","SI") -> SI | Q25: =IF($P25="NO","NO APLICA",MAX(CEILING(($O25*(1-Configuración!$B$2))/Configuración!$B$3,Configuración!$B$6),Configuración!$B$5)) -> 370 | R25: =IF($Q25="NO APLICA","NO APLICA",$Q25*Configuración!$B$3) -> 2960 | S25: =IF($O25<Configuración!$B$8,"NO","SI") -> SI | T25: =IF($S25="NO","NO APLICA",MAX(CEILING(($O25*(1-Configuración!$B$2))/Configuración!$B$4,Configuración!$B$6),Configuración!$B$5)) -> 250 | U25: =IF($T25="NO APLICA","NO APLICA",$T25*Configuración!$B$4) -> 3000 | V25: =MAX(CEILING($O25/Configuración!$B$9,Configuración!$B$6),Configuración!$B$5) -> 100 | W25: Activo | X25: 46079
A26: =IF(OR(E26="",F26="",G26=""),"",E26&"-"&F26&"-"&G26&"-"&TEXT(COUNTIFS($E$2:E26,E26,$F$2:F26,F26,$G$2:G26,G26),"000")) -> PLA-BAN-PSL-006 | B26: Plásticos | C26: Bañera | D26: Plástico | E26: =_xlfn.XLOOKUP(B26,Configuración!A:A,Configuración!B:B,"") -> PLA | F26: {=IF($C26="","",_xlfn.XLOOKUP(1,(Configuración!D:D=$B26)*(Configuración!E:E=$C26),Configuración!F:F,""))} -> BAN | G26: =IF($D26="","",_xlfn.XLOOKUP($D26,Configuración!H:H,Configuración!I:I,"")) -> PSL | H26: Bañera ovalada 650LTS | I26: Bañera ovalada 650LTS | J26: Placero | L26: 3950 | M26: =MAX(CEILING(L26/4,10),100) -> 990 | N26: =M26*4 -> 3960 | O26: 6000 | P26: =IF($O26<Configuración!$B$7,"NO","SI") -> SI | Q26: =IF($P26="NO","NO APLICA",MAX(CEILING(($O26*(1-Configuración!$B$2))/Configuración!$B$3,Configuración!$B$6),Configuración!$B$5)) -> 600 | R26: =IF($Q26="NO APLICA","NO APLICA",$Q26*Configuración!$B$3) -> 4800 | S26: =IF($O26<Configuración!$B$8,"NO","SI") -> SI | T26: =IF($S26="NO","NO APLICA",MAX(CEILING(($O26*(1-Configuración!$B$2))/Configuración!$B$4,Configuración!$B$6),Configuración!$B$5)) -> 400 | U26: =IF($T26="NO APLICA","NO APLICA",$T26*Configuración!$B$4) -> 4800 | V26: =MAX(CEILING($O26/Configuración!$B$9,Configuración!$B$6),Configuración!$B$5) -> 120 | W26: Activo | X26: 46079
A27: =IF(OR(E27="",F27="",G27=""),"",E27&"-"&F27&"-"&G27&"-"&TEXT(COUNTIFS($E$2:E27,E27,$F$2:F27,F27,$G$2:G27,G27),"000")) -> PLA-BAN-PSL-007 | B27: Plásticos | C27: Bañera | D27: Plástico | E27: =_xlfn.XLOOKUP(B27,Configuración!A:A,Configuración!B:B,"") -> PLA | F27: {=IF($C27="","",_xlfn.XLOOKUP(1,(Configuración!D:D=$B27)*(Configuración!E:E=$C27),Configuración!F:F,""))} -> BAN | G27: =IF($D27="","",_xlfn.XLOOKUP($D27,Configuración!H:H,Configuración!I:I,"")) -> PSL | H27: Bañera ovalada 700LTS | I27: Bañera ovalada 700LTS | J27: Placero | L27: 4340 | M27: =MAX(CEILING(L27/4,10),100) -> 1090 | N27: =M27*4 -> 4360 | O27: 6600 | P27: =IF($O27<Configuración!$B$7,"NO","SI") -> SI | Q27: =IF($P27="NO","NO APLICA",MAX(CEILING(($O27*(1-Configuración!$B$2))/Configuración!$B$3,Configuración!$B$6),Configuración!$B$5)) -> 660 | R27: =IF($Q27="NO APLICA","NO APLICA",$Q27*Configuración!$B$3) -> 5280 | S27: =IF($O27<Configuración!$B$8,"NO","SI") -> SI | T27: =IF($S27="NO","NO APLICA",MAX(CEILING(($O27*(1-Configuración!$B$2))/Configuración!$B$4,Configuración!$B$6),Configuración!$B$5)) -> 440 | U27: =IF($T27="NO APLICA","NO APLICA",$T27*Configuración!$B$4) -> 5280 | V27: =MAX(CEILING($O27/Configuración!$B$9,Configuración!$B$6),Configuración!$B$5) -> 130 | W27: Activo | X27: 46079
A28: =IF(OR(E28="",F28="",G28=""),"",E28&"-"&F28&"-"&G28&"-"&TEXT(COUNTIFS($E$2:E28,E28,$F$2:F28,F28,$G$2:G28,G28),"000")) -> PLA-BAN-PSL-008 | B28: Plásticos | C28: Bañera | D28: Plástico | E28: =_xlfn.XLOOKUP(B28,Configuración!A:A,Configuración!B:B,"") -> PLA | F28: {=IF($C28="","",_xlfn.XLOOKUP(1,(Configuración!D:D=$B28)*(Configuración!E:E=$C28),Configuración!F:F,""))} -> BAN | G28: =IF($D28="","",_xlfn.XLOOKUP($D28,Configuración!H:H,Configuración!I:I,"")) -> PSL | H28: Bañera ovalada 900LTS | I28: Bañera ovalada 900LTS | J28: Placero | L28: 5110 | M28: =MAX(CEILING(L28/4,10),100) -> 1280 | N28: =M28*4 -> 5120 | O28: 7400 | P28: =IF($O28<Configuración!$B$7,"NO","SI") -> SI | Q28: =IF($P28="NO","NO APLICA",MAX(CEILING(($O28*(1-Configuración!$B$2))/Configuración!$B$3,Configuración!$B$6),Configuración!$B$5)) -> 740 | R28: =IF($Q28="NO APLICA","NO APLICA",$Q28*Configuración!$B$3) -> 5920 | S28: =IF($O28<Configuración!$B$8,"NO","SI") -> SI | T28: =IF($S28="NO","NO APLICA",MAX(CEILING(($O28*(1-Configuración!$B$2))/Configuración!$B$4,Configuración!$B$6),Configuración!$B$5)) -> 500 | U28: =IF($T28="NO APLICA","NO APLICA",$T28*Configuración!$B$4) -> 6000 | V28: =MAX(CEILING($O28/Configuración!$B$9,Configuración!$B$6),Configuración!$B$5) -> 150 | W28: Activo | X28: 46079
A29: =IF(OR(E29="",F29="",G29=""),"",E29&"-"&F29&"-"&G29&"-"&TEXT(COUNTIFS($E$2:E29,E29,$F$2:F29,F29,$G$2:G29,G29),"000")) -> COC-BAT-ALU-001 | B29: Cocina | C29: Batería | D29: Alumino | E29: =_xlfn.XLOOKUP(B29,Configuración!A:A,Configuración!B:B,"") -> COC | F29: {=IF($C29="","",_xlfn.XLOOKUP(1,(Configuración!D:D=$B29)*(Configuración!E:E=$C29),Configuración!F:F,""))} -> BAT | G29: =IF($D29="","",_xlfn.XLOOKUP($D29,Configuración!H:H,Configuración!I:I,"")) -> ALU | H29: Batería acayuqueña 9pz | I29: Acayuqueña | J29: El abuelo | K29: Listo | L29: 2100 | M29: =MAX(CEILING(L29/4,10),100) -> 530 | N29: =M29*4 -> 2120 | O29: 3000 | P29: =IF($O29<Configuración!$B$7,"NO","SI") -> SI | Q29: =IF($P29="NO","NO APLICA",MAX(CEILING(($O29*(1-Configuración!$B$2))/Configuración!$B$3,Configuración!$B$6),Configuración!$B$5)) -> 300 | R29: =IF($Q29="NO APLICA","NO APLICA",$Q29*Configuración!$B$3) -> 2400 | S29: =IF($O29<Configuración!$B$8,"NO","SI") -> SI | T29: =IF($S29="NO","NO APLICA",MAX(CEILING(($O29*(1-Configuración!$B$2))/Configuración!$B$4,Configuración!$B$6),Configuración!$B$5)) -> 200 | U29: =IF($T29="NO APLICA","NO APLICA",$T29*Configuración!$B$4) -> 2400 | V29: =MAX(CEILING($O29/Configuración!$B$9,Configuración!$B$6),Configuración!$B$5) -> 100 | W29: Activo | X29: 46079
A30: =IF(OR(E30="",F30="",G30=""),"",E30&"-"&F30&"-"&G30&"-"&TEXT(COUNTIFS($E$2:E30,E30,$F$2:F30,F30,$G$2:G30,G30),"000")) -> COC-BAT-ALU-002 | B30: Cocina | C30: Batería | D30: Alumino | E30: =_xlfn.XLOOKUP(B30,Configuración!A:A,Configuración!B:B,"") -> COC | F30: {=IF($C30="","",_xlfn.XLOOKUP(1,(Configuración!D:D=$B30)*(Configuración!E:E=$C30),Configuración!F:F,""))} -> BAT | G30: =IF($D30="","",_xlfn.XLOOKUP($D30,Configuración!H:H,Configuración!I:I,"")) -> ALU | H30: Batería córdoba 14pz | I30: Córdoba | J30: El abuelo | K30: listo | L30: 2520 | M30: =MAX(CEILING(L30/4,10),100) -> 630 | N30: =M30*4 -> 2520 | O30: 4000 | P30: =IF($O30<Configuración!$B$7,"NO","SI") -> SI | Q30: =IF($P30="NO","NO APLICA",MAX(CEILING(($O30*(1-Configuración!$B$2))/Configuración!$B$3,Configuración!$B$6),Configuración!$B$5)) -> 400 | R30: =IF($Q30="NO APLICA","NO APLICA",$Q30*Configuración!$B$3) -> 3200 | S30: =IF($O30<Configuración!$B$8,"NO","SI") -> SI | T30: =IF($S30="NO","NO APLICA",MAX(CEILING(($O30*(1-Configuración!$B$2))/Configuración!$B$4,Configuración!$B$6),Configuración!$B$5)) -> 270 | U30: =IF($T30="NO APLICA","NO APLICA",$T30*Configuración!$B$4) -> 3240 | V30: =MAX(CEILING($O30/Configuración!$B$9,Configuración!$B$6),Configuración!$B$5) -> 100 | W30: Activo | X30: 46079
A31: =IF(OR(E31="",F31="",G31=""),"",E31&"-"&F31&"-"&G31&"-"&TEXT(COUNTIFS($E$2:E31,E31,$F$2:F31,F31,$G$2:G31,G31),"000")) -> COC-BAT-PEL-001 | B31: Cocina | C31: Batería | D31: Peltre | E31: =_xlfn.XLOOKUP(B31,Configuración!A:A,Configuración!B:B,"") -> COC | F31: {=IF($C31="","",_xlfn.XLOOKUP(1,(Configuración!D:D=$B31)*(Configuración!E:E=$C31),Configuración!F:F,""))} -> BAT | G31: =IF($D31="","",_xlfn.XLOOKUP($D31,Configuración!H:H,Configuración!I:I,"")) -> PEL | H31: Batería de peltre chiapaneca 10pz | I31: Chiapaneca | J31: Cinsa | K31: listo | L31: 2520 | M31: =MAX(CEILING(L31/4,10),100) -> 630 | N31: =M31*4 -> 2520 | O31: 3600 | P31: =IF($O31<Configuración!$B$7,"NO","SI") -> SI | Q31: =IF($P31="NO","NO APLICA",MAX(CEILING(($O31*(1-Configuración!$B$2))/Configuración!$B$3,Configuración!$B$6),Configuración!$B$5)) -> 360 | R31: =IF($Q31="NO APLICA","NO APLICA",$Q31*Configuración!$B$3) -> 2880 | S31: =IF($O31<Configuración!$B$8,"NO","SI") -> SI | T31: =IF($S31="NO","NO APLICA",MAX(CEILING(($O31*(1-Configuración!$B$2))/Configuración!$B$4,Configuración!$B$6),Configuración!$B$5)) -> 240 | U31: =IF($T31="NO APLICA","NO APLICA",$T31*Configuración!$B$4) -> 2880 | V31: =MAX(CEILING($O31/Configuración!$B$9,Configuración!$B$6),Configuración!$B$5) -> 100 | W31: Activo | X31: 46079
A32: =IF(OR(E32="",F32="",G32=""),"",E32&"-"&F32&"-"&G32&"-"&TEXT(COUNTIFS($E$2:E32,E32,$F$2:F32,F32,$G$2:G32,G32),"000")) -> COC-BAT-PEL-002 | B32: Cocina | C32: Batería | D32: Peltre | E32: =_xlfn.XLOOKUP(B32,Configuración!A:A,Configuración!B:B,"") -> COC | F32: {=IF($C32="","",_xlfn.XLOOKUP(1,(Configuración!D:D=$B32)*(Configuración!E:E=$C32),Configuración!F:F,""))} -> BAT | G32: =IF($D32="","",_xlfn.XLOOKUP($D32,Configuración!H:H,Configuración!I:I,"")) -> PEL | H32: Batería de peltre duramax 13pz negro | I32: Duramax | J32: Cinsa | K32: listo | L32: 3500 | M32: =MAX(CEILING(L32/4,10),100) -> 880 | N32: =M32*4 -> 3520 | O32: 5000 | P32: =IF($O32<Configuración!$B$7,"NO","SI") -> SI | Q32: =IF($P32="NO","NO APLICA",MAX(CEILING(($O32*(1-Configuración!$B$2))/Configuración!$B$3,Configuración!$B$6),Configuración!$B$5)) -> 500 | R32: =IF($Q32="NO APLICA","NO APLICA",$Q32*Configuración!$B$3) -> 4000 | S32: =IF($O32<Configuración!$B$8,"NO","SI") -> SI | T32: =IF($S32="NO","NO APLICA",MAX(CEILING(($O32*(1-Configuración!$B$2))/Configuración!$B$4,Configuración!$B$6),Configuración!$B$5)) -> 340 | U32: =IF($T32="NO APLICA","NO APLICA",$T32*Configuración!$B$4) -> 4080 | V32: =MAX(CEILING($O32/Configuración!$B$9,Configuración!$B$6),Configuración!$B$5) -> 100 | W32: Activo | X32: 46079
A33: =IF(OR(E33="",F33="",G33=""),"",E33&"-"&F33&"-"&G33&"-"&TEXT(COUNTIFS($E$2:E33,E33,$F$2:F33,F33,$G$2:G33,G33),"000")) -> COC-BAT-PEL-003 | B33: Cocina | C33: Batería | D33: Peltre | E33: =_xlfn.XLOOKUP(B33,Configuración!A:A,Configuración!B:B,"") -> COC | F33: {=IF($C33="","",_xlfn.XLOOKUP(1,(Configuración!D:D=$B33)*(Configuración!E:E=$C33),Configuración!F:F,""))} -> BAT | G33: =IF($D33="","",_xlfn.XLOOKUP($D33,Configuración!H:H,Configuración!I:I,"")) -> PEL | H33: Batería de peltre Esperanza verde 10pz | I33: Esperanza | J33: Cinsa | K33: listo | L33: 2100 | M33: =MAX(CEILING(L33/4,10),100) -> 530 | N33: =M33*4 -> 2120 | O33: 3000 | P33: =IF($O33<Configuración!$B$7,"NO","SI") -> SI | Q33: =IF($P33="NO","NO APLICA",MAX(CEILING(($O33*(1-Configuración!$B$2))/Configuración!$B$3,Configuración!$B$6),Configuración!$B$5)) -> 300 | R33: =IF($Q33="NO APLICA","NO APLICA",$Q33*Configuración!$B$3) -> 2400 | S33: =IF($O33<Configuración!$B$8,"NO","SI") -> SI | T33: =IF($S33="NO","NO APLICA",MAX(CEILING(($O33*(1-Configuración!$B$2))/Configuración!$B$4,Configuración!$B$6),Configuración!$B$5)) -> 200 | U33: =IF($T33="NO APLICA","NO APLICA",$T33*Configuración!$B$4) -> 2400 | V33: =MAX(CEILING($O33/Configuración!$B$9,Configuración!$B$6),Configuración!$B$5) -> 100 | W33: Activo | X33: 46079
A34: =IF(OR(E34="",F34="",G34=""),"",E34&"-"&F34&"-"&G34&"-"&TEXT(COUNTIFS($E$2:E34,E34,$F$2:F34,F34,$G$2:G34,G34),"000")) -> COC-BAT-PEL-004 | B34: Cocina | C34: Batería | D34: Peltre | E34: =_xlfn.XLOOKUP(B34,Configuración!A:A,Configuración!B:B,"") -> COC | F34: {=IF($C34="","",_xlfn.XLOOKUP(1,(Configuración!D:D=$B34)*(Configuración!E:E=$C34),Configuración!F:F,""))} -> BAT | G34: =IF($D34="","",_xlfn.XLOOKUP($D34,Configuración!H:H,Configuración!I:I,"")) -> PEL | H34: Batería de peltre Fernanda verde 10pz | I34: Fernanda | J34: Cinsa | K34: listo | L34: 2100 | M34: =MAX(CEILING(L34/4,10),100) -> 530 | N34: =M34*4 -> 2120 | O34: 3000 | P34: =IF($O34<Configuración!$B$7,"NO","SI") -> SI | Q34: =IF($P34="NO","NO APLICA",MAX(CEILING(($O34*(1-Configuración!$B$2))/Configuración!$B$3,Configuración!$B$6),Configuración!$B$5)) -> 300 | R34: =IF($Q34="NO APLICA","NO APLICA",$Q34*Configuración!$B$3) -> 2400 | S34: =IF($O34<Configuración!$B$8,"NO","SI") -> SI | T34: =IF($S34="NO","NO APLICA",MAX(CEILING(($O34*(1-Configuración!$B$2))/Configuración!$B$4,Configuración!$B$6),Configuración!$B$5)) -> 200 | U34: =IF($T34="NO APLICA","NO APLICA",$T34*Configuración!$B$4) -> 2400 | V34: =MAX(CEILING($O34/Configuración!$B$9,Configuración!$B$6),Configuración!$B$5) -> 100 | W34: Activo | X34: 46079
A35: =IF(OR(E35="",F35="",G35=""),"",E35&"-"&F35&"-"&G35&"-"&TEXT(COUNTIFS($E$2:E35,E35,$F$2:F35,F35,$G$2:G35,G35),"000")) -> COC-BAT-PEL-005 | B35: Cocina | C35: Batería | D35: Peltre | E35: =_xlfn.XLOOKUP(B35,Configuración!A:A,Configuración!B:B,"") -> COC | F35: {=IF($C35="","",_xlfn.XLOOKUP(1,(Configuración!D:D=$B35)*(Configuración!E:E=$C35),Configuración!F:F,""))} -> BAT | G35: =IF($D35="","",_xlfn.XLOOKUP($D35,Configuración!H:H,Configuración!I:I,"")) -> PEL | H35: Batería de peltre pontevedra 11pz | I35: Pontevedra | J35: Cinsa | K35: listo | L35: 3500 | M35: =MAX(CEILING(L35/4,10),100) -> 880 | N35: =M35*4 -> 3520 | O35: 4995 | P35: =IF($O35<Configuración!$B$7,"NO","SI") -> SI | Q35: =IF($P35="NO","NO APLICA",MAX(CEILING(($O35*(1-Configuración!$B$2))/Configuración!$B$3,Configuración!$B$6),Configuración!$B$5)) -> 500 | R35: =IF($Q35="NO APLICA","NO APLICA",$Q35*Configuración!$B$3) -> 4000 | S35: =IF($O35<Configuración!$B$8,"NO","SI") -> SI | T35: =IF($S35="NO","NO APLICA",MAX(CEILING(($O35*(1-Configuración!$B$2))/Configuración!$B$4,Configuración!$B$6),Configuración!$B$5)) -> 340 | U35: =IF($T35="NO APLICA","NO APLICA",$T35*Configuración!$B$4) -> 4080 | V35: =MAX(CEILING($O35/Configuración!$B$9,Configuración!$B$6),Configuración!$B$5) -> 100 | W35: Activo | X35: 46079
A36: =IF(OR(E36="",F36="",G36=""),"",E36&"-"&F36&"-"&G36&"-"&TEXT(COUNTIFS($E$2:E36,E36,$F$2:F36,F36,$G$2:G36,G36),"000")) -> COC-BAT-PEL-006 | B36: Cocina | C36: Batería | D36: Peltre | E36: =_xlfn.XLOOKUP(B36,Configuración!A:A,Configuración!B:B,"") -> COC | F36: {=IF($C36="","",_xlfn.XLOOKUP(1,(Configuración!D:D=$B36)*(Configuración!E:E=$C36),Configuración!F:F,""))} -> BAT | G36: =IF($D36="","",_xlfn.XLOOKUP($D36,Configuración!H:H,Configuración!I:I,"")) -> PEL | H36: Batería de peltre Tuxtla 12pz | I36: Tuxtla | J36: Cinsa | K36: listo | L36: 2800 | M36: =MAX(CEILING(L36/4,10),100) -> 700 | N36: =M36*4 -> 2800 | O36: 4000 | P36: =IF($O36<Configuración!$B$7,"NO","SI") -> SI | Q36: =IF($P36="NO","NO APLICA",MAX(CEILING(($O36*(1-Configuración!$B$2))/Configuración!$B$3,Configuración!$B$6),Configuración!$B$5)) -> 400 | R36: =IF($Q36="NO APLICA","NO APLICA",$Q36*Configuración!$B$3) -> 3200 | S36: =IF($O36<Configuración!$B$8,"NO","SI") -> SI | T36: =IF($S36="NO","NO APLICA",MAX(CEILING(($O36*(1-Configuración!$B$2))/Configuración!$B$4,Configuración!$B$6),Configuración!$B$5)) -> 270 | U36: =IF($T36="NO APLICA","NO APLICA",$T36*Configuración!$B$4) -> 3240 | V36: =MAX(CEILING($O36/Configuración!$B$9,Configuración!$B$6),Configuración!$B$5) -> 100 | W36: Activo | X36: 46079
A37: =IF(OR(E37="",F37="",G37=""),"",E37&"-"&F37&"-"&G37&"-"&TEXT(COUNTIFS($E$2:E37,E37,$F$2:F37,F37,$G$2:G37,G37),"000")) -> COC-BAT-ALUT-001 | B37: Cocina | C37: Batería | D37: Alumino y Teflon | E37: =_xlfn.XLOOKUP(B37,Configuración!A:A,Configuración!B:B,"") -> COC | F37: {=IF($C37="","",_xlfn.XLOOKUP(1,(Configuración!D:D=$B37)*(Configuración!E:E=$C37),Configuración!F:F,""))} -> BAT | G37: =IF($D37="","",_xlfn.XLOOKUP($D37,Configuración!H:H,Configuración!I:I,"")) -> ALUT | H37: Batería de teflón Habana naranja | I37: Bateria Habana | J37: Cinsa | K37: listo | L37: 2800 | M37: =MAX(CEILING(L37/4,10),100) -> 700 | N37: =M37*4 -> 2800 | O37: 4000 | P37: =IF($O37<Configuración!$B$7,"NO","SI") -> SI | Q37: =IF($P37="NO","NO APLICA",MAX(CEILING(($O37*(1-Configuración!$B$2))/Configuración!$B$3,Configuración!$B$6),Configuración!$B$5)) -> 400 | R37: =IF($Q37="NO APLICA","NO APLICA",$Q37*Configuración!$B$3) -> 3200 | S37: =IF($O37<Configuración!$B$8,"NO","SI") -> SI | T37: =IF($S37="NO","NO APLICA",MAX(CEILING(($O37*(1-Configuración!$B$2))/Configuración!$B$4,Configuración!$B$6),Configuración!$B$5)) -> 270 | U37: =IF($T37="NO APLICA","NO APLICA",$T37*Configuración!$B$4) -> 3240 | V37: =MAX(CEILING($O37/Configuración!$B$9,Configuración!$B$6),Configuración!$B$5) -> 100 | W37: Activo | X37: 46079
A38: =IF(OR(E38="",F38="",G38=""),"",E38&"-"&F38&"-"&G38&"-"&TEXT(COUNTIFS($E$2:E38,E38,$F$2:F38,F38,$G$2:G38,G38),"000")) -> COC-BAT-ALUT-002 | B38: Cocina | C38: Batería | D38: Alumino y Teflon | E38: =_xlfn.XLOOKUP(B38,Configuración!A:A,Configuración!B:B,"") -> COC | F38: {=IF($C38="","",_xlfn.XLOOKUP(1,(Configuración!D:D=$B38)*(Configuración!E:E=$C38),Configuración!F:F,""))} -> BAT | G38: =IF($D38="","",_xlfn.XLOOKUP($D38,Configuración!H:H,Configuración!I:I,"")) -> ALUT | H38: Batería de teflón negro 19pz | I38: Bateria Eko | J38: Eko | K38: listo | L38: 2940 | M38: =MAX(CEILING(L38/4,10),100) -> 740 | N38: =M38*4 -> 2960 | O38: 4200 | P38: =IF($O38<Configuración!$B$7,"NO","SI") -> SI | Q38: =IF($P38="NO","NO APLICA",MAX(CEILING(($O38*(1-Configuración!$B$2))/Configuración!$B$3,Configuración!$B$6),Configuración!$B$5)) -> 420 | R38: =IF($Q38="NO APLICA","NO APLICA",$Q38*Configuración!$B$3) -> 3360 | S38: =IF($O38<Configuración!$B$8,"NO","SI") -> SI | T38: =IF($S38="NO","NO APLICA",MAX(CEILING(($O38*(1-Configuración!$B$2))/Configuración!$B$4,Configuración!$B$6),Configuración!$B$5)) -> 280 | U38: =IF($T38="NO APLICA","NO APLICA",$T38*Configuración!$B$4) -> 3360 | V38: =MAX(CEILING($O38/Configuración!$B$9,Configuración!$B$6),Configuración!$B$5) -> 100 | W38: Activo | X38: 46079
A39: =IF(OR(E39="",F39="",G39=""),"",E39&"-"&F39&"-"&G39&"-"&TEXT(COUNTIFS($E$2:E39,E39,$F$2:F39,F39,$G$2:G39,G39),"000")) -> COC-BAT-ALUT-003 | B39: Cocina | C39: Batería | D39: Alumino y Teflon | E39: =_xlfn.XLOOKUP(B39,Configuración!A:A,Configuración!B:B,"") -> COC | F39: {=IF($C39="","",_xlfn.XLOOKUP(1,(Configuración!D:D=$B39)*(Configuración!E:E=$C39),Configuración!F:F,""))} -> BAT | G39: =IF($D39="","",_xlfn.XLOOKUP($D39,Configuración!H:H,Configuración!I:I,"")) -> ALUT | H39: Batería de teflon tobago | I39: Tobago | J39: Cinsa | K39: listo | L39: 4000 | M39: =MAX(CEILING(L39/4,10),100) -> 1000 | N39: =M39*4 -> 4000 | O39: 5700 | P39: =IF($O39<Configuración!$B$7,"NO","SI") -> SI | Q39: =IF($P39="NO","NO APLICA",MAX(CEILING(($O39*(1-Configuración!$B$2))/Configuración!$B$3,Configuración!$B$6),Configuración!$B$5)) -> 570 | R39: =IF($Q39="NO APLICA","NO APLICA",$Q39*Configuración!$B$3) -> 4560 | S39: =IF($O39<Configuración!$B$8,"NO","SI") -> SI | T39: =IF($S39="NO","NO APLICA",MAX(CEILING(($O39*(1-Configuración!$B$2))/Configuración!$B$4,Configuración!$B$6),Configuración!$B$5)) -> 380 | U39: =IF($T39="NO APLICA","NO APLICA",$T39*Configuración!$B$4) -> 4560 | V39: =MAX(CEILING($O39/Configuración!$B$9,Configuración!$B$6),Configuración!$B$5) -> 110 | W39: Activo | X39: 46079
A40: =IF(OR(E40="",F40="",G40=""),"",E40&"-"&F40&"-"&G40&"-"&TEXT(COUNTIFS($E$2:E40,E40,$F$2:F40,F40,$G$2:G40,G40),"000")) -> COC-BAT-ALU-003 | B40: Cocina | C40: Batería | D40: Alumino | E40: =_xlfn.XLOOKUP(B40,Configuración!A:A,Configuración!B:B,"") -> COC | F40: {=IF($C40="","",_xlfn.XLOOKUP(1,(Configuración!D:D=$B40)*(Configuración!E:E=$C40),Configuración!F:F,""))} -> BAT | G40: =IF($D40="","",_xlfn.XLOOKUP($D40,Configuración!H:H,Configuración!I:I,"")) -> ALU | H40: Batería Don beto 9pz | I40: Don beto | J40: Perico | K40: listo | L40: 1820 | M40: =MAX(CEILING(L40/4,10),100) -> 460 | N40: =M40*4 -> 1840 | O40: 2600 | P40: =IF($O40<Configuración!$B$7,"NO","SI") -> SI | Q40: =IF($P40="NO","NO APLICA",MAX(CEILING(($O40*(1-Configuración!$B$2))/Configuración!$B$3,Configuración!$B$6),Configuración!$B$5)) -> 260 | R40: =IF($Q40="NO APLICA","NO APLICA",$Q40*Configuración!$B$3) -> 2080 | S40: =IF($O40<Configuración!$B$8,"NO","SI") -> NO | T40: =IF($S40="NO","NO APLICA",MAX(CEILING(($O40*(1-Configuración!$B$2))/Configuración!$B$4,Configuración!$B$6),Configuración!$B$5)) -> NO APLICA | U40: =IF($T40="NO APLICA","NO APLICA",$T40*Configuración!$B$4) -> NO APLICA | V40: =MAX(CEILING($O40/Configuración!$B$9,Configuración!$B$6),Configuración!$B$5) -> 100 | W40: Activo | X40: 46079
... A49: =IF(OR(E49="",F49="",G49=""),"",E49&"-"&F49&"-"&G49&"-"&TEXT(COUNTIFS($E$2:E49,E49,$F$2:F49,F49,$G$2:G49,G49),"000")) -> COC-BAT-TF-003 | B49: Cocina | C49: Batería | D49: Triple Fuerte | E49: =_xlfn.XLOOKUP(B49,Configuración!A:A,Configuración!B:B,"") -> COC | F49: {=IF($C49="","",_xlfn.XLOOKUP(1,(Configuración!D:D=$B49)*(Configuración!E:E=$C49),Configuración!F:F,""))} -> BAT | G49: =IF($D49="","",_xlfn.XLOOKUP($D49,Configuración!H:H,Configuración!I:I,"")) -> TF | H49: Batería Victoria 7pz triple fuerte (TF) | I49: Victoria | J49: Hércules | K49: listo | L49: 4410 | M49: =MAX(CEILING(L49/4,10),100) -> 1110 | N49: =M49*4 -> 4440 | O49: 6300 | P49: =IF($O49<Configuración!$B$7,"NO","SI") -> SI | Q49: =IF($P49="NO","NO APLICA",MAX(CEILING(($O49*(1-Configuración!$B$2))/Configuración!$B$3,Configuración!$B$6),Configuración!$B$5)) -> 630 | R49: =IF($Q49="NO APLICA","NO APLICA",$Q49*Configuración!$B$3) -> 5040 | S49: =IF($O49<Configuración!$B$8,"NO","SI") -> SI | T49: =IF($S49="NO","NO APLICA",MAX(CEILING(($O49*(1-Configuración!$B$2))/Configuración!$B$4,Configuración!$B$6),Configuración!$B$5)) -> 420 | U49: =IF($T49="NO APLICA","NO APLICA",$T49*Configuración!$B$4) -> 5040 | V49: =MAX(CEILING($O49/Configuración!$B$9,Configuración!$B$6),Configuración!$B$5) -> 130 | W49: Activo | X49: 46079
A50: =IF(OR(E50="",F50="",G50=""),"",E50&"-"&F50&"-"&G50&"-"&TEXT(COUNTIFS($E$2:E50,E50,$F$2:F50,F50,$G$2:G50,G50),"000")) -> ELE-BATI-ALU-001 | B50: Electrodomésticos | C50: Batidora | D50: Alumino | E50: =_xlfn.XLOOKUP(B50,Configuración!A:A,Configuración!B:B,"") -> ELE | F50: {=IF($C50="","",_xlfn.XLOOKUP(1,(Configuración!D:D=$B50)*(Configuración!E:E=$C50),Configuración!F:F,""))} -> BATI | G50: =IF($D50="","",_xlfn.XLOOKUP($D50,Configuración!H:H,Configuración!I:I,"")) -> ALU | H50: Batidora de mano con tazón 3L | I50: Batidora 3L | J50: RCA | L50: 1820 | M50: =MAX(CEILING(L50/4,10),100) -> 460 | N50: =M50*4 -> 1840 | O50: 2600 | P50: =IF($O50<Configuración!$B$7,"NO","SI") -> SI | Q50: =IF($P50="NO","NO APLICA",MAX(CEILING(($O50*(1-Configuración!$B$2))/Configuración!$B$3,Configuración!$B$6),Configuración!$B$5)) -> 260 | R50: =IF($Q50="NO APLICA","NO APLICA",$Q50*Configuración!$B$3) -> 2080 | S50: =IF($O50<Configuración!$B$8,"NO","SI") -> NO | T50: =IF($S50="NO","NO APLICA",MAX(CEILING(($O50*(1-Configuración!$B$2))/Configuración!$B$4,Configuración!$B$6),Configuración!$B$5)) -> NO APLICA | U50: =IF($T50="NO APLICA","NO APLICA",$T50*Configuración!$B$4) -> NO APLICA | V50: =MAX(CEILING($O50/Configuración!$B$9,Configuración!$B$6),Configuración!$B$5) -> 100 | W50: Activo | X50: 46079
A51: =IF(OR(E51="",F51="",G51=""),"",E51&"-"&F51&"-"&G51&"-"&TEXT(COUNTIFS($E$2:E51,E51,$F$2:F51,F51,$G$2:G51,G51),"000")) -> ELC-BOC-PSL-001 | B51: Electrónica | C51: Bocina | D51: Plástico | E51: =_xlfn.XLOOKUP(B51,Configuración!A:A,Configuración!B:B,"") -> ELC | F51: {=IF($C51="","",_xlfn.XLOOKUP(1,(Configuración!D:D=$B51)*(Configuración!E:E=$C51),Configuración!F:F,""))} -> BOC | G51: =IF($D51="","",_xlfn.XLOOKUP($D51,Configuración!H:H,Configuración!I:I,"")) -> PSL | H51: Bocina 15" 7515 | I51: Bocina 15" 7515 | J51: Káiser | L51: 4200 | M51: =MAX(CEILING(L51/4,10),100) -> 1050 | N51: =M51*4 -> 4200 | O51: 6000 | P51: =IF($O51<Configuración!$B$7,"NO","SI") -> SI | Q51: =IF($P51="NO","NO APLICA",MAX(CEILING(($O51*(1-Configuración!$B$2))/Configuración!$B$3,Configuración!$B$6),Configuración!$B$5)) -> 600 | R51: =IF($Q51="NO APLICA","NO APLICA",$Q51*Configuración!$B$3) -> 4800 | S51: =IF($O51<Configuración!$B$8,"NO","SI") -> SI | T51: =IF($S51="NO","NO APLICA",MAX(CEILING(($O51*(1-Configuración!$B$2))/Configuración!$B$4,Configuración!$B$6),Configuración!$B$5)) -> 400 | U51: =IF($T51="NO APLICA","NO APLICA",$T51*Configuración!$B$4) -> 4800 | V51: =MAX(CEILING($O51/Configuración!$B$9,Configuración!$B$6),Configuración!$B$5) -> 120 | W51: Activo | X51: 46079
A52: =IF(OR(E52="",F52="",G52=""),"",E52&"-"&F52&"-"&G52&"-"&TEXT(COUNTIFS($E$2:E52,E52,$F$2:F52,F52,$G$2:G52,G52),"000")) -> COC-BUD-TF-001 | B52: Cocina | C52: Budinera | D52: Triple Fuerte | E52: =_xlfn.XLOOKUP(B52,Configuración!A:A,Configuración!B:B,"") -> COC | F52: {=IF($C52="","",_xlfn.XLOOKUP(1,(Configuración!D:D=$B52)*(Configuración!E:E=$C52),Configuración!F:F,""))} -> BUD | G52: =IF($D52="","",_xlfn.XLOOKUP($D52,Configuración!H:H,Configuración!I:I,"")) -> TF | H52: Budinera 55 cm triple fuerte (TF) | I52: Budinera 55cm TF | J52: El abuelo | K52: listo | L52: 3500 | M52: =MAX(CEILING(L52/4,10),100) -> 880 | N52: =M52*4 -> 3520 | O52: 5000 | P52: =IF($O52<Configuración!$B$7,"NO","SI") -> SI | Q52: =IF($P52="NO","NO APLICA",MAX(CEILING(($O52*(1-Configuración!$B$2))/Configuración!$B$3,Configuración!$B$6),Configuración!$B$5)) -> 500 | R52: =IF($Q52="NO APLICA","NO APLICA",$Q52*Configuración!$B$3) -> 4000 | S52: =IF($O52<Configuración!$B$8,"NO","SI") -> SI | T52: =IF($S52="NO","NO APLICA",MAX(CEILING(($O52*(1-Configuración!$B$2))/Configuración!$B$4,Configuración!$B$6),Configuración!$B$5)) -> 340 | U52: =IF($T52="NO APLICA","NO APLICA",$T52*Configuración!$B$4) -> 4080 | V52: =MAX(CEILING($O52/Configuración!$B$9,Configuración!$B$6),Configuración!$B$5) -> 100 | W52: Activo | X52: 46080
A53: =IF(OR(E53="",F53="",G53=""),"",E53&"-"&F53&"-"&G53&"-"&TEXT(COUNTIFS($E$2:E53,E53,$F$2:F53,F53,$G$2:G53,G53),"000")) -> COC-BUD-ALU-001 | B53: Cocina | C53: Budinera | D53: Alumino | E53: =_xlfn.XLOOKUP(B53,Configuración!A:A,Configuración!B:B,"") -> COC | F53: {=IF($C53="","",_xlfn.XLOOKUP(1,(Configuración!D:D=$B53)*(Configuración!E:E=$C53),Configuración!F:F,""))} -> BUD | G53: =IF($D53="","",_xlfn.XLOOKUP($D53,Configuración!H:H,Configuración!I:I,"")) -> ALU | H53: Budinera 55cm color | I53: Budinera 55cm color | J53: El abuelo | K53: listo | L53: 1820 | M53: =MAX(CEILING(L53/4,10),100) -> 460 | N53: =M53*4 -> 1840 | O53: 2600 | P53: =IF($O53<Configuración!$B$7,"NO","SI") -> SI | Q53: =IF($P53="NO","NO APLICA",MAX(CEILING(($O53*(1-Configuración!$B$2))/Configuración!$B$3,Configuración!$B$6),Configuración!$B$5)) -> 260 | R53: =IF($Q53="NO APLICA","NO APLICA",$Q53*Configuración!$B$3) -> 2080 | S53: =IF($O53<Configuración!$B$8,"NO","SI") -> NO | T53: =IF($S53="NO","NO APLICA",MAX(CEILING(($O53*(1-Configuración!$B$2))/Configuración!$B$4,Configuración!$B$6),Configuración!$B$5)) -> NO APLICA | U53: =IF($T53="NO APLICA","NO APLICA",$T53*Configuración!$B$4) -> NO APLICA | V53: =MAX(CEILING($O53/Configuración!$B$9,Configuración!$B$6),Configuración!$B$5) -> 100 | W53: Activo | X53: 46079
A54: =IF(OR(E54="",F54="",G54=""),"",E54&"-"&F54&"-"&G54&"-"&TEXT(COUNTIFS($E$2:E54,E54,$F$2:F54,F54,$G$2:G54,G54),"000")) -> COC-BUD-TF-002 | B54: Cocina | C54: Budinera | D54: Triple Fuerte | E54: =_xlfn.XLOOKUP(B54,Configuración!A:A,Configuración!B:B,"") -> COC | F54: {=IF($C54="","",_xlfn.XLOOKUP(1,(Configuración!D:D=$B54)*(Configuración!E:E=$C54),Configuración!F:F,""))} -> BUD | G54: =IF($D54="","",_xlfn.XLOOKUP($D54,Configuración!H:H,Configuración!I:I,"")) -> TF | H54: Budinera 55cm triple fuerte color (TF) | I54: Budinera 55cm triple fuerte color (TF) | J54: El abuelo | K54: listo | L54: 3850 | M54: =MAX(CEILING(L54/4,10),100) -> 970 | N54: =M54*4 -> 3880 | O54: 5500 | P54: =IF($O54<Configuración!$B$7,"NO","SI") -> SI | Q54: =IF($P54="NO","NO APLICA",MAX(CEILING(($O54*(1-Configuración!$B$2))/Configuración!$B$3,Configuración!$B$6),Configuración!$B$5)) -> 550 | R54: =IF($Q54="NO APLICA","NO APLICA",$Q54*Configuración!$B$3) -> 4400 | S54: =IF($O54<Configuración!$B$8,"NO","SI") -> SI | T54: =IF($S54="NO","NO APLICA",MAX(CEILING(($O54*(1-Configuración!$B$2))/Configuración!$B$4,Configuración!$B$6),Configuración!$B$5)) -> 370 | U54: =IF($T54="NO APLICA","NO APLICA",$T54*Configuración!$B$4) -> 4440 | V54: =MAX(CEILING($O54/Configuración!$B$9,Configuración!$B$6),Configuración!$B$5) -> 110 | W54: Activo | X54: 46079
A55: =IF(OR(E55="",F55="",G55=""),"",E55&"-"&F55&"-"&G55&"-"&TEXT(COUNTIFS($E$2:E55,E55,$F$2:F55,F55,$G$2:G55,G55),"000")) -> COC-BUD-ALUT-001 | B55: Cocina | C55: Budinera | D55: Alumino y Teflon | E55: =_xlfn.XLOOKUP(B55,Configuración!A:A,Configuración!B:B,"") -> COC | F55: {=IF($C55="","",_xlfn.XLOOKUP(1,(Configuración!D:D=$B55)*(Configuración!E:E=$C55),Configuración!F:F,""))} -> BUD | G55: =IF($D55="","",_xlfn.XLOOKUP($D55,Configuración!H:H,Configuración!I:I,"")) -> ALUT | H55: Budinera de teflón 40cm | I55: Budinera de teflón 40cm | J55: Lamex | K55: listo | L55: 2100 | M55: =MAX(CEILING(L55/4,10),100) -> 530 | N55: =M55*4 -> 2120 | O55: 3000 | P55: =IF($O55<Configuración!$B$7,"NO","SI") -> SI | Q55: =IF($P55="NO","NO APLICA",MAX(CEILING(($O55*(1-Configuración!$B$2))/Configuración!$B$3,Configuración!$B$6),Configuración!$B$5)) -> 300 | R55: =IF($Q55="NO APLICA","NO APLICA",$Q55*Configuración!$B$3) -> 2400 | S55: =IF($O55<Configuración!$B$8,"NO","SI") -> SI | T55: =IF($S55="NO","NO APLICA",MAX(CEILING(($O55*(1-Configuración!$B$2))/Configuración!$B$4,Configuración!$B$6),Configuración!$B$5)) -> 200 | U55: =IF($T55="NO APLICA","NO APLICA",$T55*Configuración!$B$4) -> 2400 | V55: =MAX(CEILING($O55/Configuración!$B$9,Configuración!$B$6),Configuración!$B$5) -> 100 | W55: Activo | X55: 46079
A56: =IF(OR(E56="",F56="",G56=""),"",E56&"-"&F56&"-"&G56&"-"&TEXT(COUNTIFS($E$2:E56,E56,$F$2:F56,F56,$G$2:G56,G56),"000")) -> COC-BUD-TF-003 | B56: Cocina | C56: Budinera | D56: Triple Fuerte | E56: =_xlfn.XLOOKUP(B56,Configuración!A:A,Configuración!B:B,"") -> COC | F56: {=IF($C56="","",_xlfn.XLOOKUP(1,(Configuración!D:D=$B56)*(Configuración!E:E=$C56),Configuración!F:F,""))} -> BUD | G56: =IF($D56="","",_xlfn.XLOOKUP($D56,Configuración!H:H,Configuración!I:I,"")) -> TF | H56: Budinera triple fuerte 40cm (TF) | I56: Budinera triple fuerte 40cm (TF) | J56: El abuelo | K56: listo | L56: 1610 | M56: =MAX(CEILING(L56/4,10),100) -> 410 | N56: =M56*4 -> 1640 | O56: 2300 | P56: =IF($O56<Configuración!$B$7,"NO","SI") -> SI | Q56: =IF($P56="NO","NO APLICA",MAX(CEILING(($O56*(1-Configuración!$B$2))/Configuración!$B$3,Configuración!$B$6),Configuración!$B$5)) -> 230 | R56: =IF($Q56="NO APLICA","NO APLICA",$Q56*Configuración!$B$3) -> 1840 | S56: =IF($O56<Configuración!$B$8,"NO","SI") -> NO | T56: =IF($S56="NO","NO APLICA",MAX(CEILING(($O56*(1-Configuración!$B$2))/Configuración!$B$4,Configuración!$B$6),Configuración!$B$5)) -> NO APLICA | U56: =IF($T56="NO APLICA","NO APLICA",$T56*Configuración!$B$4) -> NO APLICA | V56: =MAX(CEILING($O56/Configuración!$B$9,Configuración!$B$6),Configuración!$B$5) -> 100 | W56: Activo | X56: 46079
A57: =IF(OR(E57="",F57="",G57=""),"",E57&"-"&F57&"-"&G57&"-"&TEXT(COUNTIFS($E$2:E57,E57,$F$2:F57,F57,$G$2:G57,G57),"000")) -> MOB-BUR-TUB-001 | B57: Mobiliario | C57: Burro | D57: Tubular | E57: =_xlfn.XLOOKUP(B57,Configuración!A:A,Configuración!B:B,"") -> MOB | F57: {=IF($C57="","",_xlfn.XLOOKUP(1,(Configuración!D:D=$B57)*(Configuración!E:E=$C57),Configuración!F:F,""))} -> BUR | G57: =IF($D57="","",_xlfn.XLOOKUP($D57,Configuración!H:H,Configuración!I:I,"")) -> TUB | H57: Burro para planchar tubular | I57: Burro para planchar tubular | J57: D.C | L57: 1400 | M57: =MAX(CEILING(L57/4,10),100) -> 350 | N57: =M57*4 -> 1400 | O57: 2000 | P57: =IF($O57<Configuración!$B$7,"NO","SI") -> SI | Q57: =IF($P57="NO","NO APLICA",MAX(CEILING(($O57*(1-Configuración!$B$2))/Configuración!$B$3,Configuración!$B$6),Configuración!$B$5)) -> 200 | R57: =IF($Q57="NO APLICA","NO APLICA",$Q57*Configuración!$B$3) -> 1600 | S57: =IF($O57<Configuración!$B$8,"NO","SI") -> NO | T57: =IF($S57="NO","NO APLICA",MAX(CEILING(($O57*(1-Configuración!$B$2))/Configuración!$B$4,Configuración!$B$6),Configuración!$B$5)) -> NO APLICA | U57: =IF($T57="NO APLICA","NO APLICA",$T57*Configuración!$B$4) -> NO APLICA | V57: =MAX(CEILING($O57/Configuración!$B$9,Configuración!$B$6),Configuración!$B$5) -> 100 | W57: Activo | X57: 46079
A58: =IF(OR(E58="",F58="",G58=""),"",E58&"-"&F58&"-"&G58&"-"&TEXT(COUNTIFS($E$2:E58,E58,$F$2:F58,F58,$G$2:G58,G58),"000")) -> MOB-CAJ-PSL-001 | B58: Mobiliario | C58: Cajonera | D58: Plástico | E58: =_xlfn.XLOOKUP(B58,Configuración!A:A,Configuración!B:B,"") -> MOB | F58: {=IF($C58="","",_xlfn.XLOOKUP(1,(Configuración!D:D=$B58)*(Configuración!E:E=$C58),Configuración!F:F,""))} -> CAJ | G58: =IF($D58="","",_xlfn.XLOOKUP($D58,Configuración!H:H,Configuración!I:I,"")) -> PSL | H58: Cajonera 3 cajones Jumbo | I58: Cajonera 3 cajones Jumbo | J58: Lara | L58: 2450 | M58: =MAX(CEILING(L58/4,10),100) -> 620 | N58: =M58*4 -> 2480 | O58: 3500 | P58: =IF($O58<Configuración!$B$7,"NO","SI") -> SI | Q58: =IF($P58="NO","NO APLICA",MAX(CEILING(($O58*(1-Configuración!$B$2))/Configuración!$B$3,Configuración!$B$6),Configuración!$B$5)) -> 350 | R58: =IF($Q58="NO APLICA","NO APLICA",$Q58*Configuración!$B$3) -> 2800 | S58: =IF($O58<Configuración!$B$8,"NO","SI") -> SI | T58: =IF($S58="NO","NO APLICA",MAX(CEILING(($O58*(1-Configuración!$B$2))/Configuración!$B$4,Configuración!$B$6),Configuración!$B$5)) -> 240 | U58: =IF($T58="NO APLICA","NO APLICA",$T58*Configuración!$B$4) -> 2880 | V58: =MAX(CEILING($O58/Configuración!$B$9,Configuración!$B$6),Configuración!$B$5) -> 100 | W58: Activo | X58: 46079
A59: =IF(OR(E59="",F59="",G59=""),"",E59&"-"&F59&"-"&G59&"-"&TEXT(COUNTIFS($E$2:E59,E59,$F$2:F59,F59,$G$2:G59,G59),"000")) -> MOB-CAJ-PSL-002 | B59: Mobiliario | C59: Cajonera | D59: Plástico | E59: =_xlfn.XLOOKUP(B59,Configuración!A:A,Configuración!B:B,"") -> MOB | F59: {=IF($C59="","",_xlfn.XLOOKUP(1,(Configuración!D:D=$B59)*(Configuración!E:E=$C59),Configuración!F:F,""))} -> CAJ | G59: =IF($D59="","",_xlfn.XLOOKUP($D59,Configuración!H:H,Configuración!I:I,"")) -> PSL | H59: Cajonera 4 cajones | I59: Cajonera 4 cajones | J59: Lara | L59: 2450 | M59: =MAX(CEILING(L59/4,10),100) -> 620 | N59: =M59*4 -> 2480 | O59: 3500 | P59: =IF($O59<Configuración!$B$7,"NO","SI") -> SI | Q59: =IF($P59="NO","NO APLICA",MAX(CEILING(($O59*(1-Configuración!$B$2))/Configuración!$B$3,Configuración!$B$6),Configuración!$B$5)) -> 350 | R59: =IF($Q59="NO APLICA","NO APLICA",$Q59*Configuración!$B$3) -> 2800 | S59: =IF($O59<Configuración!$B$8,"NO","SI") -> SI | T59: =IF($S59="NO","NO APLICA",MAX(CEILING(($O59*(1-Configuración!$B$2))/Configuración!$B$4,Configuración!$B$6),Configuración!$B$5)) -> 240 | U59: =IF($T59="NO APLICA","NO APLICA",$T59*Configuración!$B$4) -> 2880 | V59: =MAX(CEILING($O59/Configuración!$B$9,Configuración!$B$6),Configuración!$B$5) -> 100 | W59: Activo | X59: 46079
A60: =IF(OR(E60="",F60="",G60=""),"",E60&"-"&F60&"-"&G60&"-"&TEXT(COUNTIFS($E$2:E60,E60,$F$2:F60,F60,$G$2:G60,G60),"000")) -> MOB-CAJ-PSL-003 | B60: Mobiliario | C60: Cajonera | D60: Plástico | E60: =_xlfn.XLOOKUP(B60,Configuración!A:A,Configuración!B:B,"") -> MOB | F60: {=IF($C60="","",_xlfn.XLOOKUP(1,(Configuración!D:D=$B60)*(Configuración!E:E=$C60),Configuración!F:F,""))} -> CAJ | G60: =IF($D60="","",_xlfn.XLOOKUP($D60,Configuración!H:H,Configuración!I:I,"")) -> PSL | H60: Cajonera 5 cajones | I60: Cajonera 5 cajones | J60: Lara | L60: 2520 | M60: =MAX(CEILING(L60/4,10),100) -> 630 | N60: =M60*4 -> 2520 | O60: 3600 | P60: =IF($O60<Configuración!$B$7,"NO","SI") -> SI | Q60: =IF($P60="NO","NO APLICA",MAX(CEILING(($O60*(1-Configuración!$B$2))/Configuración!$B$3,Configuración!$B$6),Configuración!$B$5)) -> 360 | R60: =IF($Q60="NO APLICA","NO APLICA",$Q60*Configuración!$B$3) -> 2880 | S60: =IF($O60<Configuración!$B$8,"NO","SI") -> SI | T60: =IF($S60="NO","NO APLICA",MAX(CEILING(($O60*(1-Configuración!$B$2))/Configuración!$B$4,Configuración!$B$6),Configuración!$B$5)) -> 240 | U60: =IF($T60="NO APLICA","NO APLICA",$T60*Configuración!$B$4) -> 2880 | V60: =MAX(CEILING($O60/Configuración!$B$9,Configuración!$B$6),Configuración!$B$5) -> 100 | W60: Activo | X60: 46079
A61: =IF(OR(E61="",F61="",G61=""),"",E61&"-"&F61&"-"&G61&"-"&TEXT(COUNTIFS($E$2:E61,E61,$F$2:F61,F61,$G$2:G61,G61),"000")) -> MOB-CAJ-MAD-001 | B61: Mobiliario | C61: Cajonera | D61: Madera | E61: =_xlfn.XLOOKUP(B61,Configuración!A:A,Configuración!B:B,"") -> MOB | F61: {=IF($C61="","",_xlfn.XLOOKUP(1,(Configuración!D:D=$B61)*(Configuración!E:E=$C61),Configuración!F:F,""))} -> CAJ | G61: =IF($D61="","",_xlfn.XLOOKUP($D61,Configuración!H:H,Configuración!I:I,"")) -> MAD | H61: Cajonera de 10 cajones | I61: Cajonera de 10 cajones | J61: Madera D.C | L61: 6300 | M61: =MAX(CEILING(L61/4,10),100) -> 1580 | N61: =M61*4 -> 6320 | O61: 9000 | P61: =IF($O61<Configuración!$B$7,"NO","SI") -> SI | Q61: =IF($P61="NO","NO APLICA",MAX(CEILING(($O61*(1-Configuración!$B$2))/Configuración!$B$3,Configuración!$B$6),Configuración!$B$5)) -> 900 | R61: =IF($Q61="NO APLICA","NO APLICA",$Q61*Configuración!$B$3) -> 7200 | S61: =IF($O61<Configuración!$B$8,"NO","SI") -> SI | T61: =IF($S61="NO","NO APLICA",MAX(CEILING(($O61*(1-Configuración!$B$2))/Configuración!$B$4,Configuración!$B$6),Configuración!$B$5)) -> 600 | U61: =IF($T61="NO APLICA","NO APLICA",$T61*Configuración!$B$4) -> 7200 | V61: =MAX(CEILING($O61/Configuración!$B$9,Configuración!$B$6),Configuración!$B$5) -> 180 | W61: Activo | X61: 46079
A62: =IF(OR(E62="",F62="",G62=""),"",E62&"-"&F62&"-"&G62&"-"&TEXT(COUNTIFS($E$2:E62,E62,$F$2:F62,F62,$G$2:G62,G62),"000")) -> MOB-CAJ-MAD-002 | B62: Mobiliario | C62: Cajonera | D62: Madera | E62: =_xlfn.XLOOKUP(B62,Configuración!A:A,Configuración!B:B,"") -> MOB | F62: {=IF($C62="","",_xlfn.XLOOKUP(1,(Configuración!D:D=$B62)*(Configuración!E:E=$C62),Configuración!F:F,""))} -> CAJ | G62: =IF($D62="","",_xlfn.XLOOKUP($D62,Configuración!H:H,Configuración!I:I,"")) -> MAD | H62: Cajonera de 10 cajones con chapa | I62: Cajonera de 10 cajones con chapa | J62: Madera D.C | L62: 6650 | M62: =MAX(CEILING(L62/4,10),100) -> 1670 | N62: =M62*4 -> 6680 | O62: 9500 | P62: =IF($O62<Configuración!$B$7,"NO","SI") -> SI | Q62: =IF($P62="NO","NO APLICA",MAX(CEILING(($O62*(1-Configuración!$B$2))/Configuración!$B$3,Configuración!$B$6),Configuración!$B$5)) -> 950 | R62: =IF($Q62="NO APLICA","NO APLICA",$Q62*Configuración!$B$3) -> 7600 | S62: =IF($O62<Configuración!$B$8,"NO","SI") -> SI | T62: =IF($S62="NO","NO APLICA",MAX(CEILING(($O62*(1-Configuración!$B$2))/Configuración!$B$4,Configuración!$B$6),Configuración!$B$5)) -> 640 | U62: =IF($T62="NO APLICA","NO APLICA",$T62*Configuración!$B$4) -> 7680 | V62: =MAX(CEILING($O62/Configuración!$B$9,Configuración!$B$6),Configuración!$B$5) -> 190 | W62: Activo | X62: 46079
A63: =IF(OR(E63="",F63="",G63=""),"",E63&"-"&F63&"-"&G63&"-"&TEXT(COUNTIFS($E$2:E63,E63,$F$2:F63,F63,$G$2:G63,G63),"000")) -> MOB-CAJ-MAD-003 | B63: Mobiliario | C63: Cajonera | D63: Madera | E63: =_xlfn.XLOOKUP(B63,Configuración!A:A,Configuración!B:B,"") -> MOB | F63: {=IF($C63="","",_xlfn.XLOOKUP(1,(Configuración!D:D=$B63)*(Configuración!E:E=$C63),Configuración!F:F,""))} -> CAJ | G63: =IF($D63="","",_xlfn.XLOOKUP($D63,Configuración!H:H,Configuración!I:I,"")) -> MAD | H63: Cajonera de 5 cajones | I63: Cajonera de 5 cajones | J63: Madera D.C | L63: 3500 | M63: =MAX(CEILING(L63/4,10),100) -> 880 | N63: =M63*4 -> 3520 | O63: 5000 | P63: =IF($O63<Configuración!$B$7,"NO","SI") -> SI | Q63: =IF($P63="NO","NO APLICA",MAX(CEILING(($O63*(1-Configuración!$B$2))/Configuración!$B$3,Configuración!$B$6),Configuración!$B$5)) -> 500 | R63: =IF($Q63="NO APLICA","NO APLICA",$Q63*Configuración!$B$3) -> 4000 | S63: =IF($O63<Configuración!$B$8,"NO","SI") -> SI | T63: =IF($S63="NO","NO APLICA",MAX(CEILING(($O63*(1-Configuración!$B$2))/Configuración!$B$4,Configuración!$B$6),Configuración!$B$5)) -> 340 | U63: =IF($T63="NO APLICA","NO APLICA",$T63*Configuración!$B$4) -> 4080 | V63: =MAX(CEILING($O63/Configuración!$B$9,Configuración!$B$6),Configuración!$B$5) -> 100 | W63: Activo | X63: 46079
A64: =IF(OR(E64="",F64="",G64=""),"",E64&"-"&F64&"-"&G64&"-"&TEXT(COUNTIFS($E$2:E64,E64,$F$2:F64,F64,$G$2:G64,G64),"000")) -> MOB-CAJ-MAD-004 | B64: Mobiliario | C64: Cajonera | D64: Madera | E64: =_xlfn.XLOOKUP(B64,Configuración!A:A,Configuración!B:B,"") -> MOB | F64: {=IF($C64="","",_xlfn.XLOOKUP(1,(Configuración!D:D=$B64)*(Configuración!E:E=$C64),Configuración!F:F,""))} -> CAJ | G64: =IF($D64="","",_xlfn.XLOOKUP($D64,Configuración!H:H,Configuración!I:I,"")) -> MAD | H64: Cajonera de 5 cajones con chapa | I64: Cajonera de 5 cajones con chapa | J64: Madera D.C | L64: 3850 | M64: =MAX(CEILING(L64/4,10),100) -> 970 | N64: =M64*4 -> 3880 | O64: 5500 | P64: =IF($O64<Configuración!$B$7,"NO","SI") -> SI | Q64: =IF($P64="NO","NO APLICA",MAX(CEILING(($O64*(1-Configuración!$B$2))/Configuración!$B$3,Configuración!$B$6),Configuración!$B$5)) -> 550 | R64: =IF($Q64="NO APLICA","NO APLICA",$Q64*Configuración!$B$3) -> 4400 | S64: =IF($O64<Configuración!$B$8,"NO","SI") -> SI | T64: =IF($S64="NO","NO APLICA",MAX(CEILING(($O64*(1-Configuración!$B$2))/Configuración!$B$4,Configuración!$B$6),Configuración!$B$5)) -> 370 | U64: =IF($T64="NO APLICA","NO APLICA",$T64*Configuración!$B$4) -> 4440 | V64: =MAX(CEILING($O64/Configuración!$B$9,Configuración!$B$6),Configuración!$B$5) -> 110 | W64: Activo | X64: 46079
A65: =IF(OR(E65="",F65="",G65=""),"",E65&"-"&F65&"-"&G65&"-"&TEXT(COUNTIFS($E$2:E65,E65,$F$2:F65,F65,$G$2:G65,G65),"000")) -> MOB-CAM-TUB-001 | B65: Mobiliario | C65: Cama | D65: Tubular | E65: =_xlfn.XLOOKUP(B65,Configuración!A:A,Configuración!B:B,"") -> MOB | F65: {=IF($C65="","",_xlfn.XLOOKUP(1,(Configuración!D:D=$B65)*(Configuración!E:E=$C65),Configuración!F:F,""))} -> CAM | G65: =IF($D65="","",_xlfn.XLOOKUP($D65,Configuración!H:H,Configuración!I:I,"")) -> TUB | H65: Cama individual tapizada tubular | I65: Cama individual tapizada tubular | J65: D.C | L65: 3150 | M65: =MAX(CEILING(L65/4,10),100) -> 790 | N65: =M65*4 -> 3160 | O65: 4500 | P65: =IF($O65<Configuración!$B$7,"NO","SI") -> SI | Q65: =IF($P65="NO","NO APLICA",MAX(CEILING(($O65*(1-Configuración!$B$2))/Configuración!$B$3,Configuración!$B$6),Configuración!$B$5)) -> 450 | R65: =IF($Q65="NO APLICA","NO APLICA",$Q65*Configuración!$B$3) -> 3600 | S65: =IF($O65<Configuración!$B$8,"NO","SI") -> SI | T65: =IF($S65="NO","NO APLICA",MAX(CEILING(($O65*(1-Configuración!$B$2))/Configuración!$B$4,Configuración!$B$6),Configuración!$B$5)) -> 300 | U65: =IF($T65="NO APLICA","NO APLICA",$T65*Configuración!$B$4) -> 3600 | V65: =MAX(CEILING($O65/Configuración!$B$9,Configuración!$B$6),Configuración!$B$5) -> 100 | W65: Activo | X65: 46079
A66: =IF(OR(E66="",F66="",G66=""),"",E66&"-"&F66&"-"&G66&"-"&TEXT(COUNTIFS($E$2:E66,E66,$F$2:F66,F66,$G$2:G66,G66),"000")) -> MOB-CAM-TUB-002 | B66: Mobiliario | C66: Cama | D66: Tubular | E66: =_xlfn.XLOOKUP(B66,Configuración!A:A,Configuración!B:B,"") -> MOB | F66: {=IF($C66="","",_xlfn.XLOOKUP(1,(Configuración!D:D=$B66)*(Configuración!E:E=$C66),Configuración!F:F,""))} -> CAM | G66: =IF($D66="","",_xlfn.XLOOKUP($D66,Configuración!H:H,Configuración!I:I,"")) -> TUB | H66: Cama matrimonial tapizada tubular | I66: Cama matrimonial tapizada tubular | J66: D.C | L66: 3500 | M66: =MAX(CEILING(L66/4,10),100) -> 880 | N66: =M66*4 -> 3520 | O66: 5000 | P66: =IF($O66<Configuración!$B$7,"NO","SI") -> SI | Q66: =IF($P66="NO","NO APLICA",MAX(CEILING(($O66*(1-Configuración!$B$2))/Configuración!$B$3,Configuración!$B$6),Configuración!$B$5)) -> 500 | R66: =IF($Q66="NO APLICA","NO APLICA",$Q66*Configuración!$B$3) -> 4000 | S66: =IF($O66<Configuración!$B$8,"NO","SI") -> SI | T66: =IF($S66="NO","NO APLICA",MAX(CEILING(($O66*(1-Configuración!$B$2))/Configuración!$B$4,Configuración!$B$6),Configuración!$B$5)) -> 340 | U66: =IF($T66="NO APLICA","NO APLICA",$T66*Configuración!$B$4) -> 4080 | V66: =MAX(CEILING($O66/Configuración!$B$9,Configuración!$B$6),Configuración!$B$5) -> 100 | W66: Activo | X66: 46079
A67: =IF(OR(E67="",F67="",G67=""),"",E67&"-"&F67&"-"&G67&"-"&TEXT(COUNTIFS($E$2:E67,E67,$F$2:F67,F67,$G$2:G67,G67),"000")) | B67: Mobiliario | C67: Base de Cama | D67: Tubular | E67: =_xlfn.XLOOKUP(B67,Configuración!A:A,Configuración!B:B,"") -> MOB | F67: {=IF($C67="","",_xlfn.XLOOKUP(1,(Configuración!D:D=$B67)*(Configuración!E:E=$C67),Configuración!F:F,""))} | G67: =IF($D67="","",_xlfn.XLOOKUP($D67,Configuración!H:H,Configuración!I:I,"")) -> TUB | H67: Cama tubular king size | I67: Cama tubular king size | J67: D.C | L67: 7700 | M67: =MAX(CEILING(L67/4,10),100) -> 1930 | N67: =M67*4 -> 7720 | O67: 10995 | P67: =IF($O67<Configuración!$B$7,"NO","SI") -> SI | Q67: =IF($P67="NO","NO APLICA",MAX(CEILING(($O67*(1-Configuración!$B$2))/Configuración!$B$3,Configuración!$B$6),Configuración!$B$5)) -> 1100 | R67: =IF($Q67="NO APLICA","NO APLICA",$Q67*Configuración!$B$3) -> 8800 | S67: =IF($O67<Configuración!$B$8,"NO","SI") -> SI | T67: =IF($S67="NO","NO APLICA",MAX(CEILING(($O67*(1-Configuración!$B$2))/Configuración!$B$4,Configuración!$B$6),Configuración!$B$5)) -> 740 | U67: =IF($T67="NO APLICA","NO APLICA",$T67*Configuración!$B$4) -> 8880 | V67: =MAX(CEILING($O67/Configuración!$B$9,Configuración!$B$6),Configuración!$B$5) -> 220
A68: =IF(OR(E68="",F68="",G68=""),"",E68&"-"&F68&"-"&G68&"-"&TEXT(COUNTIFS($E$2:E68,E68,$F$2:F68,F68,$G$2:G68,G68),"000")) -> COC-CAZ-ALU-001 | B68: Cocina | C68: Cazo | D68: Alumino | E68: =_xlfn.XLOOKUP(B68,Configuración!A:A,Configuración!B:B,"") -> COC | F68: {=IF($C68="","",_xlfn.XLOOKUP(1,(Configuración!D:D=$B68)*(Configuración!E:E=$C68),Configuración!F:F,""))} -> CAZ | G68: =IF($D68="","",_xlfn.XLOOKUP($D68,Configuración!H:H,Configuración!I:I,"")) -> ALU | H68: Cazo 100cm | I68: Cazo 100cm | J68: El abuelo | K68: listo | L68: 2450 | M68: =MAX(CEILING(L68/4,10),100) -> 620 | N68: =M68*4 -> 2480 | O68: 3500 | P68: =IF($O68<Configuración!$B$7,"NO","SI") -> SI | Q68: =IF($P68="NO","NO APLICA",MAX(CEILING(($O68*(1-Configuración!$B$2))/Configuración!$B$3,Configuración!$B$6),Configuración!$B$5)) -> 350 | R68: =IF($Q68="NO APLICA","NO APLICA",$Q68*Configuración!$B$3) -> 2800 | S68: =IF($O68<Configuración!$B$8,"NO","SI") -> SI | T68: =IF($S68="NO","NO APLICA",MAX(CEILING(($O68*(1-Configuración!$B$2))/Configuración!$B$4,Configuración!$B$6),Configuración!$B$5)) -> 240 | U68: =IF($T68="NO APLICA","NO APLICA",$T68*Configuración!$B$4) -> 2880 | V68: =MAX(CEILING($O68/Configuración!$B$9,Configuración!$B$6),Configuración!$B$5) -> 100 | W68: Activo | X68: 46079
A69: =IF(OR(E69="",F69="",G69=""),"",E69&"-"&F69&"-"&G69&"-"&TEXT(COUNTIFS($E$2:E69,E69,$F$2:F69,F69,$G$2:G69,G69),"000")) -> COC-CAZ-TF-001 | B69: Cocina | C69: Cazo | D69: Triple Fuerte | E69: =_xlfn.XLOOKUP(B69,Configuración!A:A,Configuración!B:B,"") -> COC | F69: {=IF($C69="","",_xlfn.XLOOKUP(1,(Configuración!D:D=$B69)*(Configuración!E:E=$C69),Configuración!F:F,""))} -> CAZ | G69: =IF($D69="","",_xlfn.XLOOKUP($D69,Configuración!H:H,Configuración!I:I,"")) -> TF | H69: Cazo 200cm triple fuerte (TF) | I69: Cazo 200cm triple fuerte (TF) | J69: El abuelo | K69: listo | L69: 4200 | M69: =MAX(CEILING(L69/4,10),100) -> 1050 | N69: =M69*4 -> 4200 | O69: 6000 | P69: =IF($O69<Configuración!$B$7,"NO","SI") -> SI | Q69: =IF($P69="NO","NO APLICA",MAX(CEILING(($O69*(1-Configuración!$B$2))/Configuración!$B$3,Configuración!$B$6),Configuración!$B$5)) -> 600 | R69: =IF($Q69="NO APLICA","NO APLICA",$Q69*Configuración!$B$3) -> 4800 | S69: =IF($O69<Configuración!$B$8,"NO","SI") -> SI | T69: =IF($S69="NO","NO APLICA",MAX(CEILING(($O69*(1-Configuración!$B$2))/Configuración!$B$4,Configuración!$B$6),Configuración!$B$5)) -> 400 | U69: =IF($T69="NO APLICA","NO APLICA",$T69*Configuración!$B$4) -> 4800 | V69: =MAX(CEILING($O69/Configuración!$B$9,Configuración!$B$6),Configuración!$B$5) -> 120 | W69: Activo | X69: 46079
A70: =IF(OR(E70="",F70="",G70=""),"",E70&"-"&F70&"-"&G70&"-"&TEXT(COUNTIFS($E$2:E70,E70,$F$2:F70,F70,$G$2:G70,G70),"000")) -> COC-CAZ-TF-002 | B70: Cocina | C70: Cazo | D70: Triple Fuerte | E70: =_xlfn.XLOOKUP(B70,Configuración!A:A,Configuración!B:B,"") -> COC | F70: {=IF($C70="","",_xlfn.XLOOKUP(1,(Configuración!D:D=$B70)*(Configuración!E:E=$C70),Configuración!F:F,""))} -> CAZ | G70: =IF($D70="","",_xlfn.XLOOKUP($D70,Configuración!H:H,Configuración!I:I,"")) -> TF | H70: Cazo 55cm | I70: Cazo 55cm | J70: El abuelo | K70: listo | L70: 2100 | M70: =MAX(CEILING(L70/4,10),100) -> 530 | N70: =M70*4 -> 2120 | O70: 3000 | P70: =IF($O70<Configuración!$B$7,"NO","SI") -> SI | Q70: =IF($P70="NO","NO APLICA",MAX(CEILING(($O70*(1-Configuración!$B$2))/Configuración!$B$3,Configuración!$B$6),Configuración!$B$5)) -> 300 | R70: =IF($Q70="NO APLICA","NO APLICA",$Q70*Configuración!$B$3) -> 2400 | S70: =IF($O70<Configuración!$B$8,"NO","SI") -> SI | T70: =IF($S70="NO","NO APLICA",MAX(CEILING(($O70*(1-Configuración!$B$2))/Configuración!$B$4,Configuración!$B$6),Configuración!$B$5)) -> 200 | U70: =IF($T70="NO APLICA","NO APLICA",$T70*Configuración!$B$4) -> 2400 | V70: =MAX(CEILING($O70/Configuración!$B$9,Configuración!$B$6),Configuración!$B$5) -> 100 | W70: Activo | X70: 46079
A71: =IF(OR(E71="",F71="",G71=""),"",E71&"-"&F71&"-"&G71&"-"&TEXT(COUNTIFS($E$2:E71,E71,$F$2:F71,F71,$G$2:G71,G71),"000")) -> COC-CAZ-ALU-002 | B71: Cocina | C71: Cazo | D71: Alumino | E71: =_xlfn.XLOOKUP(B71,Configuración!A:A,Configuración!B:B,"") -> COC | F71: {=IF($C71="","",_xlfn.XLOOKUP(1,(Configuración!D:D=$B71)*(Configuración!E:E=$C71),Configuración!F:F,""))} -> CAZ | G71: =IF($D71="","",_xlfn.XLOOKUP($D71,Configuración!H:H,Configuración!I:I,"")) -> ALU | H71: Cazo pallero 45cm | I71: Cazito pallero | J71: El abuelo | K71: Listo | L71: 1260 | M71: =MAX(CEILING(L71/4,10),100) -> 320 | N71: =M71*4 -> 1280 | O71: 1800 | P71: =IF($O71<Configuración!$B$7,"NO","SI") -> NO | Q71: =IF($P71="NO","NO APLICA",MAX(CEILING(($O71*(1-Configuración!$B$2))/Configuración!$B$3,Configuración!$B$6),Configuración!$B$5)) -> NO APLICA | R71: =IF($Q71="NO APLICA","NO APLICA",$Q71*Configuración!$B$3) -> NO APLICA | S71: =IF($O71<Configuración!$B$8,"NO","SI") -> NO | T71: =IF($S71="NO","NO APLICA",MAX(CEILING(($O71*(1-Configuración!$B$2))/Configuración!$B$4,Configuración!$B$6),Configuración!$B$5)) -> NO APLICA | U71: =IF($T71="NO APLICA","NO APLICA",$T71*Configuración!$B$4) -> NO APLICA | V71: =MAX(CEILING($O71/Configuración!$B$9,Configuración!$B$6),Configuración!$B$5) -> 100 | W71: Activo | X71: 46079
A72: =IF(OR(E72="",F72="",G72=""),"",E72&"-"&F72&"-"&G72&"-"&TEXT(COUNTIFS($E$2:E72,E72,$F$2:F72,F72,$G$2:G72,G72),"000")) -> COC-CAZ-ALU-003 | B72: Cocina | C72: Cazo | D72: Alumino | E72: =_xlfn.XLOOKUP(B72,Configuración!A:A,Configuración!B:B,"") -> COC | F72: {=IF($C72="","",_xlfn.XLOOKUP(1,(Configuración!D:D=$B72)*(Configuración!E:E=$C72),Configuración!F:F,""))} -> CAZ | G72: =IF($D72="","",_xlfn.XLOOKUP($D72,Configuración!H:H,Configuración!I:I,"")) -> ALU | H72: Cazo panal 55cm | I72: Cazo panal 55cm | J72: El abuelo | K72: Listo | L72: 1540 | M72: =MAX(CEILING(L72/4,10),100) -> 390 | N72: =M72*4 -> 1560 | O72: 2200 | P72: =IF($O72<Configuración!$B$7,"NO","SI") -> SI | Q72: =IF($P72="NO","NO APLICA",MAX(CEILING(($O72*(1-Configuración!$B$2))/Configuración!$B$3,Configuración!$B$6),Configuración!$B$5)) -> 220 | R72: =IF($Q72="NO APLICA","NO APLICA",$Q72*Configuración!$B$3) -> 1760 | S72: =IF($O72<Configuración!$B$8,"NO","SI") -> NO | T72: =IF($S72="NO","NO APLICA",MAX(CEILING(($O72*(1-Configuración!$B$2))/Configuración!$B$4,Configuración!$B$6),Configuración!$B$5)) -> NO APLICA | U72: =IF($T72="NO APLICA","NO APLICA",$T72*Configuración!$B$4) -> NO APLICA | V72: =MAX(CEILING($O72/Configuración!$B$9,Configuración!$B$6),Configuración!$B$5) -> 100 | W72: Activo | X72: 46079
A73: =IF(OR(E73="",F73="",G73=""),"",E73&"-"&F73&"-"&G73&"-"&TEXT(COUNTIFS($E$2:E73,E73,$F$2:F73,F73,$G$2:G73,G73),"000")) -> MOB-CAJ-MAD-005 | B73: Mobiliario | C73: Cajonera | D73: Madera | E73: =_xlfn.XLOOKUP(B73,Configuración!A:A,Configuración!B:B,"") -> MOB | F73: {=IF($C73="","",_xlfn.XLOOKUP(1,(Configuración!D:D=$B73)*(Configuración!E:E=$C73),Configuración!F:F,""))} -> CAJ | G73: =IF($D73="","",_xlfn.XLOOKUP($D73,Configuración!H:H,Configuración!I:I,"")) -> MAD | H73: Changa con 5 cajones | I73: Changa con 5 cajones | J73: Madera D.C | L73: 6230 | M73: =MAX(CEILING(L73/4,10),100) -> 1560 | N73: =M73*4 -> 6240 | O73: 8900 | P73: =IF($O73<Configuración!$B$7,"NO","SI") -> SI | Q73: =IF($P73="NO","NO APLICA",MAX(CEILING(($O73*(1-Configuración!$B$2))/Configuración!$B$3,Configuración!$B$6),Configuración!$B$5)) -> 890 | R73: =IF($Q73="NO APLICA","NO APLICA",$Q73*Configuración!$B$3) -> 7120 | S73: =IF($O73<Configuración!$B$8,"NO","SI") -> SI | T73: =IF($S73="NO","NO APLICA",MAX(CEILING(($O73*(1-Configuración!$B$2))/Configuración!$B$4,Configuración!$B$6),Configuración!$B$5)) -> 600 | U73: =IF($T73="NO APLICA","NO APLICA",$T73*Configuración!$B$4) -> 7200 | V73: =MAX(CEILING($O73/Configuración!$B$9,Configuración!$B$6),Configuración!$B$5) -> 180 | W73: Activo | X73: 46079
A74: =IF(OR(E74="",F74="",G74=""),"",E74&"-"&F74&"-"&G74&"-"&TEXT(COUNTIFS($E$2:E74,E74,$F$2:F74,F74,$G$2:G74,G74),"000")) -> MOB-CLO-MAD-001 | B74: Mobiliario | C74: Closet | D74: Madera | E74: =_xlfn.XLOOKUP(B74,Configuración!A:A,Configuración!B:B,"") -> MOB | F74: {=IF($C74="","",_xlfn.XLOOKUP(1,(Configuración!D:D=$B74)*(Configuración!E:E=$C74),Configuración!F:F,""))} -> CLO | G74: =IF($D74="","",_xlfn.XLOOKUP($D74,Configuración!H:H,Configuración!I:I,"")) -> MAD | H74: Closet Brasil | I74: Closet Brasil | J74: Madera D.C | L74: 8750 | M74: =MAX(CEILING(L74/4,10),100) -> 2190 | N74: =M74*4 -> 8760 | O74: 12500 | P74: =IF($O74<Configuración!$B$7,"NO","SI") -> SI | Q74: =IF($P74="NO","NO APLICA",MAX(CEILING(($O74*(1-Configuración!$B$2))/Configuración!$B$3,Configuración!$B$6),Configuración!$B$5)) -> 1250 | R74: =IF($Q74="NO APLICA","NO APLICA",$Q74*Configuración!$B$3) -> 10000 | S74: =IF($O74<Configuración!$B$8,"NO","SI") -> SI | T74: =IF($S74="NO","NO APLICA",MAX(CEILING(($O74*(1-Configuración!$B$2))/Configuración!$B$4,Configuración!$B$6),Configuración!$B$5)) -> 840 | U74: =IF($T74="NO APLICA","NO APLICA",$T74*Configuración!$B$4) -> 10080 | V74: =MAX(CEILING($O74/Configuración!$B$9,Configuración!$B$6),Configuración!$B$5) -> 250 | W74: Activo | X74: 46079
A75: =IF(OR(E75="",F75="",G75=""),"",E75&"-"&F75&"-"&G75&"-"&TEXT(COUNTIFS($E$2:E75,E75,$F$2:F75,F75,$G$2:G75,G75),"000")) -> MOB-CLO-MAD-002 | B75: Mobiliario | C75: Closet | D75: Madera | E75: =_xlfn.XLOOKUP(B75,Configuración!A:A,Configuración!B:B,"") -> MOB | F75: {=IF($C75="","",_xlfn.XLOOKUP(1,(Configuración!D:D=$B75)*(Configuración!E:E=$C75),Configuración!F:F,""))} -> CLO | G75: =IF($D75="","",_xlfn.XLOOKUP($D75,Configuración!H:H,Configuración!I:I,"")) -> MAD | H75: Closet Brasil con maleta | I75: Closet Brasil con maleta | J75: Madera D.C | L75: 10500 | M75: =MAX(CEILING(L75/4,10),100) -> 2630 | N75: =M75*4 -> 10520 | O75: 15000 | P75: =IF($O75<Configuración!$B$7,"NO","SI") -> SI | Q75: =IF($P75="NO","NO APLICA",MAX(CEILING(($O75*(1-Configuración!$B$2))/Configuración!$B$3,Configuración!$B$6),Configuración!$B$5)) -> 1500 | R75: =IF($Q75="NO APLICA","NO APLICA",$Q75*Configuración!$B$3) -> 12000 | S75: =IF($O75<Configuración!$B$8,"NO","SI") -> SI | T75: =IF($S75="NO","NO APLICA",MAX(CEILING(($O75*(1-Configuración!$B$2))/Configuración!$B$4,Configuración!$B$6),Configuración!$B$5)) -> 1000 | U75: =IF($T75="NO APLICA","NO APLICA",$T75*Configuración!$B$4) -> 12000 | V75: =MAX(CEILING($O75/Configuración!$B$9,Configuración!$B$6),Configuración!$B$5) -> 290 | W75: Activo | X75: 46079
A76: =IF(OR(E76="",F76="",G76=""),"",E76&"-"&F76&"-"&G76&"-"&TEXT(COUNTIFS($E$2:E76,E76,$F$2:F76,F76,$G$2:G76,G76),"000")) -> MOB-CLO-PSL-001 | B76: Mobiliario | C76: Closet | D76: Plástico | E76: =_xlfn.XLOOKUP(B76,Configuración!A:A,Configuración!B:B,"") -> MOB | F76: {=IF($C76="","",_xlfn.XLOOKUP(1,(Configuración!D:D=$B76)*(Configuración!E:E=$C76),Configuración!F:F,""))} -> CLO | G76: =IF($D76="","",_xlfn.XLOOKUP($D76,Configuración!H:H,Configuración!I:I,"")) -> PSL | H76: Closet de Plastico | I76: Closet de Plastico | L76: 3500 | M76: =MAX(CEILING(L76/4,10),100) -> 880 | N76: =M76*4 -> 3520 | O76: 5000 | P76: =IF($O76<Configuración!$B$7,"NO","SI") -> SI | Q76: =IF($P76="NO","NO APLICA",MAX(CEILING(($O76*(1-Configuración!$B$2))/Configuración!$B$3,Configuración!$B$6),Configuración!$B$5)) -> 500 | R76: =IF($Q76="NO APLICA","NO APLICA",$Q76*Configuración!$B$3) -> 4000 | S76: =IF($O76<Configuración!$B$8,"NO","SI") -> SI | T76: =IF($S76="NO","NO APLICA",MAX(CEILING(($O76*(1-Configuración!$B$2))/Configuración!$B$4,Configuración!$B$6),Configuración!$B$5)) -> 340 | U76: =IF($T76="NO APLICA","NO APLICA",$T76*Configuración!$B$4) -> 4080 | V76: =MAX(CEILING($O76/Configuración!$B$9,Configuración!$B$6),Configuración!$B$5) -> 100 | W76: Activo | X76: 46103
A77: =IF(OR(E77="",F77="",G77=""),"",E77&"-"&F77&"-"&G77&"-"&TEXT(COUNTIFS($E$2:E77,E77,$F$2:F77,F77,$G$2:G77,G77),"000")) -> MOB-CLO-MAD-003 | B77: Mobiliario | C77: Closet | D77: Madera | E77: =_xlfn.XLOOKUP(B77,Configuración!A:A,Configuración!B:B,"") -> MOB | F77: {=IF($C77="","",_xlfn.XLOOKUP(1,(Configuración!D:D=$B77)*(Configuración!E:E=$C77),Configuración!F:F,""))} -> CLO | G77: =IF($D77="","",_xlfn.XLOOKUP($D77,Configuración!H:H,Configuración!I:I,"")) -> MAD | H77: Closet Roma con maleta | I77: Closet Roma con maleta | J77: Madera D.C | L77: 9000 | M77: =MAX(CEILING(L77/4,10),100) -> 2250 | N77: =M77*4 -> 9000 | O77: 14000 | P77: =IF($O77<Configuración!$B$7,"NO","SI") -> SI | Q77: =IF($P77="NO","NO APLICA",MAX(CEILING(($O77*(1-Configuración!$B$2))/Configuración!$B$3,Configuración!$B$6),Configuración!$B$5)) -> 1400 | R77: =IF($Q77="NO APLICA","NO APLICA",$Q77*Configuración!$B$3) -> 11200 | S77: =IF($O77<Configuración!$B$8,"NO","SI") -> SI | T77: =IF($S77="NO","NO APLICA",MAX(CEILING(($O77*(1-Configuración!$B$2))/Configuración!$B$4,Configuración!$B$6),Configuración!$B$5)) -> 940 | U77: =IF($T77="NO APLICA","NO APLICA",$T77*Configuración!$B$4) -> 11280 | V77: =MAX(CEILING($O77/Configuración!$B$9,Configuración!$B$6),Configuración!$B$5) -> 270 | W77: Activo | X77: 46079
A78: =IF(OR(E78="",F78="",G78=""),"",E78&"-"&F78&"-"&G78&"-"&TEXT(COUNTIFS($E$2:E78,E78,$F$2:F78,F78,$G$2:G78,G78),"000")) -> HOG-FRZ-ALG-001 | B78: Hogar | C78: Frazadas | D78: Algodón | E78: =_xlfn.XLOOKUP(B78,Configuración!A:A,Configuración!B:B,"") -> HOG | F78: {=IF($C78="","",_xlfn.XLOOKUP(1,(Configuración!D:D=$B78)*(Configuración!E:E=$C78),Configuración!F:F,""))} -> FRZ | G78: =IF($D78="","",_xlfn.XLOOKUP($D78,Configuración!H:H,Configuración!I:I,"")) -> ALG | H78: Cobertor matrimonial 1pz | I78: Cobertor matrimonial 1pz | J78: D.C | L78: 1050 | M78: =MAX(CEILING(L78/4,10),100) -> 270 | N78: =M78*4 -> 1080 | O78: 1500 | P78: =IF($O78<Configuración!$B$7,"NO","SI") -> NO | Q78: =IF($P78="NO","NO APLICA",MAX(CEILING(($O78*(1-Configuración!$B$2))/Configuración!$B$3,Configuración!$B$6),Configuración!$B$5)) -> NO APLICA | R78: =IF($Q78="NO APLICA","NO APLICA",$Q78*Configuración!$B$3) -> NO APLICA | S78: =IF($O78<Configuración!$B$8,"NO","SI") -> NO | T78: =IF($S78="NO","NO APLICA",MAX(CEILING(($O78*(1-Configuración!$B$2))/Configuración!$B$4,Configuración!$B$6),Configuración!$B$5)) -> NO APLICA | U78: =IF($T78="NO APLICA","NO APLICA",$T78*Configuración!$B$4) -> NO APLICA | V78: =MAX(CEILING($O78/Configuración!$B$9,Configuración!$B$6),Configuración!$B$5) -> 100
A79: =IF(OR(E79="",F79="",G79=""),"",E79&"-"&F79&"-"&G79&"-"&TEXT(COUNTIFS($E$2:E79,E79,$F$2:F79,F79,$G$2:G79,G79),"000")) -> HOG-COL-ESP-001 | B79: Hogar | C79: Colchón | D79: Espuma | E79: =_xlfn.XLOOKUP(B79,Configuración!A:A,Configuración!B:B,"") -> HOG | F79: {=IF($C79="","",_xlfn.XLOOKUP(1,(Configuración!D:D=$B79)*(Configuración!E:E=$C79),Configuración!F:F,""))} -> COL | G79: =IF($D79="","",_xlfn.XLOOKUP($D79,Configuración!H:H,Configuración!I:I,"")) -> ESP | H79: Colchón individual | I79: Colchón individual | J79: Cosmo | L79: 5460 | M79: =MAX(CEILING(L79/4,10),100) -> 1370 | N79: =M79*4 -> 5480 | O79: 7800 | P79: =IF($O79<Configuración!$B$7,"NO","SI") -> SI | Q79: =IF($P79="NO","NO APLICA",MAX(CEILING(($O79*(1-Configuración!$B$2))/Configuración!$B$3,Configuración!$B$6),Configuración!$B$5)) -> 780 | R79: =IF($Q79="NO APLICA","NO APLICA",$Q79*Configuración!$B$3) -> 6240 | S79: =IF($O79<Configuración!$B$8,"NO","SI") -> SI | T79: =IF($S79="NO","NO APLICA",MAX(CEILING(($O79*(1-Configuración!$B$2))/Configuración!$B$4,Configuración!$B$6),Configuración!$B$5)) -> 520 | U79: =IF($T79="NO APLICA","NO APLICA",$T79*Configuración!$B$4) -> 6240 | V79: =MAX(CEILING($O79/Configuración!$B$9,Configuración!$B$6),Configuración!$B$5) -> 150 | W79: Activo | X79: 46079
A80: =IF(OR(E80="",F80="",G80=""),"",E80&"-"&F80&"-"&G80&"-"&TEXT(COUNTIFS($E$2:E80,E80,$F$2:F80,F80,$G$2:G80,G80),"000")) -> HOG-COL-ESP-002 | B80: Hogar | C80: Colchón | D80: Espuma | E80: =_xlfn.XLOOKUP(B80,Configuración!A:A,Configuración!B:B,"") -> HOG | F80: {=IF($C80="","",_xlfn.XLOOKUP(1,(Configuración!D:D=$B80)*(Configuración!E:E=$C80),Configuración!F:F,""))} -> COL | G80: =IF($D80="","",_xlfn.XLOOKUP($D80,Configuración!H:H,Configuración!I:I,"")) -> ESP | H80: Colchón individual Magic | I80: Colchón individual Magic | J80: Restonic | L80: 5950 | M80: =MAX(CEILING(L80/4,10),100) -> 1490 | N80: =M80*4 -> 5960 | O80: 8500 | P80: =IF($O80<Configuración!$B$7,"NO","SI") -> SI | Q80: =IF($P80="NO","NO APLICA",MAX(CEILING(($O80*(1-Configuración!$B$2))/Configuración!$B$3,Configuración!$B$6),Configuración!$B$5)) -> 850 | R80: =IF($Q80="NO APLICA","NO APLICA",$Q80*Configuración!$B$3) -> 6800 | S80: =IF($O80<Configuración!$B$8,"NO","SI") -> SI | T80: =IF($S80="NO","NO APLICA",MAX(CEILING(($O80*(1-Configuración!$B$2))/Configuración!$B$4,Configuración!$B$6),Configuración!$B$5)) -> 570 | U80: =IF($T80="NO APLICA","NO APLICA",$T80*Configuración!$B$4) -> 6840 | V80: =MAX(CEILING($O80/Configuración!$B$9,Configuración!$B$6),Configuración!$B$5) -> 170 | W80: Activo | X80: 46079
A81: =IF(OR(E81="",F81="",G81=""),"",E81&"-"&F81&"-"&G81&"-"&TEXT(COUNTIFS($E$2:E81,E81,$F$2:F81,F81,$G$2:G81,G81),"000")) -> HOG-COL-ESP-003 | B81: Hogar | C81: Colchón | D81: Espuma | E81: =_xlfn.XLOOKUP(B81,Configuración!A:A,Configuración!B:B,"") -> HOG | F81: {=IF($C81="","",_xlfn.XLOOKUP(1,(Configuración!D:D=$B81)*(Configuración!E:E=$C81),Configuración!F:F,""))} -> COL | G81: =IF($D81="","",_xlfn.XLOOKUP($D81,Configuración!H:H,Configuración!I:I,"")) -> ESP | H81: Colchón king size | I81: Colchón king size | J81: Cosmo | L81: 9800 | M81: =MAX(CEILING(L81/4,10),100) -> 2450 | N81: =M81*4 -> 9800 | O81: 13995 | P81: =IF($O81<Configuración!$B$7,"NO","SI") -> SI | Q81: =IF($P81="NO","NO APLICA",MAX(CEILING(($O81*(1-Configuración!$B$2))/Configuración!$B$3,Configuración!$B$6),Configuración!$B$5)) -> 1400 | R81: =IF($Q81="NO APLICA","NO APLICA",$Q81*Configuración!$B$3) -> 11200 | S81: =IF($O81<Configuración!$B$8,"NO","SI") -> SI | T81: =IF($S81="NO","NO APLICA",MAX(CEILING(($O81*(1-Configuración!$B$2))/Configuración!$B$4,Configuración!$B$6),Configuración!$B$5)) -> 940 | U81: =IF($T81="NO APLICA","NO APLICA",$T81*Configuración!$B$4) -> 11280 | V81: =MAX(CEILING($O81/Configuración!$B$9,Configuración!$B$6),Configuración!$B$5) -> 270 | W81: Activo | X81: 46079
A82: =IF(OR(E82="",F82="",G82=""),"",E82&"-"&F82&"-"&G82&"-"&TEXT(COUNTIFS($E$2:E89,E82,$F$2:F89,F82,$G$2:G89,G82),"000")) -> HOG-COL-ESP-006 | B82: Hogar | C82: Colchón | D82: Espuma | E82: =_xlfn.XLOOKUP(B82,Configuración!A:A,Configuración!B:B,"") -> HOG | F82: {=IF($C82="","",_xlfn.XLOOKUP(1,(Configuración!D:D=$B82)*(Configuración!E:E=$C82),Configuración!F:F,""))} -> COL | G82: =IF($D82="","",_xlfn.XLOOKUP($D82,Configuración!H:H,Configuración!I:I,"")) -> ESP | H82: Colchón kingsa Magic | I82: Colchón kingsa Magic | J82: Restonic | L82: 10500 | M82: =MAX(CEILING(L82/4,10),100) -> 2630 | N82: =M82*4 -> 10520 | O82: 15000 | P82: =IF($O82<Configuración!$B$7,"NO","SI") -> SI | Q82: =IF($P82="NO","NO APLICA",MAX(CEILING(($O82*(1-Configuración!$B$2))/Configuración!$B$3,Configuración!$B$6),Configuración!$B$5)) -> 1500 | R82: =IF($Q82="NO APLICA","NO APLICA",$Q82*Configuración!$B$3) -> 12000 | S82: =IF($O82<Configuración!$B$8,"NO","SI") -> SI | T82: =IF($S82="NO","NO APLICA",MAX(CEILING(($O82*(1-Configuración!$B$2))/Configuración!$B$4,Configuración!$B$6),Configuración!$B$5)) -> 1000 | U82: =IF($T82="NO APLICA","NO APLICA",$T82*Configuración!$B$4) -> 12000 | V82: =MAX(CEILING($O82/Configuración!$B$9,Configuración!$B$6),Configuración!$B$5) -> 290 | W82: Activo | X82: 46079
A83: =IF(OR(E83="",F83="",G83=""),"",E83&"-"&F83&"-"&G83&"-"&TEXT(COUNTIFS($E$2:E83,E83,$F$2:F83,F83,$G$2:G83,G83),"000")) -> HOG-COL-ESP-005 | B83: Hogar | C83: Colchón | D83: Espuma | E83: =_xlfn.XLOOKUP(B83,Configuración!A:A,Configuración!B:B,"") -> HOG | F83: {=IF($C83="","",_xlfn.XLOOKUP(1,(Configuración!D:D=$B83)*(Configuración!E:E=$C83),Configuración!F:F,""))} -> COL | G83: =IF($D83="","",_xlfn.XLOOKUP($D83,Configuración!H:H,Configuración!I:I,"")) -> ESP | H83: Colchón matrimonial | I83: Colchón matrimonial | J83: Cosmo | L83: 7000 | M83: =MAX(CEILING(L83/4,10),100) -> 1750 | N83: =M83*4 -> 7000 | O83: 10000 | P83: =IF($O83<Configuración!$B$7,"NO","SI") -> SI | Q83: =IF($P83="NO","NO APLICA",MAX(CEILING(($O83*(1-Configuración!$B$2))/Configuración!$B$3,Configuración!$B$6),Configuración!$B$5)) -> 1000 | R83: =IF($Q83="NO APLICA","NO APLICA",$Q83*Configuración!$B$3) -> 8000 | S83: =IF($O83<Configuración!$B$8,"NO","SI") -> SI | T83: =IF($S83="NO","NO APLICA",MAX(CEILING(($O83*(1-Configuración!$B$2))/Configuración!$B$4,Configuración!$B$6),Configuración!$B$5)) -> 670 | U83: =IF($T83="NO APLICA","NO APLICA",$T83*Configuración!$B$4) -> 8040 | V83: =MAX(CEILING($O83/Configuración!$B$9,Configuración!$B$6),Configuración!$B$5) -> 200 | W83: Activo | X83: 46079
A84: =IF(OR(E84="",F84="",G84=""),"",E84&"-"&F84&"-"&G84&"-"&TEXT(COUNTIFS($E$2:E84,E84,$F$2:F84,F84,$G$2:G84,G84),"000")) -> HOG-COL-ESP-006 | B84: Hogar | C84: Colchón | D84: Espuma | E84: =_xlfn.XLOOKUP(B84,Configuración!A:A,Configuración!B:B,"") -> HOG | F84: {=IF($C84="","",_xlfn.XLOOKUP(1,(Configuración!D:D=$B84)*(Configuración!E:E=$C84),Configuración!F:F,""))} -> COL | G84: =IF($D84="","",_xlfn.XLOOKUP($D84,Configuración!H:H,Configuración!I:I,"")) -> ESP | H84: Colchón matrimonial Magic | I84: Colchón matrimonial Magic | J84: Restonic | L84: 7525 | M84: =MAX(CEILING(L84/4,10),100) -> 1890 | N84: =M84*4 -> 7560 | O84: 10750 | P84: =IF($O84<Configuración!$B$7,"NO","SI") -> SI | Q84: =IF($P84="NO","NO APLICA",MAX(CEILING(($O84*(1-Configuración!$B$2))/Configuración!$B$3,Configuración!$B$6),Configuración!$B$5)) -> 1080 | R84: =IF($Q84="NO APLICA","NO APLICA",$Q84*Configuración!$B$3) -> 8640 | S84: =IF($O84<Configuración!$B$8,"NO","SI") -> SI | T84: =IF($S84="NO","NO APLICA",MAX(CEILING(($O84*(1-Configuración!$B$2))/Configuración!$B$4,Configuración!$B$6),Configuración!$B$5)) -> 720 | U84: =IF($T84="NO APLICA","NO APLICA",$T84*Configuración!$B$4) -> 8640 | V84: =MAX(CEILING($O84/Configuración!$B$9,Configuración!$B$6),Configuración!$B$5) -> 210 | W84: Activo | X84: 46079
A85: =IF(OR(E85="",F85="",G85=""),"",E85&"-"&F85&"-"&G85&"-"&TEXT(COUNTIFS($E$2:E85,E85,$F$2:F85,F85,$G$2:G85,G85),"000")) -> COC-COM-ALUT-001 | B85: Cocina | C85: Comal | D85: Alumino y Teflon | E85: =_xlfn.XLOOKUP(B85,Configuración!A:A,Configuración!B:B,"") -> COC | F85: {=IF($C85="","",_xlfn.XLOOKUP(1,(Configuración!D:D=$B85)*(Configuración!E:E=$C85),Configuración!F:F,""))} -> COM | G85: =IF($D85="","",_xlfn.XLOOKUP($D85,Configuración!H:H,Configuración!I:I,"")) -> ALUT | H85: Comal doble grill | I85: Comal Cinsa | J85: Cinsa | K85: listo | L85: 1540 | M85: =MAX(CEILING(L85/4,10),100) -> 390 | N85: =M85*4 -> 1560 | O85: 2200 | P85: =IF($O85<Configuración!$B$7,"NO","SI") -> SI | Q85: =IF($P85="NO","NO APLICA",MAX(CEILING(($O85*(1-Configuración!$B$2))/Configuración!$B$3,Configuración!$B$6),Configuración!$B$5)) -> 220 | R85: =IF($Q85="NO APLICA","NO APLICA",$Q85*Configuración!$B$3) -> 1760 | S85: =IF($O85<Configuración!$B$8,"NO","SI") -> NO | T85: =IF($S85="NO","NO APLICA",MAX(CEILING(($O85*(1-Configuración!$B$2))/Configuración!$B$4,Configuración!$B$6),Configuración!$B$5)) -> NO APLICA | U85: =IF($T85="NO APLICA","NO APLICA",$T85*Configuración!$B$4) -> NO APLICA | V85: =MAX(CEILING($O85/Configuración!$B$9,Configuración!$B$6),Configuración!$B$5) -> 100 | W85: Activo | X85: 46079
A86: =IF(OR(E86="",F86="",G86=""),"",E86&"-"&F86&"-"&G86&"-"&TEXT(COUNTIFS($E$2:E86,E86,$F$2:F86,F86,$G$2:G86,G86),"000")) -> COC-COM-ALUT-002 | B86: Cocina | C86: Comal | D86: Alumino y Teflon | E86: =_xlfn.XLOOKUP(B86,Configuración!A:A,Configuración!B:B,"") -> COC | F86: {=IF($C86="","",_xlfn.XLOOKUP(1,(Configuración!D:D=$B86)*(Configuración!E:E=$C86),Configuración!F:F,""))} -> COM | G86: =IF($D86="","",_xlfn.XLOOKUP($D86,Configuración!H:H,Configuración!I:I,"")) -> ALUT | H86: Comal texas grill (Lamex) | I86: Comal Lamex | J86: Lamex | K86: listo | L86: 1680 | M86: =MAX(CEILING(L86/4,10),100) -> 420 | N86: =M86*4 -> 1680 | O86: 2400 | P86: =IF($O86<Configuración!$B$7,"NO","SI") -> SI | Q86: =IF($P86="NO","NO APLICA",MAX(CEILING(($O86*(1-Configuración!$B$2))/Configuración!$B$3,Configuración!$B$6),Configuración!$B$5)) -> 240 | R86: =IF($Q86="NO APLICA","NO APLICA",$Q86*Configuración!$B$3) -> 1920 | S86: =IF($O86<Configuración!$B$8,"NO","SI") -> NO | T86: =IF($S86="NO","NO APLICA",MAX(CEILING(($O86*(1-Configuración!$B$2))/Configuración!$B$4,Configuración!$B$6),Configuración!$B$5)) -> NO APLICA | U86: =IF($T86="NO APLICA","NO APLICA",$T86*Configuración!$B$4) -> NO APLICA | V86: =MAX(CEILING($O86/Configuración!$B$9,Configuración!$B$6),Configuración!$B$5) -> 100 | W86: Activo | X86: 46079
A87: =IF(OR(E87="",F87="",G87=""),"",E87&"-"&F87&"-"&G87&"-"&TEXT(COUNTIFS($E$2:E87,E87,$F$2:F87,F87,$G$2:G87,G87),"000")) -> COC-SAR-ALUT-001 | B87: Cocina | C87: Sartén | D87: Alumino y Teflon | E87: =_xlfn.XLOOKUP(B87,Configuración!A:A,Configuración!B:B,"") -> COC | F87: {=IF($C87="","",_xlfn.XLOOKUP(1,(Configuración!D:D=$B87)*(Configuración!E:E=$C87),Configuración!F:F,""))} -> SAR | G87: =IF($D87="","",_xlfn.XLOOKUP($D87,Configuración!H:H,Configuración!I:I,"")) -> ALUT | H87: Comaleta | I87: Comaleta | J87: Cinsa | K87: listo | L87: 960 | M87: =MAX(CEILING(L87/4,10),100) -> 240 | N87: =M87*4 -> 960 | O87: 1200 | P87: =IF($O87<Configuración!$B$7,"NO","SI") -> NO | Q87: =IF($P87="NO","NO APLICA",MAX(CEILING(($O87*(1-Configuración!$B$2))/Configuración!$B$3,Configuración!$B$6),Configuración!$B$5)) -> NO APLICA | R87: =IF($Q87="NO APLICA","NO APLICA",$Q87*Configuración!$B$3) -> NO APLICA | S87: =IF($O87<Configuración!$B$8,"NO","SI") -> NO | T87: =IF($S87="NO","NO APLICA",MAX(CEILING(($O87*(1-Configuración!$B$2))/Configuración!$B$4,Configuración!$B$6),Configuración!$B$5)) -> NO APLICA | U87: =IF($T87="NO APLICA","NO APLICA",$T87*Configuración!$B$4) -> NO APLICA | V87: =MAX(CEILING($O87/Configuración!$B$9,Configuración!$B$6),Configuración!$B$5) -> 100 | W87: Activo | X87: 46079
A88: =IF(OR(E88="",F88="",G88=""),"",E88&"-"&F88&"-"&G88&"-"&TEXT(COUNTIFS($E$2:E88,E88,$F$2:F88,F88,$G$2:G88,G88),"000")) -> MOB-COMD-TUB-001 | B88: Mobiliario | C88: Comedor | D88: Tubular | E88: =_xlfn.XLOOKUP(B88,Configuración!A:A,Configuración!B:B,"") -> MOB | F88: {=IF($C88="","",_xlfn.XLOOKUP(1,(Configuración!D:D=$B88)*(Configuración!E:E=$C88),Configuración!F:F,""))} -> COMD | G88: =IF($D88="","",_xlfn.XLOOKUP($D88,Configuración!H:H,Configuración!I:I,"")) -> TUB | H88: Comedor tubular para 4 sillas | I88: Comedor tubular para 4 sillas | J88: D.C | L88: 4200 | M88: =MAX(CEILING(L88/4,10),100) -> 1050 | N88: =M88*4 -> 4200 | O88: 6000 | P88: =IF($O88<Configuración!$B$7,"NO","SI") -> SI | Q88: =IF($P88="NO","NO APLICA",MAX(CEILING(($O88*(1-Configuración!$B$2))/Configuración!$B$3,Configuración!$B$6),Configuración!$B$5)) -> 600 | R88: =IF($Q88="NO APLICA","NO APLICA",$Q88*Configuración!$B$3) -> 4800 | S88: =IF($O88<Configuración!$B$8,"NO","SI") -> SI | T88: =IF($S88="NO","NO APLICA",MAX(CEILING(($O88*(1-Configuración!$B$2))/Configuración!$B$4,Configuración!$B$6),Configuración!$B$5)) -> 400 | U88: =IF($T88="NO APLICA","NO APLICA",$T88*Configuración!$B$4) -> 4800 | V88: =MAX(CEILING($O88/Configuración!$B$9,Configuración!$B$6),Configuración!$B$5) -> 120 | W88: Activo | X88: 46079
A89: =IF(OR(E89="",F89="",G89=""),"",E89&"-"&F89&"-"&G89&"-"&TEXT(COUNTIFS($E$2:E89,E89,$F$2:F89,F89,$G$2:G89,G89),"000")) -> MOB-COMD-TUB-002 | B89: Mobiliario | C89: Comedor | D89: Tubular | E89: =_xlfn.XLOOKUP(B89,Configuración!A:A,Configuración!B:B,"") -> MOB | F89: {=IF($C89="","",_xlfn.XLOOKUP(1,(Configuración!D:D=$B89)*(Configuración!E:E=$C89),Configuración!F:F,""))} -> COMD | G89: =IF($D89="","",_xlfn.XLOOKUP($D89,Configuración!H:H,Configuración!I:I,"")) -> TUB | H89: Comedor tubular para 6 sillas | I89: Comedor tubular para 6 sillas | J89: D.C | L89: 4900 | M89: =MAX(CEILING(L89/4,10),100) -> 1230 | N89: =M89*4 -> 4920 | O89: 7000 | P89: =IF($O89<Configuración!$B$7,"NO","SI") -> SI | Q89: =IF($P89="NO","NO APLICA",MAX(CEILING(($O89*(1-Configuración!$B$2))/Configuración!$B$3,Configuración!$B$6),Configuración!$B$5)) -> 700 | R89: =IF($Q89="NO APLICA","NO APLICA",$Q89*Configuración!$B$3) -> 5600 | S89: =IF($O89<Configuración!$B$8,"NO","SI") -> SI | T89: =IF($S89="NO","NO APLICA",MAX(CEILING(($O89*(1-Configuración!$B$2))/Configuración!$B$4,Configuración!$B$6),Configuración!$B$5)) -> 470 | U89: =IF($T89="NO APLICA","NO APLICA",$T89*Configuración!$B$4) -> 5640 | V89: =MAX(CEILING($O89/Configuración!$B$9,Configuración!$B$6),Configuración!$B$5) -> 140 | W89: Activo | X89: 46079
A90: =IF(OR(E90="",F90="",G90=""),"",E90&"-"&F90&"-"&G90&"-"&TEXT(COUNTIFS($E$2:E90,E90,$F$2:F90,F90,$G$2:G90,G90),"000")) -> MOB-COMD-TUB-003 | B90: Mobiliario | C90: Comedor | D90: Tubular | E90: =_xlfn.XLOOKUP(B90,Configuración!A:A,Configuración!B:B,"") -> MOB | F90: {=IF($C90="","",_xlfn.XLOOKUP(1,(Configuración!D:D=$B90)*(Configuración!E:E=$C90),Configuración!F:F,""))} -> COMD | G90: =IF($D90="","",_xlfn.XLOOKUP($D90,Configuración!H:H,Configuración!I:I,"")) -> TUB | H90: Comedor tubular para 8 sillas | I90: Comedor tubular para 8 sillas | J90: D.C | L90: 5600 | M90: =MAX(CEILING(L90/4,10),100) -> 1400 | N90: =M90*4 -> 5600 | O90: 8000 | P90: =IF($O90<Configuración!$B$7,"NO","SI") -> SI | Q90: =IF($P90="NO","NO APLICA",MAX(CEILING(($O90*(1-Configuración!$B$2))/Configuración!$B$3,Configuración!$B$6),Configuración!$B$5)) -> 800 | R90: =IF($Q90="NO APLICA","NO APLICA",$Q90*Configuración!$B$3) -> 6400 | S90: =IF($O90<Configuración!$B$8,"NO","SI") -> SI | T90: =IF($S90="NO","NO APLICA",MAX(CEILING(($O90*(1-Configuración!$B$2))/Configuración!$B$4,Configuración!$B$6),Configuración!$B$5)) -> 540 | U90: =IF($T90="NO APLICA","NO APLICA",$T90*Configuración!$B$4) -> 6480 | V90: =MAX(CEILING($O90/Configuración!$B$9,Configuración!$B$6),Configuración!$B$5) -> 160 | W90: Activo | X90: 46079
A91: =IF(OR(E91="",F91="",G91=""),"",E91&"-"&F91&"-"&G91&"-"&TEXT(COUNTIFS($E$2:E91,E91,$F$2:F91,F91,$G$2:G91,G91),"000")) -> MOB-ESP-TUB-001 | B91: Mobiliario | C91: Espejo | D91: Tubular | E91: =_xlfn.XLOOKUP(B91,Configuración!A:A,Configuración!B:B,"") -> MOB | F91: {=IF($C91="","",_xlfn.XLOOKUP(1,(Configuración!D:D=$B91)*(Configuración!E:E=$C91),Configuración!F:F,""))} -> ESP | G91: =IF($D91="","",_xlfn.XLOOKUP($D91,Configuración!H:H,Configuración!I:I,"")) -> TUB | H91: Espejo tubular con luces | I91: Espejo tubular con luces | J91: D.C | L91: 2800 | M91: =MAX(CEILING(L91/4,10),100) -> 700 | N91: =M91*4 -> 2800 | O91: 4000 | P91: =IF($O91<Configuración!$B$7,"NO","SI") -> SI | Q91: =IF($P91="NO","NO APLICA",MAX(CEILING(($O91*(1-Configuración!$B$2))/Configuración!$B$3,Configuración!$B$6),Configuración!$B$5)) -> 400 | R91: =IF($Q91="NO APLICA","NO APLICA",$Q91*Configuración!$B$3) -> 3200 | S91: =IF($O91<Configuración!$B$8,"NO","SI") -> SI | T91: =IF($S91="NO","NO APLICA",MAX(CEILING(($O91*(1-Configuración!$B$2))/Configuración!$B$4,Configuración!$B$6),Configuración!$B$5)) -> 270 | U91: =IF($T91="NO APLICA","NO APLICA",$T91*Configuración!$B$4) -> 3240 | V91: =MAX(CEILING($O91/Configuración!$B$9,Configuración!$B$6),Configuración!$B$5) -> 100 | W91: Activo | X91: 46079
A92: =IF(OR(E92="",F92="",G92=""),"",E92&"-"&F92&"-"&G92&"-"&TEXT(COUNTIFS($E$2:E92,E92,$F$2:F92,F92,$G$2:G92,G92),"000")) -> MOB-ESQ-TUB-001 | B92: Mobiliario | C92: Esquinero | D92: Tubular | E92: =_xlfn.XLOOKUP(B92,Configuración!A:A,Configuración!B:B,"") -> MOB | F92: {=IF($C92="","",_xlfn.XLOOKUP(1,(Configuración!D:D=$B92)*(Configuración!E:E=$C92),Configuración!F:F,""))} -> ESQ | G92: =IF($D92="","",_xlfn.XLOOKUP($D92,Configuración!H:H,Configuración!I:I,"")) -> TUB | H92: Esquinero tubular | I92: Esquinero tubular | J92: D.C | L92: 1820 | M92: =MAX(CEILING(L92/4,10),100) -> 460 | N92: =M92*4 -> 1840 | O92: 2600 | P92: =IF($O92<Configuración!$B$7,"NO","SI") -> SI | Q92: =IF($P92="NO","NO APLICA",MAX(CEILING(($O92*(1-Configuración!$B$2))/Configuración!$B$3,Configuración!$B$6),Configuración!$B$5)) -> 260 | R92: =IF($Q92="NO APLICA","NO APLICA",$Q92*Configuración!$B$3) -> 2080 | S92: =IF($O92<Configuración!$B$8,"NO","SI") -> NO | T92: =IF($S92="NO","NO APLICA",MAX(CEILING(($O92*(1-Configuración!$B$2))/Configuración!$B$4,Configuración!$B$6),Configuración!$B$5)) -> NO APLICA | U92: =IF($T92="NO APLICA","NO APLICA",$T92*Configuración!$B$4) -> NO APLICA | V92: =MAX(CEILING($O92/Configuración!$B$9,Configuración!$B$6),Configuración!$B$5) -> 100 | W92: Activo | X92: 46079
A93: =IF(OR(E93="",F93="",G93=""),"",E93&"-"&F93&"-"&G93&"-"&TEXT(COUNTIFS($E$2:E93,E93,$F$2:F93,F93,$G$2:G93,G93),"000")) -> LBL-EST-MET-001 | B93: Línea blanca | C93: Estufa | D93: Metal | E93: =_xlfn.XLOOKUP(B93,Configuración!A:A,Configuración!B:B,"") -> LBL | F93: {=IF($C93="","",_xlfn.XLOOKUP(1,(Configuración!D:D=$B93)*(Configuración!E:E=$C93),Configuración!F:F,""))} -> EST | G93: =IF($D93="","",_xlfn.XLOOKUP($D93,Configuración!H:H,Configuración!I:I,"")) -> MET | H93: Estufa de 4 quemadores | I93: Estufa de 4 quemadores | J93: Iem | L93: 11200 | M93: =MAX(CEILING(L93/4,10),100) -> 2800 | N93: =M93*4 -> 11200 | O93: 15995 | P93: =IF($O93<Configuración!$B$7,"NO","SI") -> SI | Q93: =IF($P93="NO","NO APLICA",MAX(CEILING(($O93*(1-Configuración!$B$2))/Configuración!$B$3,Configuración!$B$6),Configuración!$B$5)) -> 1600 | R93: =IF($Q93="NO APLICA","NO APLICA",$Q93*Configuración!$B$3) -> 12800 | S93: =IF($O93<Configuración!$B$8,"NO","SI") -> SI | T93: =IF($S93="NO","NO APLICA",MAX(CEILING(($O93*(1-Configuración!$B$2))/Configuración!$B$4,Configuración!$B$6),Configuración!$B$5)) -> 1070 | U93: =IF($T93="NO APLICA","NO APLICA",$T93*Configuración!$B$4) -> 12840 | V93: =MAX(CEILING($O93/Configuración!$B$9,Configuración!$B$6),Configuración!$B$5) -> 310 | W93: Activo | X93: 46079
A94: =IF(OR(E94="",F94="",G94=""),"",E94&"-"&F94&"-"&G94&"-"&TEXT(COUNTIFS($E$2:E94,E94,$F$2:F94,F94,$G$2:G94,G94),"000")) -> LBL-EST-MET-002 | B94: Línea blanca | C94: Estufa | D94: Metal | E94: =_xlfn.XLOOKUP(B94,Configuración!A:A,Configuración!B:B,"") -> LBL | F94: {=IF($C94="","",_xlfn.XLOOKUP(1,(Configuración!D:D=$B94)*(Configuración!E:E=$C94),Configuración!F:F,""))} -> EST | G94: =IF($D94="","",_xlfn.XLOOKUP($D94,Configuración!H:H,Configuración!I:I,"")) -> MET | H94: Estufa de 6 quemadores con horno | I94: Estufa de 6 quemadores con horno | J94: Iem | L94: 14000 | M94: =MAX(CEILING(L94/4,10),100) -> 3500 | N94: =M94*4 -> 14000 | O94: 19995 | P94: =IF($O94<Configuración!$B$7,"NO","SI") -> SI | Q94: =IF($P94="NO","NO APLICA",MAX(CEILING(($O94*(1-Configuración!$B$2))/Configuración!$B$3,Configuración!$B$6),Configuración!$B$5)) -> 2000 | R94: =IF($Q94="NO APLICA","NO APLICA",$Q94*Configuración!$B$3) -> 16000 | S94: =IF($O94<Configuración!$B$8,"NO","SI") -> SI | T94: =IF($S94="NO","NO APLICA",MAX(CEILING(($O94*(1-Configuración!$B$2))/Configuración!$B$4,Configuración!$B$6),Configuración!$B$5)) -> 1340 | U94: =IF($T94="NO APLICA","NO APLICA",$T94*Configuración!$B$4) -> 16080 | V94: =MAX(CEILING($O94/Configuración!$B$9,Configuración!$B$6),Configuración!$B$5) -> 390 | W94: Activo | X94: 46079
A95: =IF(OR(E95="",F95="",G95=""),"",E95&"-"&F95&"-"&G95&"-"&TEXT(COUNTIFS($E$2:E98,E95,$F$2:F98,F95,$G$2:G98,G95),"000")) -> HOG-FRZ-ALG-002 | B95: Hogar | C95: Frazadas | D95: Algodón | E95: =_xlfn.XLOOKUP(B95,Configuración!A:A,Configuración!B:B,"") -> HOG | F95: {=IF($C95="","",_xlfn.XLOOKUP(1,(Configuración!D:D=$B95)*(Configuración!E:E=$C95),Configuración!F:F,""))} -> FRZ | G95: =IF($D95="","",_xlfn.XLOOKUP($D95,Configuración!H:H,Configuración!I:I,"")) -> ALG | H95: Frazada 1pz | I95: Frazada 1pz | J95: D.C | L95: 350 | M95: =MAX(CEILING(L95/4,10),100) -> 100 | N95: =M95*4 -> 400 | O95: 500 | P95: =IF($O95<Configuración!$B$7,"NO","SI") -> NO | Q95: =IF($P95="NO","NO APLICA",MAX(CEILING(($O95*(1-Configuración!$B$2))/Configuración!$B$3,Configuración!$B$6),Configuración!$B$5)) -> NO APLICA | R95: =IF($Q95="NO APLICA","NO APLICA",$Q95*Configuración!$B$3) -> NO APLICA | S95: =IF($O95<Configuración!$B$8,"NO","SI") -> NO | T95: =IF($S95="NO","NO APLICA",MAX(CEILING(($O95*(1-Configuración!$B$2))/Configuración!$B$4,Configuración!$B$6),Configuración!$B$5)) -> NO APLICA | U95: =IF($T95="NO APLICA","NO APLICA",$T95*Configuración!$B$4) -> NO APLICA | V95: =MAX(CEILING($O95/Configuración!$B$9,Configuración!$B$6),Configuración!$B$5) -> 100
A96: =IF(OR(E96="",F96="",G96=""),"",E96&"-"&F96&"-"&G96&"-"&TEXT(COUNTIFS($E$2:E96,E96,$F$2:F96,F96,$G$2:G96,G96),"000")) -> COC-BAT-ALU-005 | B96: Cocina | C96: Batería | D96: Alumino | E96: =_xlfn.XLOOKUP(B96,Configuración!A:A,Configuración!B:B,"") -> COC | F96: {=IF($C96="","",_xlfn.XLOOKUP(1,(Configuración!D:D=$B96)*(Configuración!E:E=$C96),Configuración!F:F,""))} -> BAT | G96: =IF($D96="","",_xlfn.XLOOKUP($D96,Configuración!H:H,Configuración!I:I,"")) -> ALU | H96: Juego básico 1 | I96: Basico 1 | J96: El abuelo | K96: listo | L96: 2100 | M96: =MAX(CEILING(L96/4,10),100) -> 530 | N96: =M96*4 -> 2120 | O96: 3000 | P96: =IF($O96<Configuración!$B$7,"NO","SI") -> SI | Q96: =IF($P96="NO","NO APLICA",MAX(CEILING(($O96*(1-Configuración!$B$2))/Configuración!$B$3,Configuración!$B$6),Configuración!$B$5)) -> 300 | R96: =IF($Q96="NO APLICA","NO APLICA",$Q96*Configuración!$B$3) -> 2400 | S96: =IF($O96<Configuración!$B$8,"NO","SI") -> SI | T96: =IF($S96="NO","NO APLICA",MAX(CEILING(($O96*(1-Configuración!$B$2))/Configuración!$B$4,Configuración!$B$6),Configuración!$B$5)) -> 200 | U96: =IF($T96="NO APLICA","NO APLICA",$T96*Configuración!$B$4) -> 2400 | V96: =MAX(CEILING($O96/Configuración!$B$9,Configuración!$B$6),Configuración!$B$5) -> 100 | W96: Activo | X96: 46079
A97: =IF(OR(E97="",F97="",G97=""),"",E97&"-"&F97&"-"&G97&"-"&TEXT(COUNTIFS($E$2:E97,E97,$F$2:F97,F97,$G$2:G97,G97),"000")) -> COC-BAT-ALU-006 | B97: Cocina | C97: Batería | D97: Alumino | E97: =_xlfn.XLOOKUP(B97,Configuración!A:A,Configuración!B:B,"") -> COC | F97: {=IF($C97="","",_xlfn.XLOOKUP(1,(Configuración!D:D=$B97)*(Configuración!E:E=$C97),Configuración!F:F,""))} -> BAT | G97: =IF($D97="","",_xlfn.XLOOKUP($D97,Configuración!H:H,Configuración!I:I,"")) -> ALU | H97: Juego básico 2 | I97: Basico 2 | J97: El abuelo | K97: listo | L97: 2100 | M97: =MAX(CEILING(L97/4,10),100) -> 530 | N97: =M97*4 -> 2120 | O97: 3000 | P97: =IF($O97<Configuración!$B$7,"NO","SI") -> SI | Q97: =IF($P97="NO","NO APLICA",MAX(CEILING(($O97*(1-Configuración!$B$2))/Configuración!$B$3,Configuración!$B$6),Configuración!$B$5)) -> 300 | R97: =IF($Q97="NO APLICA","NO APLICA",$Q97*Configuración!$B$3) -> 2400 | S97: =IF($O97<Configuración!$B$8,"NO","SI") -> SI | T97: =IF($S97="NO","NO APLICA",MAX(CEILING(($O97*(1-Configuración!$B$2))/Configuración!$B$4,Configuración!$B$6),Configuración!$B$5)) -> 200 | U97: =IF($T97="NO APLICA","NO APLICA",$T97*Configuración!$B$4) -> 2400 | V97: =MAX(CEILING($O97/Configuración!$B$9,Configuración!$B$6),Configuración!$B$5) -> 100 | W97: Activo | X97: 46079
A98: =IF(OR(E98="",F98="",G98=""),"",E98&"-"&F98&"-"&G98&"-"&TEXT(COUNTIFS($E$2:E98,E98,$F$2:F98,F98,$G$2:G98,G98),"000")) -> COC-BUD-ALU-002 | B98: Cocina | C98: Budinera | D98: Alumino | E98: =_xlfn.XLOOKUP(B98,Configuración!A:A,Configuración!B:B,"") -> COC | F98: {=IF($C98="","",_xlfn.XLOOKUP(1,(Configuración!D:D=$B98)*(Configuración!E:E=$C98),Configuración!F:F,""))} -> BUD | G98: =IF($D98="","",_xlfn.XLOOKUP($D98,Configuración!H:H,Configuración!I:I,"")) -> ALU | H98: Juego de budineras 3pz | I98: Juego de budineras 3pz | J98: El abuelo | K98: listo | L98: 1750 | M98: =MAX(CEILING(L98/4,10),100) -> 440 | N98: =M98*4 -> 1760 | O98: 2500 | P98: =IF($O98<Configuración!$B$7,"NO","SI") -> SI | Q98: =IF($P98="NO","NO APLICA",MAX(CEILING(($O98*(1-Configuración!$B$2))/Configuración!$B$3,Configuración!$B$6),Configuración!$B$5)) -> 250 | R98: =IF($Q98="NO APLICA","NO APLICA",$Q98*Configuración!$B$3) -> 2000 | S98: =IF($O98<Configuración!$B$8,"NO","SI") -> NO | T98: =IF($S98="NO","NO APLICA",MAX(CEILING(($O98*(1-Configuración!$B$2))/Configuración!$B$4,Configuración!$B$6),Configuración!$B$5)) -> NO APLICA | U98: =IF($T98="NO APLICA","NO APLICA",$T98*Configuración!$B$4) -> NO APLICA | V98: =MAX(CEILING($O98/Configuración!$B$9,Configuración!$B$6),Configuración!$B$5) -> 100 | W98: Activo | X98: 46079
A99: =IF(OR(E99="",F99="",G99=""),"",E99&"-"&F99&"-"&G99&"-"&TEXT(COUNTIFS($E$2:E99,E99,$F$2:F99,F99,$G$2:G99,G99),"000")) -> COC-BUD-PEL-001 | B99: Cocina | C99: Budinera | D99: Peltre | E99: =_xlfn.XLOOKUP(B99,Configuración!A:A,Configuración!B:B,"") -> COC | F99: {=IF($C99="","",_xlfn.XLOOKUP(1,(Configuración!D:D=$B99)*(Configuración!E:E=$C99),Configuración!F:F,""))} -> BUD | G99: =IF($D99="","",_xlfn.XLOOKUP($D99,Configuración!H:H,Configuración!I:I,"")) -> PEL | H99: Juego de budineras Sonora 6pz | I99: Sonora | J99: Cinsa | K99: listo | L99: 3500 | M99: =MAX(CEILING(L99/4,10),100) -> 880 | N99: =M99*4 -> 3520 | O99: 5000 | P99: =IF($O99<Configuración!$B$7,"NO","SI") -> SI | Q99: =IF($P99="NO","NO APLICA",MAX(CEILING(($O99*(1-Configuración!$B$2))/Configuración!$B$3,Configuración!$B$6),Configuración!$B$5)) -> 500 | R99: =IF($Q99="NO APLICA","NO APLICA",$Q99*Configuración!$B$3) -> 4000 | S99: =IF($O99<Configuración!$B$8,"NO","SI") -> SI | T99: =IF($S99="NO","NO APLICA",MAX(CEILING(($O99*(1-Configuración!$B$2))/Configuración!$B$4,Configuración!$B$6),Configuración!$B$5)) -> 340 | U99: =IF($T99="NO APLICA","NO APLICA",$T99*Configuración!$B$4) -> 4080 | V99: =MAX(CEILING($O99/Configuración!$B$9,Configuración!$B$6),Configuración!$B$5) -> 100 | W99: Activo | X99: 46079
A100: =IF(OR(E100="",F100="",G100=""),"",E100&"-"&F100&"-"&G100&"-"&TEXT(COUNTIFS($E$2:E100,E100,$F$2:F100,F100,$G$2:G100,G100),"000")) -> COC-OLL-PEL-001 | B100: Cocina | C100: Olla | D100: Peltre | E100: =_xlfn.XLOOKUP(B100,Configuración!A:A,Configuración!B:B,"") -> COC | F100: {=IF($C100="","",_xlfn.XLOOKUP(1,(Configuración!D:D=$B100)*(Configuración!E:E=$C100),Configuración!F:F,""))} -> OLL | G100: =IF($D100="","",_xlfn.XLOOKUP($D100,Configuración!H:H,Configuración!I:I,"")) -> PEL | H100: Juego de ollas mexicana 9pz | I100: Ollas mexicana PEL | J100: Cinsa | K100: listo | L100: 3850 | M100: =MAX(CEILING(L100/4,10),100) -> 970 | N100: =M100*4 -> 3880 | O100: 5500 | P100: =IF($O100<Configuración!$B$7,"NO","SI") -> SI | Q100: =IF($P100="NO","NO APLICA",MAX(CEILING(($O100*(1-Configuración!$B$2))/Configuración!$B$3,Configuración!$B$6),Configuración!$B$5)) -> 550 | R100: =IF($Q100="NO APLICA","NO APLICA",$Q100*Configuración!$B$3) -> 4400 | S100: =IF($O100<Configuración!$B$8,"NO","SI") -> SI | T100: =IF($S100="NO","NO APLICA",MAX(CEILING(($O100*(1-Configuración!$B$2))/Configuración!$B$4,Configuración!$B$6),Configuración!$B$5)) -> 370 | U100: =IF($T100="NO APLICA","NO APLICA",$T100*Configuración!$B$4) -> 4440 | V100: =MAX(CEILING($O100/Configuración!$B$9,Configuración!$B$6),Configuración!$B$5) -> 110 | W100: Activo | X100: 46079
A101: =IF(OR(E101="",F101="",G101=""),"",E101&"-"&F101&"-"&G101&"-"&TEXT(COUNTIFS($E$2:E101,E101,$F$2:F101,F101,$G$2:G101,G101),"000")) -> COC-VAP-ALU-001 | B101: Cocina | C101: Vaporera | D101: Alumino | E101: =_xlfn.XLOOKUP(B101,Configuración!A:A,Configuración!B:B,"") -> COC | F101: {=IF($C101="","",_xlfn.XLOOKUP(1,(Configuración!D:D=$B101)*(Configuración!E:E=$C101),Configuración!F:F,""))} -> VAP | G101: =IF($D101="","",_xlfn.XLOOKUP($D101,Configuración!H:H,Configuración!I:I,"")) -> ALU | H101: Juego de vaporera de 3pz de aluminio 34cm maya | I101: Juego Maya | J101: El abuelo | K101: listo | L101: 2170 | M101: =MAX(CEILING(L101/4,10),100) -> 550 | N101: =M101*4 -> 2200 | O101: 3100 | P101: =IF($O101<Configuración!$B$7,"NO","SI") -> SI | Q101: =IF($P101="NO","NO APLICA",MAX(CEILING(($O101*(1-Configuración!$B$2))/Configuración!$B$3,Configuración!$B$6),Configuración!$B$5)) -> 310 | R101: =IF($Q101="NO APLICA","NO APLICA",$Q101*Configuración!$B$3) -> 2480 | S101: =IF($O101<Configuración!$B$8,"NO","SI") -> SI | T101: =IF($S101="NO","NO APLICA",MAX(CEILING(($O101*(1-Configuración!$B$2))/Configuración!$B$4,Configuración!$B$6),Configuración!$B$5)) -> 210 | U101: =IF($T101="NO APLICA","NO APLICA",$T101*Configuración!$B$4) -> 2520 | V101: =MAX(CEILING($O101/Configuración!$B$9,Configuración!$B$6),Configuración!$B$5) -> 100 | W101: Activo | X101: 46079
A102: =IF(OR(E102="",F102="",G102=""),"",E102&"-"&F102&"-"&G102&"-"&TEXT(COUNTIFS($E$2:E102,E102,$F$2:F102,F102,$G$2:G102,G102),"000")) -> COC-VAP-ACI-001 | B102: Cocina | C102: Vaporera | D102: Acero inoxidable | E102: =_xlfn.XLOOKUP(B102,Configuración!A:A,Configuración!B:B,"") -> COC | F102: {=IF($C102="","",_xlfn.XLOOKUP(1,(Configuración!D:D=$B102)*(Configuración!E:E=$C102),Configuración!F:F,""))} -> VAP | G102: =IF($D102="","",_xlfn.XLOOKUP($D102,Configuración!H:H,Configuración!I:I,"")) -> ACI | H102: Juego de vaporera Hanna 9pz | I102: Vaporera Hanna 9pz | J102: Acero inoxidable | K102: listo | L102: 5380 | M102: =MAX(CEILING(L102/4,10),100) -> 1350 | N102: =M102*4 -> 5400 | O102: 7690 | P102: =IF($O102<Configuración!$B$7,"NO","SI") -> SI | Q102: =IF($P102="NO","NO APLICA",MAX(CEILING(($O102*(1-Configuración!$B$2))/Configuración!$B$3,Configuración!$B$6),Configuración!$B$5)) -> 770 | R102: =IF($Q102="NO APLICA","NO APLICA",$Q102*Configuración!$B$3) -> 6160 | S102: =IF($O102<Configuración!$B$8,"NO","SI") -> SI | T102: =IF($S102="NO","NO APLICA",MAX(CEILING(($O102*(1-Configuración!$B$2))/Configuración!$B$4,Configuración!$B$6),Configuración!$B$5)) -> 520 | U102: =IF($T102="NO APLICA","NO APLICA",$T102*Configuración!$B$4) -> 6240 | V102: =MAX(CEILING($O102/Configuración!$B$9,Configuración!$B$6),Configuración!$B$5) -> 150 | W102: Activo | X102: 46079
A103: =IF(OR(E103="",F103="",G103=""),"",E103&"-"&F103&"-"&G103&"-"&TEXT(COUNTIFS($E$2:E103,E103,$F$2:F103,F103,$G$2:G103,G103),"000")) -> COC-BUD-ALU-003 | B103: Cocina | C103: Budinera | D103: Alumino | E103: =_xlfn.XLOOKUP(B103,Configuración!A:A,Configuración!B:B,"") -> COC | F103: {=IF($C103="","",_xlfn.XLOOKUP(1,(Configuración!D:D=$B103)*(Configuración!E:E=$C103),Configuración!F:F,""))} -> BUD | G103: =IF($D103="","",_xlfn.XLOOKUP($D103,Configuración!H:H,Configuración!I:I,"")) -> ALU | H103: Juego Vallarta 3pz | I103: Juego Vallarta 3pz | J103: El abuelo | K103: listo | L103: 2450 | M103: =MAX(CEILING(L103/4,10),100) -> 620 | N103: =M103*4 -> 2480 | O103: 3500 | P103: =IF($O103<Configuración!$B$7,"NO","SI") -> SI | Q103: =IF($P103="NO","NO APLICA",MAX(CEILING(($O103*(1-Configuración!$B$2))/Configuración!$B$3,Configuración!$B$6),Configuración!$B$5)) -> 350 | R103: =IF($Q103="NO APLICA","NO APLICA",$Q103*Configuración!$B$3) -> 2800 | S103: =IF($O103<Configuración!$B$8,"NO","SI") -> SI | T103: =IF($S103="NO","NO APLICA",MAX(CEILING(($O103*(1-Configuración!$B$2))/Configuración!$B$4,Configuración!$B$6),Configuración!$B$5)) -> 240 | U103: =IF($T103="NO APLICA","NO APLICA",$T103*Configuración!$B$4) -> 2880 | V103: =MAX(CEILING($O103/Configuración!$B$9,Configuración!$B$6),Configuración!$B$5) -> 100 | W103: Activo | X103: 46079
A104: =IF(OR(E104="",F104="",G104=""),"",E104&"-"&F104&"-"&G104&"-"&TEXT(COUNTIFS($E$2:E104,E104,$F$2:F104,F104,$G$2:G104,G104),"000")) -> PLA-LAV-PSL-001 | B104: Plásticos | C104: Lavadero | D104: Plástico | E104: =_xlfn.XLOOKUP(B104,Configuración!A:A,Configuración!B:B,"") -> PLA | F104: {=IF($C104="","",_xlfn.XLOOKUP(1,(Configuración!D:D=$B104)*(Configuración!E:E=$C104),Configuración!F:F,""))} -> LAV | G104: =IF($D104="","",_xlfn.XLOOKUP($D104,Configuración!H:H,Configuración!I:I,"")) -> PSL | H104: Lavadero infonavit café chico | I104: Lavadero infonavit café chico | J104: Placero | L104: 770 | M104: =MAX(CEILING(L104/4,10),100) -> 200 | N104: =M104*4 -> 800 | O104: 1100 | P104: =IF($O104<Configuración!$B$7,"NO","SI") -> NO | Q104: =IF($P104="NO","NO APLICA",MAX(CEILING(($O104*(1-Configuración!$B$2))/Configuración!$B$3,Configuración!$B$6),Configuración!$B$5)) -> NO APLICA | R104: =IF($Q104="NO APLICA","NO APLICA",$Q104*Configuración!$B$3) -> NO APLICA | S104: =IF($O104<Configuración!$B$8,"NO","SI") -> NO | T104: =IF($S104="NO","NO APLICA",MAX(CEILING(($O104*(1-Configuración!$B$2))/Configuración!$B$4,Configuración!$B$6),Configuración!$B$5)) -> NO APLICA | U104: =IF($T104="NO APLICA","NO APLICA",$T104*Configuración!$B$4) -> NO APLICA | V104: =MAX(CEILING($O104/Configuración!$B$9,Configuración!$B$6),Configuración!$B$5) -> 100 | W104: Activo | X104: 46079
A105: =IF(OR(E105="",F105="",G105=""),"",E105&"-"&F105&"-"&G105&"-"&TEXT(COUNTIFS($E$2:E105,E105,$F$2:F105,F105,$G$2:G105,G105),"000")) -> PLA-LAV-PSL-002 | B105: Plásticos | C105: Lavadero | D105: Plástico | E105: =_xlfn.XLOOKUP(B105,Configuración!A:A,Configuración!B:B,"") -> PLA | F105: {=IF($C105="","",_xlfn.XLOOKUP(1,(Configuración!D:D=$B105)*(Configuración!E:E=$C105),Configuración!F:F,""))} -> LAV | G105: =IF($D105="","",_xlfn.XLOOKUP($D105,Configuración!H:H,Configuración!I:I,"")) -> PSL | H105: Lavadero infonavit café grande | I105: Lavadero infonavit café grande | J105: Placero | L105: 910 | M105: =MAX(CEILING(L105/4,10),100) -> 230 | N105: =M105*4 -> 920 | O105: 1300 | P105: =IF($O105<Configuración!$B$7,"NO","SI") -> NO | Q105: =IF($P105="NO","NO APLICA",MAX(CEILING(($O105*(1-Configuración!$B$2))/Configuración!$B$3,Configuración!$B$6),Configuración!$B$5)) -> NO APLICA | R105: =IF($Q105="NO APLICA","NO APLICA",$Q105*Configuración!$B$3) -> NO APLICA | S105: =IF($O105<Configuración!$B$8,"NO","SI") -> NO | T105: =IF($S105="NO","NO APLICA",MAX(CEILING(($O105*(1-Configuración!$B$2))/Configuración!$B$4,Configuración!$B$6),Configuración!$B$5)) -> NO APLICA | U105: =IF($T105="NO APLICA","NO APLICA",$T105*Configuración!$B$4) -> NO APLICA | V105: =MAX(CEILING($O105/Configuración!$B$9,Configuración!$B$6),Configuración!$B$5) -> 100 | W105: Activo | X105: 46079
A106: =IF(OR(E106="",F106="",G106=""),"",E106&"-"&F106&"-"&G106&"-"&TEXT(COUNTIFS($E$2:E106,E106,$F$2:F106,F106,$G$2:G106,G106),"000")) -> PLA-LAV-PSL-003 | B106: Plásticos | C106: Lavadero | D106: Plástico | E106: =_xlfn.XLOOKUP(B106,Configuración!A:A,Configuración!B:B,"") -> PLA | F106: {=IF($C106="","",_xlfn.XLOOKUP(1,(Configuración!D:D=$B106)*(Configuración!E:E=$C106),Configuración!F:F,""))} -> LAV | G106: =IF($D106="","",_xlfn.XLOOKUP($D106,Configuración!H:H,Configuración!I:I,"")) -> PSL | H106: Lavadero infonavit café grande con pileta | I106: Lavadero infonavit café grande con pileta | J106: Placero | L106: 1610 | M106: =MAX(CEILING(L106/4,10),100) -> 410 | N106: =M106*4 -> 1640 | O106: 2300 | P106: =IF($O106<Configuración!$B$7,"NO","SI") -> SI | Q106: =IF($P106="NO","NO APLICA",MAX(CEILING(($O106*(1-Configuración!$B$2))/Configuración!$B$3,Configuración!$B$6),Configuración!$B$5)) -> 230 | R106: =IF($Q106="NO APLICA","NO APLICA",$Q106*Configuración!$B$3) -> 1840 | S106: =IF($O106<Configuración!$B$8,"NO","SI") -> NO | T106: =IF($S106="NO","NO APLICA",MAX(CEILING(($O106*(1-Configuración!$B$2))/Configuración!$B$4,Configuración!$B$6),Configuración!$B$5)) -> NO APLICA | U106: =IF($T106="NO APLICA","NO APLICA",$T106*Configuración!$B$4) -> NO APLICA | V106: =MAX(CEILING($O106/Configuración!$B$9,Configuración!$B$6),Configuración!$B$5) -> 100 | W106: Activo | X106: 46079
A107: =IF(OR(E107="",F107="",G107=""),"",E107&"-"&F107&"-"&G107&"-"&TEXT(COUNTIFS($E$2:E107,E107,$F$2:F107,F107,$G$2:G107,G107),"000")) -> LBL-LAV-PSL-001 | B107: Línea blanca | C107: Lavadora | D107: Plástico | E107: =_xlfn.XLOOKUP(B107,Configuración!A:A,Configuración!B:B,"") -> LBL | F107: {=IF($C107="","",_xlfn.XLOOKUP(1,(Configuración!D:D=$B107)*(Configuración!E:E=$C107),Configuración!F:F,""))} -> LAV | G107: =IF($D107="","",_xlfn.XLOOKUP($D107,Configuración!H:H,Configuración!I:I,"")) -> PSL | H107: Lavadora 11kg | I107: Lavadora 11kg | J107: Hisense | L107: 6230 | M107: =MAX(CEILING(L107/4,10),100) -> 1560 | N107: =M107*4 -> 6240 | O107: 8900 | P107: =IF($O107<Configuración!$B$7,"NO","SI") -> SI | Q107: =IF($P107="NO","NO APLICA",MAX(CEILING(($O107*(1-Configuración!$B$2))/Configuración!$B$3,Configuración!$B$6),Configuración!$B$5)) -> 890 | R107: =IF($Q107="NO APLICA","NO APLICA",$Q107*Configuración!$B$3) -> 7120 | S107: =IF($O107<Configuración!$B$8,"NO","SI") -> SI | T107: =IF($S107="NO","NO APLICA",MAX(CEILING(($O107*(1-Configuración!$B$2))/Configuración!$B$4,Configuración!$B$6),Configuración!$B$5)) -> 600 | U107: =IF($T107="NO APLICA","NO APLICA",$T107*Configuración!$B$4) -> 7200 | V107: =MAX(CEILING($O107/Configuración!$B$9,Configuración!$B$6),Configuración!$B$5) -> 180 | W107: Activo | X107: 46079
A108: =IF(OR(E108="",F108="",G108=""),"",E108&"-"&F108&"-"&G108&"-"&TEXT(COUNTIFS($E$2:E108,E108,$F$2:F108,F108,$G$2:G108,G108),"000")) -> LBL-LAV-PSL-002 | B108: Línea blanca | C108: Lavadora | D108: Plástico | E108: =_xlfn.XLOOKUP(B108,Configuración!A:A,Configuración!B:B,"") -> LBL | F108: {=IF($C108="","",_xlfn.XLOOKUP(1,(Configuración!D:D=$B108)*(Configuración!E:E=$C108),Configuración!F:F,""))} -> LAV | G108: =IF($D108="","",_xlfn.XLOOKUP($D108,Configuración!H:H,Configuración!I:I,"")) -> PSL | H108: Lavadora 13kg | I108: Lavadora 13kg | J108: ZMartech | L108: 9450 | M108: =MAX(CEILING(L108/4,10),100) -> 2370 | N108: =M108*4 -> 9480 | O108: 13500 | P108: =IF($O108<Configuración!$B$7,"NO","SI") -> SI | Q108: =IF($P108="NO","NO APLICA",MAX(CEILING(($O108*(1-Configuración!$B$2))/Configuración!$B$3,Configuración!$B$6),Configuración!$B$5)) -> 1350 | R108: =IF($Q108="NO APLICA","NO APLICA",$Q108*Configuración!$B$3) -> 10800 | S108: =IF($O108<Configuración!$B$8,"NO","SI") -> SI | T108: =IF($S108="NO","NO APLICA",MAX(CEILING(($O108*(1-Configuración!$B$2))/Configuración!$B$4,Configuración!$B$6),Configuración!$B$5)) -> 900 | U108: =IF($T108="NO APLICA","NO APLICA",$T108*Configuración!$B$4) -> 10800 | V108: =MAX(CEILING($O108/Configuración!$B$9,Configuración!$B$6),Configuración!$B$5) -> 260 | W108: Activo | X108: 46079
...

Sheet Cotizador
A1: Cotizador rápido (elige un producto)
A3: Producto (Nombre Comercial) | B3: Tripleta gigante 3pz
A4: Código | B4: =IFERROR(INDEX(Lista_Maestra!$A:$A,MATCH($B$3,Lista_Maestra!$H:$H,0)),) -> COC-ARR-ACI-003
A5: Categoría | B5: =IFERROR(INDEX(Lista_Maestra!$B:$B,MATCH($B$3,Lista_Maestra!$H:$H,0)),) -> Cocina
A6: Subcategoría | B6: =IFERROR(INDEX(Lista_Maestra!$C:$C,MATCH($B$3,Lista_Maestra!$H:$H,0)),) -> Arrocera
A7: Precio Contado | B7: =IFERROR(INDEX(Lista_Maestra!$L:$L,MATCH($B$3,Lista_Maestra!$H:$H,0)),) -> 2880
A8: Precio Crédito | B8: =IFERROR(INDEX(Lista_Maestra!$M:$M,MATCH($B$3,Lista_Maestra!$H:$H,0)),) -> 720
A10: Pago semanal 2 meses | B10: =IFERROR(INDEX(Lista_Maestra!$O:$O,MATCH($B$3,Lista_Maestra!$H:$H,0)),) -> 3600
A11: Total 2 meses | B11: =IFERROR(INDEX(Lista_Maestra!$P:$P,MATCH($B$3,Lista_Maestra!$H:$H,0)),) -> SI
A13: Pago semanal 3 meses | B13: =IFERROR(INDEX(Lista_Maestra!$R:$R,MATCH($B$3,Lista_Maestra!$H:$H,0)),) -> 2880
A14: Total 3 meses | B14: =IFERROR(INDEX(Lista_Maestra!$S:$S,MATCH($B$3,Lista_Maestra!$H:$H,0)),) -> SI
A16: Abono semanal (largo plazo) | B16: =IF($B$3="","", MAX(100,ROUNDUP(_xlfn.XLOOKUP($B$3,Tabla_Productos[Nombre_Comercial],Tabla_Productos[Precio_Credito],0)/52,0))) -> 100
A17: Semanas | B17: =IF($B$3="","",MIN(52,ROUNDUP(_xlfn.XLOOKUP($B$3,Tabla_Productos[Nombre_Comercial],Tabla_Productos[Precio_Credito],0)/B16,0))) -> 36
A18: Total largo plazo | B18: =IF($B$3="","",B16*B17) -> 3600

Sheet Inventario_Ruta
A1: Fecha | B1: Ruta | C1: Vendedor | D1: Código | E1: Producto | F1: Cantidad | G1: Tipo_Venta (Crédito/Contado) | H1: Cliente | I1: Notas

Sheet Historial_Cambios
A1: Fecha | B1: Código | C1: Producto | D1: Campo | E1: Antes | F1: Después | G1: Autorizó | H1: Motivo/Notas
